Workbook

Sheet Division Incrementos
A3: Incremento | B3: Porcentaje | C3: Porcentaje Acumulado | D3: Cantidad de Casos de Uso
A4: 1 | B4: =D4/$C$9 -> 0.23287671 | C4: =B4 -> 0.23287671 | D4: =COUNTIF('ProductSprint Backlog'!B:B, 1) -> 17
A5: 2 | B5: =D5/$C$9 -> 0.57534247 | C5: =C4+B5 -> 0.80821918 | D5: =COUNTIF('ProductSprint Backlog'!B:B, 2) +COUNTIF('ProductSprint Backlog'!B:B, 3) -> 42
A6: 3 | B6: =D6/$C$9 -> 0.16438356 | C6: =C5+B6 -> 0.97260274 | D6: =COUNTIF('ProductSprint Backlog'!B:B, 4) -> 12
A7: 4 | B7: =D7/$C$9 -> 0.02739726 | C7: =C6+B7 -> 1 | D7: =COUNTIF('ProductSprint Backlog'!B:B, 5) -> 2
E8: =SUM(D4:D7) -> 73
B9: Total CU | C9: =E8 -> 73

Sheet ProductSprint Backlog
B1: Product Backlog | I1: Estimado | K1: Real | M1: Proyecto
A2: Incremento | B2: Sprint | C2: Caso de Uso Extendido | D2: Actividades | E2: Responsable | F2: Estimar HH | G2: Estado | H2: Objetivo del Sprint | I2: Inicio | J2: Fin | K2: Inicio | L2: Fin | M2: HH Efectivas
A3: 1 | B3: 1 | C3: 8.1.1 Iniciando sesión en el sistema | D3: Diseñar y desarrollar el formulario de login. | E3: Geronimo Lopez | F3: 5 | G3: Terminado | H3: Realizar el diseño del login junto con sus conexiones y llamadas a la BD | I3: 45806 | J3: 45812 | K3: 45806 | L3: 45812 | M3: 4.5
D4: Implementar validación de formato y de credenciales contra base de datos. | E4: Geronimo Lopez | F4: 3 | G4: Terminado | H4: Aplicar las validaciones de formato para correo y pwd, junto con las de credenciales | I4: 45808 | J4: 45813 | K4: 45809 | L4: 45813 | M4: 2
D5: Redireccionar a vista según rol del usuario. | E5: Geronimo Lopez | F5: 2 | G5: Terminado | H5: Redireccionar a la vista del rol definido en la BD, inmediatamente después de ingresar | I5: 45810 | J5: 45811 | K5: 45810 | L5: 45812 | M5: 1.5
D6: Registrar evento de inicio de sesión en logs. | E6: Geronimo Lopez | F6: 2 | G6: Terminado | H6: Guardar en los logs de auditoría y en la info interna de usuarios, los registros de inicio de sesión | I6: 45813 | J6: 45818 | K6: 45813 | L6: 45816 | M6: 2
A8: 1 | B8: 1 | C8: 8.2.1 Recuperando contraseña olvidada | D8: Diseñar botón y flujo de “¿Olvidó su contraseña?”. | E8: Geronimo Lopez | F8: 1 | G8: Terminado | H8: Agregar al diseño del login la entrada al flujo del recuperacion de contraseña, y diseñar el flujo correspondiente | I8: 45810 | J8: 45812 | K8: 45811 | L8: 45812 | M8: 1.5
D9: Implementar validación de existencia del correo electrónico. | E9: Geronimo Lopez | F9: 2 | G9: Terminado | H9: Consultar en la BD si existe el correo de la persona que quiere recuperar contraseña | I9: 45810 | J9: 45812 | K9: 45812 | L9: 45813 | M9: 1
D10: Generar contraseña temporal de recuperación. | E10: Geronimo Lopez | F10: 3 | G10: Terminado | H10: Generar la password, que sea segura al ser una combinación de número, letras y caracteres especiales | I10: 45811 | J10: 45813 | K10: 45812 | L10: 45813 | M10: 3
D11: Enviar correo con la contraseña temporal. | E11: Geronimo Lopez | F11: 3 | G11: Terminado | H11: Diseñar y enviar el mensaje con la nueva contraseña al correo de la persona | I11: 45811 | J11: 45814 | K11: 45813 | L11: 45814 | M11: 3
D12: Validar contraseña y permitir ingreso con nueva contraseña. | E12: Geronimo Lopez | F12: 2 | G12: Terminado | H12: Realizar el cambio de pwd en la BD, y así validar cuando entre con la contraseña nueva | I12: 45812 | J12: 45814 | K12: 45814 | L12: 45815 | M12: 2
G13: Terminado
A14: 1 | B14: 1 | C14: 8.3.1 Expirando sesión tras 16 horas | D14: Registrar hora de inicio de sesión. | E14: Geronimo Lopez | F14: 2 | G14: Terminado | H14: Cuando inicie sesión la persona, tomar un timestamp del momento en que ingresó | I14: 45813 | J14: 45815 | K14: 45815 | L14: 45816 | M14: 1
D15: Implementar monitoreo de duración de sesión. | E15: Geronimo Lopez | F15: 4 | G15: Terminado | H15: Hacer que el sistema sea capaz de monitorear la sesión, sabiendo su tiempo de sesión actual | I15: 45813 | J15: 45815 | K15: 45815 | L15: 45817 | M15: 4.5
D16: Forzar cierre de sesión a las 16 horas. | E16: Geronimo Lopez | F16: 3 | G16: Terminado | H16: En base al monitoreo, forzar salida de sesión cuando se detecten las 16 horas | I16: 45815 | J16: 45818 | K16: 45816 | L16: 45818 | M16: 2
D17: Mostrar mensaje de expiración y redirigir al login. | E17: Geronimo Lopez | F17: 2 | G17: Terminado | H17: Cuando suceda lo anterior, mostrar un mensaje al usuario y redirigir a la vista de inicio de sesión | I17: 45817 | J17: 45818 | K17: 45818 | L17: 45819 | M17: 1
A19: 1 | B19: 1 | C19: 4.1.1 Registrando un nuevo equipo (Registro) | D19: Diseñar formulario de registro de equipo (marca, modelo, número de serie, tipo, descripción, cliente). | E19: Samir Saud | F19: 6 | G19: Terminado | H19: Diseñar el formulario del registro de equipo para el proceso de reparación, incluyendo los campos mencionados | I19: 45806 | J19: 45812 | K19: 45808 | L19: 45814 | M19: 5.5
D20: Validar que el número de serie no exista en la base de datos y los campos obligatorios. | E20: Samir Saud | F20: 3 | G20: Terminado | H20: Revisar el número de serie al momento de ser ingresado, para decidir si ir a CU 4.2.1, luego validar los otros campos | I20: 45808 | J20: 45810 | K20: 45809 | L20: 45810 | M20: 2
D21: Registrar equipo y asociarlo al cliente (usar cliente único durante entorno de desarrollo). | E21: Samir Saud | F21: 2 | G21: Terminado | H21: Registrar lo ingresado en el formulario en la base de datos, vinculando a un cliente en la BD (usar un cliente estático en desarrollo) | I21: 45811 | J21: 45814 | K21: 45811 | L21: 45812 | M21: 3
D22: Generar automáticamente una orden de trabajo inicial y almacenarla | E22: Samir Saud | F22: 3 | G22: Terminado | H22: Generar la orden de trabajo con los datos ingresados, almacenarlo en la BD | I22: 45812 | J22: 45814 | K22: 45812 | L22: 45814 | M22: 2
A24: 1 | B24: 1 | C24: 4.2.1 Generando orden de trabajo asociada a equipo ya ingresado (Registro) | D24: Detectar qué equipo ya está registrado al ingresar el número de serie. | E24: Samir Saud | F24: 1 | G24: Terminado | H24: Detectar que el número de serie ingresado ya existe en la BD | I24: 45808 | J24: 45809 | K24: 45808 | L24: 45809 | M24: 1
D25: Autocompletar datos del equipo y cliente al acceder, y notificar al usuario de que se encontró un equipo ya existente | E25: Samir Saud | F25: 3 | G25: Terminado | H25: Luego, consultar en la BD la info del equipo, utilizando los datos para autocompletar el formulario, para luego notificar al usuario de que ya existe el equipo | I25: 45808 | J25: 45812 | K25: 45810 | L25: 45812 | M25: 3.5
D26: Generar orden de trabajo (número único, estado “Recibido”) y almacenarla | E26: Samir Saud | F26: 2 | G26: Terminado | H26: Generar una nueva orden de trabajo con los datos ingresados, almacenarlo en la BD | I26: 45812 | J26: 45814 | K26: 45812 | L26: 45814 | M26: 1
A28: 1 | B28: 1 | C28: 4.3.1 Mostrando alerta de registro exitoso de equipo (Registro) | D28: Diseñar e implementar alerta visual (popup o toast) para mensaje de éxito. | E28: Samir Saud | F28: 1 | G28: Terminado | H28: Diseñar una alerta visual para cuando se genera la orden | I28: 45813 | J28: 45815 | K28: 45814 | L28: 45816 | M28: 1
D29: Incluir en el mensaje: “Equipo registrado exitosamente” y “Orden de trabajo generada con número: [ID]” y otra información relevante. | E29: Samir Saud | F29: 1 | G29: Terminado | H29: Agregar la información pertinente al equipo y la orden de trabajo en la alerta visual diseñada | I29: 45813 | J29: 45815 | K29: 45815 | L29: 45815 | M29: 0.5
D30: Asegurar que la alerta se active automáticamente tras registrar equipo y generar orden. | E30: Samir Saud | F30: 1 | G30: Terminado | H30: Luego de 4.1.1 o 4.2.1, hacer que el sistema muestre la alerta diseñada | I30: 45814 | J30: 45815 | K30: 45815 | L30: 45816 | M30: 1
A32: 1 | B32: 1 | C32: 2.1.1 Visualizando información principal de los equipos (Laboratorio) | D32: Crear vista para técnicos del laboratorio con listado de equipos | E32: Bastian Benitez | F32: 3 | G32: Terminado | H32: Crear la vista genera de Gestión de Órdenes del personal de laboratorio | I32: 45807 | J32: 45810 | K32: 45807 | L32: 45810 | M32: 3
D33: Mostrar campos: marca, modelo, cliente, estado, prioridad, fecha de ingreso. | E33: Bastian Benitez | F33: 2 | G33: Terminado | H33: Incluir en esa vista la información del equipo y orden más importante para el rol | I33: 45809 | J33: 45811 | K33: 45809 | L33: 45810 | M33: 2
D34: Mostrar los botones de interacción: ver informe, ver cotizacion, crear cotización, ver historial de equipo y crear informe | E34: Bastian Benitez | F34: 2 | G34: Terminado | H34: Agregar los botones de interacción posibles, solo visualmente, la funcionalidad se integra cuando las secciones correspondientes estén listas | I34: 45810 | J34: 45811 | K34: 45810 | L34: 45811 | M34: 1
D35: Asegurar actualización en tiempo real o con recarga controlada | E35: Bastian Benitez | F35: 2 | G35: Terminado | H35: Implementar que el sistema actualice en tiempo real (o pseudoreal, con un timer corto) los cambio en la BD de los equipos y órdenes | I35: 45810 | J35: 45811 | K35: 45810 | L35: 45811 | M35: 1
A37: 1 | B37: 1 | C37: 3.1.1 Visualizando información principal de los equipos (Recepción) | D37: Crear vista para recepción con listado de equipos | E37: Bastian Benitez | F37: 3 | G37: Terminado | H37: Crear la vista genera de Gestión de Órdenes del personal de laboratorio | I37: 45810 | J37: 45811 | K37: 45810 | L37: 45810 | M37: 2
D38: Mostrar marca, modelo, cliente, estado actual, prioridad y fecha. | E38: Bastian Benitez | F38: 2 | G38: Terminado | H38: Incluir en esa vista la información del equipo y orden más importante para el rol | I38: 45810 | J38: 45811 | K38: 45810 | L38: 45811 | M38: 1
D39: Mostrar los botones de interacción: ver informe, ver cotización, aprobar cotizacion, rechazar cotizacion y ver historial de equipo | E39: Bastian Benitez | F39: 2 | G39: Terminado | H39: Agregar los botones de interacción posibles, solo visualmente, la funcionalidad se integra cuando las secciones correspondientes estén listas | I39: 45811 | J39: 45812 | K39: 45811 | L39: 45811 | M39: 1
D40: Asegurar actualización en tiempo real o con recarga controlada | E40: Bastian Benitez | F40: 2 | G40: Terminado | H40: Implementar que el sistema actualice en tiempo real (o pseudoreal, con un timer corto) los cambio en la BD de los equipos y órdenes | I40: 45812 | J40: 45813 | K40: 45811 | L40: 45811 | M40: 1
A42: 1 | B42: 1 | C42: 2.2.1 Visualizando Informe Técnico de un Equipo (Laboratorio) | D42: Habilitar opción “Visualizar Informe Técnico” solo si el informe existe. | E42: Manuel Vidal | F42: 1 | G42: Terminado | H42: Activar el botón cuando el campo de la BD de la orden tenga un informe relacionado | I42: 45815 | J42: 45817 | K42: 45816 | L42: 45817 | M42: 1
D43: Mostrar contenido del informe en vista interna legible. | E43: Manuel Vidal | F43: 3 | G43: Terminado | H43: Al presionar el botón, aparezca una vista del informe técnico (no necesariamente PDF), con los datos guardados en la BD | I43: 45816 | J43: 45818 | K43: 45816 | L43: 45818 | M43: 4
A45: 1 | B45: 1 | C45: 2.2.2 Visualizando Cotización de un Equipo(Laboratorio) | D45: Habilitar opción “Visualizar Cotizacion” solo si la Cotización existe. | E45: Eliam Rivas | F45: 1 | G45: Terminado | H45: Activar el botón cuando el campo de la BD de la orden tenga una cotización relacionada | I45: 45815 | J45: 45817 | K45: 45815 | L45: 45817 | M45: 1
D46: Mostrar contenido de la cotización en vista interna legible. | E46: Eliam Rivas | F46: 3 | G46: Terminado | H46: Al presionar el botón, aparezca una vista de cotización (no necesariamente PDF), con los datos guardados en la BD | I46: 45816 | J46: 45818 | K46: 45816 | L46: 45818 | M46: 3
A48: 1 | B48: 1 | C48: 3.2.1 Visualizando Informe Técnico de un equipo (Recepción) | D48: Habilitar opción “Visualizar Informe Técnico” solo si el informe existe. | E48: Manuel Vidal | F48: 1 | G48: Terminado | H48: Activar el botón cuando el campo de la BD de la orden tenga un informe relacionado | I48: 45815 | J48: 45817 | K48: 45816 | L48: 45816 | M48: 0.5
D49: Mostrar contenido del informe en vista interna legible. | E49: Manuel Vidal | F49: 3 | G49: Terminado | H49: Al presionar el botón, aparezca una vista del informe técnico (no necesariamente PDF), con los datos guardados en la BD | I49: 45816 | J49: 45818 | K49: 45818 | L49: 45819 | M49: 3
A51: 1 | B51: 1 | C51: 3.2.2 Visualizando Cotización de un equipo (Recepción) | D51: Habilitar opción “Visualizar Cotizacion” solo si la Cotización existe. | E51: Eliam Rivas | F51: 1 | G51: Terminado | H51: Activar el botón cuando el campo de la BD de la orden tenga una cotización relacionada | I51: 45815 | J51: 45817 | K51: 45815 | L51: 45816 | M51: 0.5
D52: Mostrar contenido de la cotización en vista interna legible. | E52: Eliam Rivas | F52: 3 | G52: Terminado | H52: Al presionar el botón, aparezca una vista de cotización (no necesariamente PDF), con los datos guardados en la BD | I52: 45816 | J52: 45818 | K52: 45816 | L52: 45817 | M52: 2
A54: 1 | B54: 1 | C54: 6.1.1 Generando informe de reparación | D54: Diseñar el formulario de creación de informe técnico. | E54: Manuel Vidal | F54: 5 | G54: Terminado | H54: Realizar el diseño del formulario para el informe técnico, incluyendo los campos necesarios | I54: 45806 | J54: 45812 | K54: 45808 | L54: 45814 | M54: 6
D55: Autocompletar datos del equipo y cliente al acceder. | E55: Manuel Vidal | F55: 3 | G55: Terminado | H55: Autocompletar los datos del equipo, orden y cliente correspondiente, a través de una consulta en la BD | I55: 45810 | J55: 45813 | K55: 45812 | L55: 45815 | M55: 4
D56: Permitir ingresar diagnóstico, trabajos realizados, repuestos y observaciones en un formato intuitivo | E56: Manuel Vidal | F56: 2 | G56: Terminado | H56: Asegurar que el diseño del formulario sea intuitivo y fácil de implementar para las medidas de evaluación y el ingreso en la tabla de piezas utilizadas | I56: 45810 | J56: 45812 | K56: 45812 | L56: 45814 | M56: 2
D57: Validar campos obligatorios antes de continuar e implementar mensaje de error cuando falle | E57: Manuel Vidal | F57: 2 | G57: Terminado | H57: Implementar validación en los campos y diseñar alertas de error, aplicándolas cuando la validación falle en algún campo | I57: 45811 | J57: 45813 | K57: 45814 | L57: 45815 | M57: 2
D58: Mostrar vista previa del informe técnico | E58: Manuel Vidal | F58: 2 | G58: Terminado | H58: Luego de completar y antes de pasar a la etapa de "Confirmación (6.3.1)", mostrar una vista previa del informe técnico con los datos ingresados | I58: 45812 | J58: 45813 | K58: 45814 | L58: 45816 | M58: 3
A60: 1 | B60: 1 | C60: 6.3.1 Confirmando generación de informe | D60: Implementar el botón de confirmación y luego de presionarlo solicitar confirmación del usuario. | E60: Manuel Vidal | F60: 1 | G60: Terminado | H60: Implementar el flujo de confirmar la generación del informe, primero con un botón, que abre otra confirmación (ej modal), que pregunta "Estas seguro" o algo similar | I60: 45813 | J60: 45814 | K60: 45815 | L60: 45816 | M60: 1
D61: Bloquear el informe para futuras ediciones. | E61: Manuel Vidal | F61: 2 | G61: Terminado | H61: En la realidad, el informe existe en forma de borrador, luego de confirmar ya no puede ser modificado | I61: 45813 | J61: 45814 | K61: 45815 | L61: 45815 | M61: 1
D62: Generar el informe, almacenar en la base de datos y asociarlo a la orden correspondiente | E62: Manuel Vidal | F62: 2 | G62: Terminado | H62: Generar el informe en la base de datos si por alguna razón no existe, asociarlo a la orden correspondiente | I62: 45814 | J62: 45816 | K62: 45815 | L62: 45816 | M62: 2
D63: Cambiar estado de la orden de trabajo a “Espera de Retiro”. | E63: Manuel Vidal | F63: 1 | G63: Terminado | H63: Cambiar el estado de la orden de trabajo asociada | I63: 45814 | J63: 45815 | K63: 45815 | L63: 45815 | M63: 1
D64: Registrar la fecha y hora de confirmación junto con la actividad en los logs. | E64: Manuel Vidal | F64: 2 | G64: Terminado | H64: Registrar el evento como un registro de auditoría en la bd | I64: 45815 | J64: 45816 | K64: 45816 | L64: 45817 | M64: 1
D65: Mostrar mensaje de éxito | E65: Manuel Vidal | F65: 1 | G65: Terminado | H65: Diseñar y mostrar el mensaje de éxito, dando información sobre el informe creado | I65: 45815 | J65: 45816 | K65: 45816 | L65: 45817 | M65: 1
A67: 1 | B67: 1 | C67: 5.1.1 Generando nueva cotización | D67: Diseñar el formulario de creación de cotización. | E67: Eliam Rivas | F67: 5 | G67: Terminado | H67: Realizar el diseño del formulario para el informe técnico, incluyendo los campos necesarios | I67: 45806 | J67: 45812 | K67: 45806 | L67: 45811 | M67: 5
D68: Autocompletar datos del equipo y cliente al acceder a la sección. | E68: Eliam Rivas | F68: 3 | G68: Terminado | H68: Autocompletar los datos del equipo, orden y cliente correspondiente, a través de una consulta en la BD | I68: 45810 | J68: 45813 | K68: 45810 | L68: 45812 | M68: 3.5
D69: Permitir ingresar: mano de obra, repuestos, observaciones, condiciones. | E69: Eliam Rivas | F69: 2 | G69: Terminado | H69: Asegurar que el diseño del formulario sea intuitivo y fácil de implementar los precios, observaciones, y la tabla de repuestos | I69: 45810 | J69: 45812 | K69: 45810 | L69: 45812 | M69: 2.5
D70: Validar que no exista cotización previa activa. | E70: Eliam Rivas | F70: 1 | G70: Terminado | H70: Revisar que la orden de trabajo tenga una cotización previa conectada a ella, evitando sobrescribir información útil. | I70: 45811 | J70: 45813 | K70: 45812 | L70: 45813 | M70: 1
D71: Validar campos obligatorios y formatos, e implementar mensaje de error cuando falle. | E71: Eliam Rivas | F71: 2 | G71: Terminado | H71: Implementar validación en los campos y diseñar alertas de error, aplicándolas cuando la validación falle en algún campo | I71: 45811 | J71: 45813 | K71: 45811 | L71: 45812 | M71: 1.5
D72: Mostrar vista previa de la cotización | E72: Eliam Rivas | F72: 2 | G72: Terminado | H72: Luego de completar y antes de pasar a la etapa de "Confirmación (5.4.1)", mostrar una vista previa del informe técnico con los datos ingresados | I72: 45812 | J72: 45813 | K72: 45812 | L72: 45813 | M72: 1.5
A74: 1 | B74: 1 | C74: 5.4.1 Confirmando creación de cotización | D74: Implementar el botón de confirmación y luego de presionarlo solicitar confirmación del usuario. | E74: Eliam Rivas | F74: 1 | G74: Terminado | H74: Implementar el flujo de confirmar la generación de cotización, primero con un botón, que abre otra confirmación (ej modal), que pregunta "Estas seguro" o algo similar | I74: 45813 | J74: 45814 | K74: 45814 | L74: 45814 | M74: 0.5
D75: Generar la cotización, almacenar en la base de datos y asociarlo a la orden correspondiente | E75: Eliam Rivas | F75: 2 | G75: Terminado | H75: Generar la cotización en la base de datos si por alguna razón no existe, asociarlo a la orden correspondiente | I75: 45813 | J75: 45814 | K75: 45814 | L75: 45815 | M75: 1.5
D76: Cambiar estado de la orden de trabajo a “Cotización Enviada”. | E76: Eliam Rivas | F76: 1 | G76: Terminado | H76: Cambiar el estado de la orden de trabajo asociada | I76: 45814 | J76: 45816 | K76: 45814 | L76: 45814 | M76: 0.5
D77: Registrar la fecha y hora de confirmación junto con la actividad en los logs. | E77: Eliam Rivas | F77: 2 | G77: Terminado | H77: Registrar el evento como un registro de auditoría en la bd | I77: 45814 | J77: 45815 | K77: 45814 | L77: 45815 | M77: 1.5
D78: Mostrar mensaje de éxito | E78: Eliam Rivas | F78: 1 | G78: Terminado | H78: Diseñar y mostrar el mensaje de éxito, dando información sobre la cotización creada | I78: 45815 | J78: 45816 | K78: 45815 | L78: 45815 | M78: 0.5
A80: 1 | B80: 1 | C80: 4.4.1 Enviando correo de notificación a laboratorio (Registro) | D80: Detectar evento de registro exitoso de equipo y generación de orden de trabajo. | E80: Bastian Benitez | F80: 2 | G80: Terminado | H80: Hacer que el sistema reconozca la creación de una nueva orden de trabajo | I80: 45813 | J80: 45815 | K80: 45814 | L80: 45815 | M80: 1.5
D81: Recopilar automáticamente los siguientes datos: fecha, cliente, modelo, marca. id orden de trabajo y descripción del problema | E81: Bastian Benitez | F81: 1 | G81: Terminado | H81: Recopilar aparte la información importante de la orden para laboratorio | I81: 45813 | J81: 45815 | K81: 45814 | L81: 45815 | M81: 1
D82: Generar correo con asunto estándar (“Nueva Orden de Trabajo Generada”) y redactar el cuerpo con los datos anteriores y mensaje dirigido al laboratorio. | E82: Bastian Benitez | F82: 2 | G82: Terminado | H82: En base a la información anterior, preparar el cuerpo y asunto del correo | I82: 45814 | J82: 45816 | K82: 45814 | L82: 45816 | M82: 2.5
D83: Enviar el correo a los destinatarios correspondientes del laboratorio. | E83: Bastian Benitez | F83: 1 | G83: Terminado | H83: Efectivamente enviar el correo, actualmente usamos Resend en entorno de desarrollo pero creo que puede cambiar si usamos la SMTP de Toscanini | I83: 45815 | J83: 45817 | K83: 45815 | L83: 45817 | M83: 1
D84: Registrar el evento de envío en el log del sistema para trazabilidad. | E84: Bastian Benitez | F84: 1 | G84: Terminado | H84: Registrar el evento en los logs, en específico el timestamp de cuando se mandó, y los detalles del envío | I84: 45816 | J84: 45818 | K84: 45816 | L84: 45817 | M84: 0.5
A86: 2 | B86: 2 | C86: 3.3.1 Aprobando cotización de un equipo | D86: Implementar botón para la aprobación de la cotización, y que esté habilitado sólo si la cotización la orden de trabajo asociada está en estado "Cotización Enviada" | E86: Samir Saud | F86: 1 | G86: Terminado | H86: Implementar el botón para la aprobación después de la comunicación del cliente, asegurando que esté habilitado para las órdenes válidas | I86: 45875 | J86: 45879 | K86: 45881 | L86: 45882 | M86: 0.5
D87: Implementar la confirmación de la aprobación de la cotización, que puede ser en forma de modal | E87: Samir Saud | F87: 1 | G87: Terminado | H87: Diseñar la interfaz de la confirmación | I87: 45875 | J87: 45879 | K87: 45881 | L87: 45882 | M87: 1
D88: Cambiar el estado de la orden de trabajo a "En reparación" | E88: Samir Saud | F88: 1 | G88: Terminado | H88: Asegurar que se realice el cambio de estado en la BD | I88: 45875 | J88: 45879 | K88: 45881 | L88: 45882 | M88: 0.5
D89: Registrar el evento en el log del sistema | E89: Samir Saud | F89: 1 | G89: Terminado | H89: Registrar en los logs para auditoría | I89: 45875 | J89: 45879 | K89: 45881 | L89: 45882 | M89: 1
D90: Diseñar mensaje de confirmación luego de la realización de la acción de forma correcta, y su implementación | E90: Samir Saud | F90: 1 | G90: Terminado | H90: Mostrar un mensaje que confirme al usuario que el proceso fue exitoso | I90: 45875 | J90: 45879 | K90: 45881 | L90: 45882 | M90: 0.5
A91: 2 | B91: 2 | C91: 3.3.2 Rechazando cotización de un equipo | D91: Implementar botón para el rechazo de la cotización, y que esté habilitado sólo si la cotización la orden de trabajo asociada está en estado "Cotización Enviada" | E91: Samir Saud | F91: 1 | G91: Terminado | H91: Implementar el botón para el rechazo después de la comunicación del cliente, asegurando que esté habilitado para las órdenes válidas | I91: 45880 | J91: 45883 | K91: 45883 | L91: 45884 | M91: 0.5
D92: Implementar la confirmación del rechazo de la cotización, que puede ser en forma de modal. Además, incluir un campo opcional para ingresar el motivo del rechazo | E92: Samir Saud | F92: 1 | G92: Terminado | H92: Diseñar la interfaz del rechazo, incluyendo campos opcionales de motivos | I92: 45880 | J92: 45883 | K92: 45883 | L92: 45884 | M92: 0.5
D93: Cambiar el estado de la orden de trabajo a "Cotización Rechazada" | E93: Samir Saud | F93: 1 | G93: Terminado | H93: Asegurar que se realice el cambio de estado en la BD | I93: 45880 | J93: 45883 | K93: 45883 | L93: 45884 | M93: 0.5
D94: Registrar el evento en el log del sistema | E94: Samir Saud | F94: 1 | G94: Terminado | H94: Registrar en los logs para auditoría | I94: 45880 | J94: 45883 | K94: 45883 | L94: 45884 | M94: 0.5
D95: Diseñar mensaje de confirmación luego de la realización de la acción de forma correcta, y su implementación | E95: Samir Saud | F95: 1 | G95: Terminado | H95: Mostrar un mensaje que confirme al usuario que el proceso fue exitoso | I95: 45880 | J95: 45883 | K95: 45883 | L95: 45884 | M95: 0.5
A97: 2 | B97: 2 | C97: 2.2.4 Declarando Equipo como No Reparable (Laboratorio) | D97: Implementar botón para la declaración de no reparable, y que esté habilitado sólo si la cotización la orden de trabajo asociada está en estado "Recibido" | E97: Samir Saud | F97: 1 | G97: Terminado | H97: Implementar el botón para la declaración luego del análisis del Técnico, asegurando que esté habilitado para las órdenes válidas | I97: 45883 | J97: 45886 | K97: 45886 | L97: 45887 | M97: 0.5
D98: Implementar la confirmación de la declaración de abandono, que puede ser en forma de modal. Además, incluir un campo opcional para ingresar justificación o comentarios | E98: Samir Saud | F98: 1 | G98: Terminado | H98: Diseñar la interfaz del rechazo, incluyendo campos opcionales de motivos | I98: 45883 | J98: 45886 | K98: 45886 | L98: 45887 | M98: 1
D99: Cambiar el estado de la orden de trabajo a "No Reparable" | E99: Samir Saud | F99: 1 | G99: Terminado | H99: Asegurar que se realice el cambio de estado en la BD | I99: 45883 | J99: 45886 | K99: 45886 | L99: 45887 | M99: 0.5
D100: Registrar el evento en el log del sistema | E100: Samir Saud | F100: 1 | G100: Terminado | H100: Registrar en los logs para auditoría | I100: 45883 | J100: 45886 | K100: 45886 | L100: 45887 | M100: 1
D101: Diseñar mensaje de confirmación luego de la realización de la acción de forma correcta, y su implementación | E101: Samir Saud | F101: 1 | G101: Terminado | H101: Mostrar un mensaje que confirme al usuario que el proceso fue exitoso | I101: 45883 | J101: 45886 | K101: 45886 | L101: 45887 | M101: 0.5
A102: 2 | B102: 2 | C102: 3.2.4 Declarando Equipo como Abandonado (Recepción) | D102: Implementar botón para la declaración de abandono, y que esté habilitado sólo si la cotización la orden de trabajo asociada NO está en estado "Recibido" y ha pasado el tiempo necesario desde su creación original | E102: Samir Saud | F102: 1 | G102: Terminado | H102: Implementar el botón para la declaración luego del análisis del usuario, asegurando que esté habilitado para las órdenes válidas | I102: 45887 | J102: 45889 | K102: 45887 | L102: 45888 | M102: 0.5
D103: Implementar la confirmación de la declaración de abandono, que puede ser en forma de modal. Además, incluir un campo opcional para ingresar justificación o comentarios | E103: Samir Saud | F103: 1 | G103: Terminado | H103: Diseñar la interfaz del rechazo, incluyendo campos opcionales de motivos | I103: 45887 | J103: 45889 | K103: 45887 | L103: 45888 | M103: 0.5
D104: Cambiar el estado de la orden de trabajo a "Abandonado" | E104: Samir Saud | F104: 1 | G104: Terminado | H104: Asegurar que se realice el cambio de estado en la BD | I104: 45887 | J104: 45889 | K104: 45887 | L104: 45888 | M104: 0.5
D105: Registrar el evento en el log del sistema | E105: Samir Saud | F105: 1 | G105: Terminado | H105: Registrar en los logs para auditoría | I105: 45887 | J105: 45889 | K105: 45887 | L105: 45888 | M105: 0.5
D106: Diseñar mensaje de confirmación luego de la realización de la acción de forma correcta, y su implementación | E106: Samir Saud | F106: 1 | G106: Terminado | H106: Mostrar un mensaje que confirme al usuario que el proceso fue exitoso | I106: 45887 | J106: 45889 | K106: 45887 | L106: 45888 | M106: 0.5
A108: 2 | B108: 2 | C108: 2.5.1 Notificando por cotización no realizada | D108: Implementar revision de ordenes de trabajo en estado "Recibido", cuales NO tengan cotización asociada en 2 días hábiles desde su creación | E108: Francisco Torres | F108: 1 | G108: Terminado | H108: Implementar una revisión periódica de los datos de la BD, buscando si existen órdenes que cumplan los requerimientos | I108: 45875 | J108: 45879 | K108: 45887 | L108: 45888 | M108: 2
D109: Diseñar notificación de cotización no realizada, debe incluir: tiempo transcurrido, identificación del equipo/orden de trabajo, fecha de ingreso | E109: Francisco Torres | F109: 1 | G109: Terminado | H109: Diseñar la notificación con la información de utilidad para el técnico, con el objetivo que tenga la información necesaria para considerar qué hacer | I109: 45875 | J109: 45879 | K109: 45887 | L109: 45888 | M109: 1
D110: Mostrar la notificación en la interfaz del usuario si su rol es técnico de laboratorio | E110: Francisco Torres | F110: 1 | G110: Terminado | H110: Asegurar que aparezca la notificación en la interfaz del sistema | I110: 45875 | J110: 45879 | K110: 45887 | L110: 45888 | M110: 1
A111: 2 | B111: 2 | C111: 2.5.2 Notificando por cotización no enviada | D111: Implementar revision de ordenes de trabajo en estado "Recibido", las cuales tengan 3 días hábiles de antigüedad. | E111: Francisco Torres | F111: 1 | G111: Terminado | H111: Implementar una revisión periódica de los datos de la BD, buscando si existen órdenes que cumplan los requerimientos | I111: 45880 | J111: 45883 | K111: 45889 | L111: 45889 | M111: 1
D112: Diseñar notificación de cotización no enviada, debe incluir: tiempo de retraso, identificación del equipo/orden de trabajo, fecha de ingreso | E112: Francisco Torres | F112: 1 | G112: Terminado | H112: Diseñar la notificación con la información de utilidad para el técnico, con el objetivo que tenga la información necesaria para considerar qué hacer | I112: 45880 | J112: 45883 | K112: 45889 | L112: 45889 | M112: 1
D113: Mostrar la notificación en la interfaz del usuario si su rol es técnico de laboratorio | E113: Francisco Torres | F113: 1 | G113: Terminado | H113: Asegurar que aparezca la notificación en la interfaz del sistema | I113: 45880 | J113: 45883 | K113: 45889 | L113: 45889 | M113: 1
A114: 2 | B114: 2 | C114: 2.5.3 Notificando por alta prioridad no atendida | D114: Implementar revision de ordenes de trabajo en estado "Recibido" con prioridad "Alta", cuales NO tengan cotización asociada o cambio de estado en 24 horas hábiles desde su creación. | E114: Francisco Torres | F114: 1 | G114: Terminado | H114: Implementar una revisión periódica de los datos de la BD, buscando si existen órdenes que cumplan los requerimientos | I114: 45884 | J114: 45889 | K114: 45889 | L114: 45890 | M114: 1
D115: Diseñar notificación de recordatorio de atención, debe incluir: tiempo transcurrido, identificación del equipo/orden de trabajo, fecha de ingreso | E115: Francisco Torres | F115: 1 | G115: Terminado | H115: Diseñar la notificación con la información de utilidad para el técnico, con el objetivo que tenga la información necesaria para considerar qué hacer | I115: 45884 | J115: 45889 | K115: 45889 | L115: 45890 | M115: 1
D116: Mostrar la notificación en la interfaz del usuario si su rol es técnico de laboratorio | E116: Francisco Torres | F116: 1 | G116: Terminado | H116: Asegurar que aparezca la notificación en la interfaz del sistema | I116: 45884 | J116: 45889 | K116: 45889 | L116: 45890 | M116: 1
A118: 2 | B118: 2 | C118: 3.2.3 Visualizando Historial de un equipo (Recepción) | D118: Implementar botón de "Visualizar Historial" en la vista de los equipos | E118: Eliam Rivas | F118: 1 | G118: Terminado | H118: Implementar el botón en la interfaz, en la vista de equipos | I118: 45875 | J118: 45885 | K118: 45876 | L118: 45880 | M118: 1
D119: Diseñar vista del historial del equipo, mostrando: fecha de ingreso, las órdenes de trabajo asociadas junto con sus cotizaciones, informes técnicos y cambios de estado | E119: Eliam Rivas | F119: 2 | G119: Terminado | H119: Diseñar la vista, tiene que incluir el pasado del equipo, con todos los documentos asociados. De alguna manera debe quedar comprensible | I119: 45875 | J119: 45885 | K119: 45876 | L119: 45880 | M119: 1
...

Sheet BurnUp-Down INC 4
A1: Periodo de Sprint 1 | D1: 45961 | E1: 45968 | F1: =E1-D1 -> 7
A3: BurnUp
B4: 45961 | C4: 45962 | D4: 45963 | E4: 45964 | F4: 45965 | G4: 45966 | H4: 45967 | I4: 45968 | J4: 45969
B5: Día 1 | C5: Día 2 | D5: Día 3 | E5: Día 4 | F5: Día 5 | G5: Día 6 | H5: Día 7 | I5: Día 8 | J5: Día 9
A6: Esfuerzo Real Acumulado (HH) | B6: 0 | C6: ='Registro de HH INC4'!C11 -> 0 | D6: ='Registro de HH INC4'!D11 -> 1 | E6: ='Registro de HH INC4'!E11 -> 1.5 | F6: ='Registro de HH INC4'!F11 -> 2.5 | G6: ='Registro de HH INC4'!G11 -> 4 | H6: ='Registro de HH INC4'!H11 -> 4.5 | I6: ='Registro de HH INC4'!I11 -> 4.5 | J6: ='Registro de HH INC4'!J11 -> 4.5
A7: Esfuerzo Estimado Acumulado (HH) | B7: 0 | C7: =SUM('Aux Esfuerzo Estimado INC4 SPT5'!B3:B1000) -> 0.5 | D7: =SUM('Aux Esfuerzo Estimado INC4 SPT5'!C3:C1000)+C7 -> 1 | E7: =SUM('Aux Esfuerzo Estimado INC4 SPT5'!D3:D1000)+D7 -> 2.5 | F7: =SUM('Aux Esfuerzo Estimado INC4 SPT5'!E3:E1000)+E7 -> 3.5 | G7: =SUM('Aux Esfuerzo Estimado INC4 SPT5'!F3:F1000)+F7 -> 4 | H7: =SUM('Aux Esfuerzo Estimado INC4 SPT5'!G3:G1000)+G7 -> 4.5 | I7: =SUM('Aux Esfuerzo Estimado INC4 SPT5'!H3:H1000)+H7 -> 5.5 | J7: =SUM('Aux Esfuerzo Estimado INC4 SPT5'!I3:I1000)+I7 -> 5.5
A9: BurnDown
B10: 45961 | C10: 45962 | D10: 45963 | E10: 45964 | F10: 45965 | G10: 45966 | H10: 45967 | I10: 45968 | J10: 45969
B11: Día 1 | C11: Día 2 | D11: Día 3 | E11: Día 4 | F11: Día 5 | G11: Día 6 | H11: Día 7 | I11: Día 8 | J11: Día 9
A12: Esfuerzo Real Restante (HH) | B12: =SUM('ProductSprint Backlog'!M282:M289) -> 4.5 | C12: =B12-'Registro de HH INC4'!C10 -> 4.5 | D12: =C12-'Registro de HH INC4'!D10 -> 3.5 | E12: =D12-'Registro de HH INC4'!E10 -> 3 | F12: =E12-'Registro de HH INC4'!F10 -> 2 | G12: =F12-'Registro de HH INC4'!G10 -> 0.5 | H12: =G12-'Registro de HH INC4'!H10 -> 0 | I12: =H12-'Registro de HH INC4'!I10 -> 0 | J12: =I12-'Registro de HH INC4'!J10 -> 0
A13: Esfuerzo Estimado Restante (HH) | B13: =SUM('ProductSprint Backlog'!F282:F289) -> 5.5 | C13: =B13-SUM('Aux Esfuerzo Estimado INC4 SPT5'!B3:B1000) -> 5 | D13: =C13-SUM('Aux Esfuerzo Estimado INC4 SPT5'!C3:C1000) -> 4.5 | E13: =D13-SUM('Aux Esfuerzo Estimado INC4 SPT5'!D3:D1000) -> 3 | F13: =E13-SUM('Aux Esfuerzo Estimado INC4 SPT5'!E3:E1000) -> 2 | G13: =F13-SUM('Aux Esfuerzo Estimado INC4 SPT5'!F3:F1000) -> 1.5 | H13: =G13-SUM('Aux Esfuerzo Estimado INC4 SPT5'!G3:G1000) -> 1 | I13: =H13-SUM('Aux Esfuerzo Estimado INC4 SPT5'!H3:H1000) -> 0 | J13: =I13-SUM('Aux Esfuerzo Estimado INC4 SPT5'!I3:I1000) -> 0

Sheet Registro de HH INC4
A1: Sprint 2
B2: Dia 0 | C2: Dia 1 | D2: Dia 2 | E2: Dia 3 | F2: Dia 4 | G2: Dia 5 | H2: Dia 6 | I2: Dia 7 | J2: Dia 8 | K2: Dia 9
A3: Persona | C3: 45961 | D3: 45962 | E3: 45963 | F3: 45964 | G3: 45965 | H3: 45966 | I3: 45967 | J3: 45968 | K3: 45969
A4: Bastian | D4: 1 | E4: 0.5 | F4: 1 | G4: 1.5 | H4: 0.5
A5: Eliam
A6: Geronimo
A7: Manuel
A8: Samir
A9: Francisco
A10: Total Dia | C10: =SUM(C4:C9) -> 0 | D10: =SUM(D4:D9) -> 1 | E10: =SUM(E4:E9) -> 0.5 | F10: =SUM(F4:F9) -> 1 | G10: =SUM(G4:G9) -> 1.5 | H10: =SUM(H4:H9) -> 0.5 | I10: =SUM(I4:I9) -> 0 | J10: =SUM(J4:J9) -> 0 | K10: =SUM(K4:K9) -> 0
A11: Total Acumulado | C11: =SUM(C4:C9) -> 0 | D11: =SUM(D4:D9)+C11 -> 1 | E11: =SUM(E4:E9)+D11 -> 1.5 | F11: =SUM(F4:F9)+E11 -> 2.5 | G11: =SUM(G4:G9)+F11 -> 4 | H11: =SUM(H4:H9)+G11 -> 4.5 | I11: =SUM(I4:I9)+H11 -> 4.5 | J11: =SUM(J4:J9)+I11 -> 4.5 | K11: =SUM(K4:K9)+J11 -> 4.5

Sheet Tabla de Esfuerzo INC4 SPT5
B2: 45961 | C2: 45962 | D2: 45963 | E2: 45964 | F2: 45965 | G2: 45966 | H2: 45967 | I2: 45968
A3: Tareas Pendientes | B3: =COUNTIFS('ProductSprint Backlog'!$D$282:$D$289,"<>",'ProductSprint Backlog'!$L$282:$L$289,">"&DATEVALUE(B2)) -> 0 | C3: =COUNTIFS('ProductSprint Backlog'!$D$282:$D$289,"<>",'ProductSprint Backlog'!$L$282:$L$289,">"&DATEVALUE(C2)) -> 0 | D3: =COUNTIFS('ProductSprint Backlog'!$D$282:$D$289,"<>",'ProductSprint Backlog'!$L$282:$L$289,">"&DATEVALUE(D2)) -> 0 | E3: =COUNTIFS('ProductSprint Backlog'!$D$282:$D$289,"<>",'ProductSprint Backlog'!$L$282:$L$289,">"&DATEVALUE(E2)) -> 0 | F3: =COUNTIFS('ProductSprint Backlog'!$D$282:$D$289,"<>",'ProductSprint Backlog'!$L$282:$L$289,">"&DATEVALUE(F2)) -> 0 | G3: =COUNTIFS('ProductSprint Backlog'!$D$282:$D$289,"<>",'ProductSprint Backlog'!$L$282:$L$289,">"&DATEVALUE(G2)) -> 0 | H3: =COUNTIFS('ProductSprint Backlog'!$D$282:$D$289,"<>",'ProductSprint Backlog'!$L$282:$L$289,">"&DATEVALUE(H2)) -> 0 | I3: =COUNTIFS('ProductSprint Backlog'!$D$282:$D$289,"<>",'ProductSprint Backlog'!$L$282:$L$289,">"&DATEVALUE(I2)) -> 0
A6: Tarea | B6: Esfuerzo
A7: Diseñar botones e interfaces del proceso de eliminación | B7: =IF('ProductSprint Backlog'!$L282>B$2,'ProductSprint Backlog'!$M282,0) -> 0.5 | C7: =IF('ProductSprint Backlog'!$L282>C$2,'ProductSprint Backlog'!$M282,0) -> 0.5 | D7: =IF('ProductSprint Backlog'!$L282>D$2,'ProductSprint Backlog'!$M282,0) -> 0 | E7: =IF('ProductSprint Backlog'!$L282>E$2,'ProductSprint Backlog'!$M282,0) -> 0 | F7: =IF('ProductSprint Backlog'!$L282>F$2,'ProductSprint Backlog'!$M282,0) -> 0 | G7: =IF('ProductSprint Backlog'!$L282>G$2,'ProductSprint Backlog'!$M282,0) -> 0 | H7: =IF('ProductSprint Backlog'!$L282>H$2,'ProductSprint Backlog'!$M282,0) -> 0 | I7: =IF('ProductSprint Backlog'!$L282>I$2,'ProductSprint Backlog'!$M282,0) -> 0
A8: Mostrar el modal de confirmación, incluyendo el campo de detalles. | B8: =IF('ProductSprint Backlog'!$L283>B$2,'ProductSprint Backlog'!$M283,0) -> 0.5 | C8: =IF('ProductSprint Backlog'!$L283>C$2,'ProductSprint Backlog'!$M283,0) -> 0.5 | D8: =IF('ProductSprint Backlog'!$L283>D$2,'ProductSprint Backlog'!$M283,0) -> 0 | E8: =IF('ProductSprint Backlog'!$L283>E$2,'ProductSprint Backlog'!$M283,0) -> 0 | F8: =IF('ProductSprint Backlog'!$L283>F$2,'ProductSprint Backlog'!$M283,0) -> 0 | G8: =IF('ProductSprint Backlog'!$L283>G$2,'ProductSprint Backlog'!$M283,0) -> 0 | H8: =IF('ProductSprint Backlog'!$L283>H$2,'ProductSprint Backlog'!$M283,0) -> 0 | I8: =IF('ProductSprint Backlog'!$L283>I$2,'ProductSprint Backlog'!$M283,0) -> 0
A9: Asegurar el registro en auditoria para mantener la trazabilidad de las acciones | B9: =IF('ProductSprint Backlog'!$L284>B$2,'ProductSprint Backlog'!$M284,0) -> 1 | C9: =IF('ProductSprint Backlog'!$L284>C$2,'ProductSprint Backlog'!$M284,0) -> 1 | D9: =IF('ProductSprint Backlog'!$L284>D$2,'ProductSprint Backlog'!$M284,0) -> 1 | E9: =IF('ProductSprint Backlog'!$L284>E$2,'ProductSprint Backlog'!$M284,0) -> 0 | F9: =IF('ProductSprint Backlog'!$L284>F$2,'ProductSprint Backlog'!$M284,0) -> 0 | G9: =IF('ProductSprint Backlog'!$L284>G$2,'ProductSprint Backlog'!$M284,0) -> 0 | H9: =IF('ProductSprint Backlog'!$L284>H$2,'ProductSprint Backlog'!$M284,0) -> 0 | I9: =IF('ProductSprint Backlog'!$L284>I$2,'ProductSprint Backlog'!$M284,0) -> 0
A10: Diseñar y mostrar un mensaje de éxito al completar el proceso | B10: =IF('ProductSprint Backlog'!$L285>B$2,'ProductSprint Backlog'!$M285,0) -> 0.5 | C10: =IF('ProductSprint Backlog'!$L285>C$2,'ProductSprint Backlog'!$M285,0) -> 0.5 | D10: =IF('ProductSprint Backlog'!$L285>D$2,'ProductSprint Backlog'!$M285,0) -> 0.5 | E10: =IF('ProductSprint Backlog'!$L285>E$2,'ProductSprint Backlog'!$M285,0) -> 0.5 | F10: =IF('ProductSprint Backlog'!$L285>F$2,'ProductSprint Backlog'!$M285,0) -> 0 | G10: =IF('ProductSprint Backlog'!$L285>G$2,'ProductSprint Backlog'!$M285,0) -> 0 | H10: =IF('ProductSprint Backlog'!$L285>H$2,'ProductSprint Backlog'!$M285,0) -> 0 | I10: =IF('ProductSprint Backlog'!$L285>I$2,'ProductSprint Backlog'!$M285,0) -> 0
A11: Diseñar botones e interfaces del proceso de eliminación | B11: =IF('ProductSprint Backlog'!$L286>B$2,'ProductSprint Backlog'!$M286,0) -> 0.5 | C11: =IF('ProductSprint Backlog'!$L286>C$2,'ProductSprint Backlog'!$M286,0) -> 0.5 | D11: =IF('ProductSprint Backlog'!$L286>D$2,'ProductSprint Backlog'!$M286,0) -> 0.5 | E11: =IF('ProductSprint Backlog'!$L286>E$2,'ProductSprint Backlog'!$M286,0) -> 0.5 | F11: =IF('ProductSprint Backlog'!$L286>F$2,'ProductSprint Backlog'!$M286,0) -> 0 | G11: =IF('ProductSprint Backlog'!$L286>G$2,'ProductSprint Backlog'!$M286,0) -> 0 | H11: =IF('ProductSprint Backlog'!$L286>H$2,'ProductSprint Backlog'!$M286,0) -> 0 | I11: =IF('ProductSprint Backlog'!$L286>I$2,'ProductSprint Backlog'!$M286,0) -> 0
A12: Mostrar el modal de confirmación, incluyendo el campo de detalles. | B12: =IF('ProductSprint Backlog'!$L287>B$2,'ProductSprint Backlog'!$M287,0) -> 0.5 | C12: =IF('ProductSprint Backlog'!$L287>C$2,'ProductSprint Backlog'!$M287,0) -> 0.5 | D12: =IF('ProductSprint Backlog'!$L287>D$2,'ProductSprint Backlog'!$M287,0) -> 0.5 | E12: =IF('ProductSprint Backlog'!$L287>E$2,'ProductSprint Backlog'!$M287,0) -> 0.5 | F12: =IF('ProductSprint Backlog'!$L287>F$2,'ProductSprint Backlog'!$M287,0) -> 0.5 | G12: =IF('ProductSprint Backlog'!$L287>G$2,'ProductSprint Backlog'!$M287,0) -> 0 | H12: =IF('ProductSprint Backlog'!$L287>H$2,'ProductSprint Backlog'!$M287,0) -> 0 | I12: =IF('ProductSprint Backlog'!$L287>I$2,'ProductSprint Backlog'!$M287,0) -> 0
A13: Asegurar el registro en auditoria para mantener la trazabilidad de las acciones | B13: =IF('ProductSprint Backlog'!$L288>B$2,'ProductSprint Backlog'!$M288,0) -> 0.5 | C13: =IF('ProductSprint Backlog'!$L288>C$2,'ProductSprint Backlog'!$M288,0) -> 0.5 | D13: =IF('ProductSprint Backlog'!$L288>D$2,'ProductSprint Backlog'!$M288,0) -> 0.5 | E13: =IF('ProductSprint Backlog'!$L288>E$2,'ProductSprint Backlog'!$M288,0) -> 0.5 | F13: =IF('ProductSprint Backlog'!$L288>F$2,'ProductSprint Backlog'!$M288,0) -> 0.5 | G13: =IF('ProductSprint Backlog'!$L288>G$2,'ProductSprint Backlog'!$M288,0) -> 0 | H13: =IF('ProductSprint Backlog'!$L288>H$2,'ProductSprint Backlog'!$M288,0) -> 0 | I13: =IF('ProductSprint Backlog'!$L288>I$2,'ProductSprint Backlog'!$M288,0) -> 0
A14: Diseñar y mostrar un mensaje de éxito al completar el proceso | B14: =IF('ProductSprint Backlog'!$L289>B$2,'ProductSprint Backlog'!$M289,0) -> 0.5 | C14: =IF('ProductSprint Backlog'!$L289>C$2,'ProductSprint Backlog'!$M289,0) -> 0.5 | D14: =IF('ProductSprint Backlog'!$L289>D$2,'ProductSprint Backlog'!$M289,0) -> 0.5 | E14: =IF('ProductSprint Backlog'!$L289>E$2,'ProductSprint Backlog'!$M289,0) -> 0.5 | F14: =IF('ProductSprint Backlog'!$L289>F$2,'ProductSprint Backlog'!$M289,0) -> 0.5 | G14: =IF('ProductSprint Backlog'!$L289>G$2,'ProductSprint Backlog'!$M289,0) -> 0.5 | H14: =IF('ProductSprint Backlog'!$L289>H$2,'ProductSprint Backlog'!$M289,0) -> 0 | I14: =IF('ProductSprint Backlog'!$L289>I$2,'ProductSprint Backlog'!$M289,0) -> 0

Sheet Aux Esfuerzo Estimado INC4 SPT5
B1: Dia 1 | C1: Dia 2 | D1: Dia 3 | E1: Dia 4 | F1: Dia 5 | G1: Dia 6 | H1: Dia 7 | I1: Dia 8 | J1: Dia 9
B2: 45961 | C2: 45962 | D2: 45963 | E2: 45964 | F2: 45965 | G2: 45966 | H2: 45967 | I2: 45968 | J2: 45969 | R2: <------------------ | S2: Modificar esto para que calcular los esfuersos en el tiempo
B3: {=_xlfn.IFS('ProductSprint Backlog'!$F3="", "", AND('ProductSprint Backlog'!$J3>B$2,'ProductSprint Backlog'!$I3<=B$2), 'ProductSprint Backlog'!$F3 / MAX(1, 'ProductSprint Backlog'!$J3-'ProductSprint Backlog'!$I3), AND('ProductSprint Backlog'!$J3=B$2,'ProductSprint Backlog'!$I3=B$2), 'ProductSprint Backlog'!$F3, TRUE, 0)} -> 0 | C3: {=_xlfn.IFS('ProductSprint Backlog'!$F3="", "", AND('ProductSprint Backlog'!$J3>C$2,'ProductSprint Backlog'!$I3<=C$2), 'ProductSprint Backlog'!$F3 / MAX(1, 'ProductSprint Backlog'!$J3-'ProductSprint Backlog'!$I3), AND('ProductSprint Backlog'!$J3=C$2,'ProductSprint Backlog'!$I3=C$2), 'ProductSprint Backlog'!$F3, TRUE, 0)} -> 0 | D3: {=_xlfn.IFS('ProductSprint Backlog'!$F3="", "", AND('ProductSprint Backlog'!$J3>D$2,'ProductSprint Backlog'!$I3<=D$2), 'ProductSprint Backlog'!$F3 / MAX(1, 'ProductSprint Backlog'!$J3-'ProductSprint Backlog'!$I3), AND('ProductSprint Backlog'!$J3=D$2,'ProductSprint Backlog'!$I3=D$2), 'ProductSprint Backlog'!$F3, TRUE, 0)} -> 0 | E3: {=_xlfn.IFS('ProductSprint Backlog'!$F3="", "", AND('ProductSprint Backlog'!$J3>E$2,'ProductSprint Backlog'!$I3<=E$2), 'ProductSprint Backlog'!$F3 / MAX(1, 'ProductSprint Backlog'!$J3-'ProductSprint Backlog'!$I3), AND('ProductSprint Backlog'!$J3=E$2,'ProductSprint Backlog'!$I3=E$2), 'ProductSprint Backlog'!$F3, TRUE, 0)} -> 0 | F3: {=_xlfn.IFS('ProductSprint Backlog'!$F3="", "", AND('ProductSprint Backlog'!$J3>F$2,'ProductSprint Backlog'!$I3<=F$2), 'ProductSprint Backlog'!$F3 / MAX(1, 'ProductSprint Backlog'!$J3-'ProductSprint Backlog'!$I3), AND('ProductSprint Backlog'!$J3=F$2,'ProductSprint Backlog'!$I3=F$2), 'ProductSprint Backlog'!$F3, TRUE, 0)} -> 0 | G3: {=_xlfn.IFS('ProductSprint Backlog'!$F3="", "", AND('ProductSprint Backlog'!$J3>G$2,'ProductSprint Backlog'!$I3<=G$2), 'ProductSprint Backlog'!$F3 / MAX(1, 'ProductSprint Backlog'!$J3-'ProductSprint Backlog'!$I3), AND('ProductSprint Backlog'!$J3=G$2,'ProductSprint Backlog'!$I3=G$2), 'ProductSprint Backlog'!$F3, TRUE, 0)} -> 0 | H3: {=_xlfn.IFS('ProductSprint Backlog'!$F3="", "", AND('ProductSprint Backlog'!$J3>H$2,'ProductSprint Backlog'!$I3<=H$2), 'ProductSprint Backlog'!$F3 / MAX(1, 'ProductSprint Backlog'!$J3-'ProductSprint Backlog'!$I3), AND('ProductSprint Backlog'!$J3=H$2,'ProductSprint Backlog'!$I3=H$2), 'ProductSprint Backlog'!$F3, TRUE, 0)} -> 0 | I3: {=_xlfn.IFS('ProductSprint Backlog'!$F3="", "", AND('ProductSprint Backlog'!$J3>I$2,'ProductSprint Backlog'!$I3<=I$2), 'ProductSprint Backlog'!$F3 / MAX(1, 'ProductSprint Backlog'!$J3-'ProductSprint Backlog'!$I3), AND('ProductSprint Backlog'!$J3=I$2,'ProductSprint Backlog'!$I3=I$2), 'ProductSprint Backlog'!$F3, TRUE, 0)} -> 0 | J3: {=_xlfn.IFS('ProductSprint Backlog'!$F3="", "", AND('ProductSprint Backlog'!$J3>J$2,'ProductSprint Backlog'!$I3<=J$2), 'ProductSprint Backlog'!$F3 / MAX(1, 'ProductSprint Backlog'!$J3-'ProductSprint Backlog'!$I3), AND('ProductSprint Backlog'!$J3=J$2,'ProductSprint Backlog'!$I3=J$2), 'ProductSprint Backlog'!$F3, TRUE, 0)} -> 0
B4: {=_xlfn.IFS('ProductSprint Backlog'!$F4="", "", AND('ProductSprint Backlog'!$J4>B$2,'ProductSprint Backlog'!$I4<=B$2), 'ProductSprint Backlog'!$F4 / MAX(1, 'ProductSprint Backlog'!$J4-'ProductSprint Backlog'!$I4), AND('ProductSprint Backlog'!$J4=B$2,'ProductSprint Backlog'!$I4=B$2), 'ProductSprint Backlog'!$F4, TRUE, 0)} -> 0 | C4: {=_xlfn.IFS('ProductSprint Backlog'!$F4="", "", AND('ProductSprint Backlog'!$J4>C$2,'ProductSprint Backlog'!$I4<=C$2), 'ProductSprint Backlog'!$F4 / MAX(1, 'ProductSprint Backlog'!$J4-'ProductSprint Backlog'!$I4), AND('ProductSprint Backlog'!$J4=C$2,'ProductSprint Backlog'!$I4=C$2), 'ProductSprint Backlog'!$F4, TRUE, 0)} -> 0 | D4: {=_xlfn.IFS('ProductSprint Backlog'!$F4="", "", AND('ProductSprint Backlog'!$J4>D$2,'ProductSprint Backlog'!$I4<=D$2), 'ProductSprint Backlog'!$F4 / MAX(1, 'ProductSprint Backlog'!$J4-'ProductSprint Backlog'!$I4), AND('ProductSprint Backlog'!$J4=D$2,'ProductSprint Backlog'!$I4=D$2), 'ProductSprint Backlog'!$F4, TRUE, 0)} -> 0 | E4: {=_xlfn.IFS('ProductSprint Backlog'!$F4="", "", AND('ProductSprint Backlog'!$J4>E$2,'ProductSprint Backlog'!$I4<=E$2), 'ProductSprint Backlog'!$F4 / MAX(1, 'ProductSprint Backlog'!$J4-'ProductSprint Backlog'!$I4), AND('ProductSprint Backlog'!$J4=E$2,'ProductSprint Backlog'!$I4=E$2), 'ProductSprint Backlog'!$F4, TRUE, 0)} -> 0 | F4: {=_xlfn.IFS('ProductSprint Backlog'!$F4="", "", AND('ProductSprint Backlog'!$J4>F$2,'ProductSprint Backlog'!$I4<=F$2), 'ProductSprint Backlog'!$F4 / MAX(1, 'ProductSprint Backlog'!$J4-'ProductSprint Backlog'!$I4), AND('ProductSprint Backlog'!$J4=F$2,'ProductSprint Backlog'!$I4=F$2), 'ProductSprint Backlog'!$F4, TRUE, 0)} -> 0 | G4: {=_xlfn.IFS('ProductSprint Backlog'!$F4="", "", AND('ProductSprint Backlog'!$J4>G$2,'ProductSprint Backlog'!$I4<=G$2), 'ProductSprint Backlog'!$F4 / MAX(1, 'ProductSprint Backlog'!$J4-'ProductSprint Backlog'!$I4), AND('ProductSprint Backlog'!$J4=G$2,'ProductSprint Backlog'!$I4=G$2), 'ProductSprint Backlog'!$F4, TRUE, 0)} -> 0 | H4: {=_xlfn.IFS('ProductSprint Backlog'!$F4="", "", AND('ProductSprint Backlog'!$J4>H$2,'ProductSprint Backlog'!$I4<=H$2), 'ProductSprint Backlog'!$F4 / MAX(1, 'ProductSprint Backlog'!$J4-'ProductSprint Backlog'!$I4), AND('ProductSprint Backlog'!$J4=H$2,'ProductSprint Backlog'!$I4=H$2), 'ProductSprint Backlog'!$F4, TRUE, 0)} -> 0 | I4: {=_xlfn.IFS('ProductSprint Backlog'!$F4="", "", AND('ProductSprint Backlog'!$J4>I$2,'ProductSprint Backlog'!$I4<=I$2), 'ProductSprint Backlog'!$F4 / MAX(1, 'ProductSprint Backlog'!$J4-'ProductSprint Backlog'!$I4), AND('ProductSprint Backlog'!$J4=I$2,'ProductSprint Backlog'!$I4=I$2), 'ProductSprint Backlog'!$F4, TRUE, 0)} -> 0 | J4: {=_xlfn.IFS('ProductSprint Backlog'!$F4="", "", AND('ProductSprint Backlog'!$J4>J$2,'ProductSprint Backlog'!$I4<=J$2), 'ProductSprint Backlog'!$F4 / MAX(1, 'ProductSprint Backlog'!$J4-'ProductSprint Backlog'!$I4), AND('ProductSprint Backlog'!$J4=J$2,'ProductSprint Backlog'!$I4=J$2), 'ProductSprint Backlog'!$F4, TRUE, 0)} -> 0
B5: {=_xlfn.IFS('ProductSprint Backlog'!$F5="", "", AND('ProductSprint Backlog'!$J5>B$2,'ProductSprint Backlog'!$I5<=B$2), 'ProductSprint Backlog'!$F5 / MAX(1, 'ProductSprint Backlog'!$J5-'ProductSprint Backlog'!$I5), AND('ProductSprint Backlog'!$J5=B$2,'ProductSprint Backlog'!$I5=B$2), 'ProductSprint Backlog'!$F5, TRUE, 0)} -> 0 | C5: {=_xlfn.IFS('ProductSprint Backlog'!$F5="", "", AND('ProductSprint Backlog'!$J5>C$2,'ProductSprint Backlog'!$I5<=C$2), 'ProductSprint Backlog'!$F5 / MAX(1, 'ProductSprint Backlog'!$J5-'ProductSprint Backlog'!$I5), AND('ProductSprint Backlog'!$J5=C$2,'ProductSprint Backlog'!$I5=C$2), 'ProductSprint Backlog'!$F5, TRUE, 0)} -> 0 | D5: {=_xlfn.IFS('ProductSprint Backlog'!$F5="", "", AND('ProductSprint Backlog'!$J5>D$2,'ProductSprint Backlog'!$I5<=D$2), 'ProductSprint Backlog'!$F5 / MAX(1, 'ProductSprint Backlog'!$J5-'ProductSprint Backlog'!$I5), AND('ProductSprint Backlog'!$J5=D$2,'ProductSprint Backlog'!$I5=D$2), 'ProductSprint Backlog'!$F5, TRUE, 0)} -> 0 | E5: {=_xlfn.IFS('ProductSprint Backlog'!$F5="", "", AND('ProductSprint Backlog'!$J5>E$2,'ProductSprint Backlog'!$I5<=E$2), 'ProductSprint Backlog'!$F5 / MAX(1, 'ProductSprint Backlog'!$J5-'ProductSprint Backlog'!$I5), AND('ProductSprint Backlog'!$J5=E$2,'ProductSprint Backlog'!$I5=E$2), 'ProductSprint Backlog'!$F5, TRUE, 0)} -> 0 | F5: {=_xlfn.IFS('ProductSprint Backlog'!$F5="", "", AND('ProductSprint Backlog'!$J5>F$2,'ProductSprint Backlog'!$I5<=F$2), 'ProductSprint Backlog'!$F5 / MAX(1, 'ProductSprint Backlog'!$J5-'ProductSprint Backlog'!$I5), AND('ProductSprint Backlog'!$J5=F$2,'ProductSprint Backlog'!$I5=F$2), 'ProductSprint Backlog'!$F5, TRUE, 0)} -> 0 | G5: {=_xlfn.IFS('ProductSprint Backlog'!$F5="", "", AND('ProductSprint Backlog'!$J5>G$2,'ProductSprint Backlog'!$I5<=G$2), 'ProductSprint Backlog'!$F5 / MAX(1, 'ProductSprint Backlog'!$J5-'ProductSprint Backlog'!$I5), AND('ProductSprint Backlog'!$J5=G$2,'ProductSprint Backlog'!$I5=G$2), 'ProductSprint Backlog'!$F5, TRUE, 0)} -> 0 | H5: {=_xlfn.IFS('ProductSprint Backlog'!$F5="", "", AND('ProductSprint Backlog'!$J5>H$2,'ProductSprint Backlog'!$I5<=H$2), 'ProductSprint Backlog'!$F5 / MAX(1, 'ProductSprint Backlog'!$J5-'ProductSprint Backlog'!$I5), AND('ProductSprint Backlog'!$J5=H$2,'ProductSprint Backlog'!$I5=H$2), 'ProductSprint Backlog'!$F5, TRUE, 0)} -> 0 | I5: {=_xlfn.IFS('ProductSprint Backlog'!$F5="", "", AND('ProductSprint Backlog'!$J5>I$2,'ProductSprint Backlog'!$I5<=I$2), 'ProductSprint Backlog'!$F5 / MAX(1, 'ProductSprint Backlog'!$J5-'ProductSprint Backlog'!$I5), AND('ProductSprint Backlog'!$J5=I$2,'ProductSprint Backlog'!$I5=I$2), 'ProductSprint Backlog'!$F5, TRUE, 0)} -> 0 | J5: {=_xlfn.IFS('ProductSprint Backlog'!$F5="", "", AND('ProductSprint Backlog'!$J5>J$2,'ProductSprint Backlog'!$I5<=J$2), 'ProductSprint Backlog'!$F5 / MAX(1, 'ProductSprint Backlog'!$J5-'ProductSprint Backlog'!$I5), AND('ProductSprint Backlog'!$J5=J$2,'ProductSprint Backlog'!$I5=J$2), 'ProductSprint Backlog'!$F5, TRUE, 0)} -> 0
B6: {=_xlfn.IFS('ProductSprint Backlog'!$F6="", "", AND('ProductSprint Backlog'!$J6>B$2,'ProductSprint Backlog'!$I6<=B$2), 'ProductSprint Backlog'!$F6 / MAX(1, 'ProductSprint Backlog'!$J6-'ProductSprint Backlog'!$I6), AND('ProductSprint Backlog'!$J6=B$2,'ProductSprint Backlog'!$I6=B$2), 'ProductSprint Backlog'!$F6, TRUE, 0)} -> 0 | C6: {=_xlfn.IFS('ProductSprint Backlog'!$F6="", "", AND('ProductSprint Backlog'!$J6>C$2,'ProductSprint Backlog'!$I6<=C$2), 'ProductSprint Backlog'!$F6 / MAX(1, 'ProductSprint Backlog'!$J6-'ProductSprint Backlog'!$I6), AND('ProductSprint Backlog'!$J6=C$2,'ProductSprint Backlog'!$I6=C$2), 'ProductSprint Backlog'!$F6, TRUE, 0)} -> 0 | D6: {=_xlfn.IFS('ProductSprint Backlog'!$F6="", "", AND('ProductSprint Backlog'!$J6>D$2,'ProductSprint Backlog'!$I6<=D$2), 'ProductSprint Backlog'!$F6 / MAX(1, 'ProductSprint Backlog'!$J6-'ProductSprint Backlog'!$I6), AND('ProductSprint Backlog'!$J6=D$2,'ProductSprint Backlog'!$I6=D$2), 'ProductSprint Backlog'!$F6, TRUE, 0)} -> 0 | E6: {=_xlfn.IFS('ProductSprint Backlog'!$F6="", "", AND('ProductSprint Backlog'!$J6>E$2,'ProductSprint Backlog'!$I6<=E$2), 'ProductSprint Backlog'!$F6 / MAX(1, 'ProductSprint Backlog'!$J6-'ProductSprint Backlog'!$I6), AND('ProductSprint Backlog'!$J6=E$2,'ProductSprint Backlog'!$I6=E$2), 'ProductSprint Backlog'!$F6, TRUE, 0)} -> 0 | F6: {=_xlfn.IFS('ProductSprint Backlog'!$F6="", "", AND('ProductSprint Backlog'!$J6>F$2,'ProductSprint Backlog'!$I6<=F$2), 'ProductSprint Backlog'!$F6 / MAX(1, 'ProductSprint Backlog'!$J6-'ProductSprint Backlog'!$I6), AND('ProductSprint Backlog'!$J6=F$2,'ProductSprint Backlog'!$I6=F$2), 'ProductSprint Backlog'!$F6, TRUE, 0)} -> 0 | G6: {=_xlfn.IFS('ProductSprint Backlog'!$F6="", "", AND('ProductSprint Backlog'!$J6>G$2,'ProductSprint Backlog'!$I6<=G$2), 'ProductSprint Backlog'!$F6 / MAX(1, 'ProductSprint Backlog'!$J6-'ProductSprint Backlog'!$I6), AND('ProductSprint Backlog'!$J6=G$2,'ProductSprint Backlog'!$I6=G$2), 'ProductSprint Backlog'!$F6, TRUE, 0)} -> 0 | H6: {=_xlfn.IFS('ProductSprint Backlog'!$F6="", "", AND('ProductSprint Backlog'!$J6>H$2,'ProductSprint Backlog'!$I6<=H$2), 'ProductSprint Backlog'!$F6 / MAX(1, 'ProductSprint Backlog'!$J6-'ProductSprint Backlog'!$I6), AND('ProductSprint Backlog'!$J6=H$2,'ProductSprint Backlog'!$I6=H$2), 'ProductSprint Backlog'!$F6, TRUE, 0)} -> 0 | I6: {=_xlfn.IFS('ProductSprint Backlog'!$F6="", "", AND('ProductSprint Backlog'!$J6>I$2,'ProductSprint Backlog'!$I6<=I$2), 'ProductSprint Backlog'!$F6 / MAX(1, 'ProductSprint Backlog'!$J6-'ProductSprint Backlog'!$I6), AND('ProductSprint Backlog'!$J6=I$2,'ProductSprint Backlog'!$I6=I$2), 'ProductSprint Backlog'!$F6, TRUE, 0)} -> 0 | J6: {=_xlfn.IFS('ProductSprint Backlog'!$F6="", "", AND('ProductSprint Backlog'!$J6>J$2,'ProductSprint Backlog'!$I6<=J$2), 'ProductSprint Backlog'!$F6 / MAX(1, 'ProductSprint Backlog'!$J6-'ProductSprint Backlog'!$I6), AND('ProductSprint Backlog'!$J6=J$2,'ProductSprint Backlog'!$I6=J$2), 'ProductSprint Backlog'!$F6, TRUE, 0)} -> 0
B7: {=_xlfn.IFS('ProductSprint Backlog'!$F7="", "", AND('ProductSprint Backlog'!$J7>B$2,'ProductSprint Backlog'!$I7<=B$2), 'ProductSprint Backlog'!$F7 / MAX(1, 'ProductSprint Backlog'!$J7-'ProductSprint Backlog'!$I7), AND('ProductSprint Backlog'!$J7=B$2,'ProductSprint Backlog'!$I7=B$2), 'ProductSprint Backlog'!$F7, TRUE, 0)} | C7: {=_xlfn.IFS('ProductSprint Backlog'!$F7="", "", AND('ProductSprint Backlog'!$J7>C$2,'ProductSprint Backlog'!$I7<=C$2), 'ProductSprint Backlog'!$F7 / MAX(1, 'ProductSprint Backlog'!$J7-'ProductSprint Backlog'!$I7), AND('ProductSprint Backlog'!$J7=C$2,'ProductSprint Backlog'!$I7=C$2), 'ProductSprint Backlog'!$F7, TRUE, 0)} | D7: {=_xlfn.IFS('ProductSprint Backlog'!$F7="", "", AND('ProductSprint Backlog'!$J7>D$2,'ProductSprint Backlog'!$I7<=D$2), 'ProductSprint Backlog'!$F7 / MAX(1, 'ProductSprint Backlog'!$J7-'ProductSprint Backlog'!$I7), AND('ProductSprint Backlog'!$J7=D$2,'ProductSprint Backlog'!$I7=D$2), 'ProductSprint Backlog'!$F7, TRUE, 0)} | E7: {=_xlfn.IFS('ProductSprint Backlog'!$F7="", "", AND('ProductSprint Backlog'!$J7>E$2,'ProductSprint Backlog'!$I7<=E$2), 'ProductSprint Backlog'!$F7 / MAX(1, 'ProductSprint Backlog'!$J7-'ProductSprint Backlog'!$I7), AND('ProductSprint Backlog'!$J7=E$2,'ProductSprint Backlog'!$I7=E$2), 'ProductSprint Backlog'!$F7, TRUE, 0)} | F7: {=_xlfn.IFS('ProductSprint Backlog'!$F7="", "", AND('ProductSprint Backlog'!$J7>F$2,'ProductSprint Backlog'!$I7<=F$2), 'ProductSprint Backlog'!$F7 / MAX(1, 'ProductSprint Backlog'!$J7-'ProductSprint Backlog'!$I7), AND('ProductSprint Backlog'!$J7=F$2,'ProductSprint Backlog'!$I7=F$2), 'ProductSprint Backlog'!$F7, TRUE, 0)} | G7: {=_xlfn.IFS('ProductSprint Backlog'!$F7="", "", AND('ProductSprint Backlog'!$J7>G$2,'ProductSprint Backlog'!$I7<=G$2), 'ProductSprint Backlog'!$F7 / MAX(1, 'ProductSprint Backlog'!$J7-'ProductSprint Backlog'!$I7), AND('ProductSprint Backlog'!$J7=G$2,'ProductSprint Backlog'!$I7=G$2), 'ProductSprint Backlog'!$F7, TRUE, 0)} | H7: {=_xlfn.IFS('ProductSprint Backlog'!$F7="", "", AND('ProductSprint Backlog'!$J7>H$2,'ProductSprint Backlog'!$I7<=H$2), 'ProductSprint Backlog'!$F7 / MAX(1, 'ProductSprint Backlog'!$J7-'ProductSprint Backlog'!$I7), AND('ProductSprint Backlog'!$J7=H$2,'ProductSprint Backlog'!$I7=H$2), 'ProductSprint Backlog'!$F7, TRUE, 0)} | I7: {=_xlfn.IFS('ProductSprint Backlog'!$F7="", "", AND('ProductSprint Backlog'!$J7>I$2,'ProductSprint Backlog'!$I7<=I$2), 'ProductSprint Backlog'!$F7 / MAX(1, 'ProductSprint Backlog'!$J7-'ProductSprint Backlog'!$I7), AND('ProductSprint Backlog'!$J7=I$2,'ProductSprint Backlog'!$I7=I$2), 'ProductSprint Backlog'!$F7, TRUE, 0)} | J7: {=_xlfn.IFS('ProductSprint Backlog'!$F7="", "", AND('ProductSprint Backlog'!$J7>J$2,'ProductSprint Backlog'!$I7<=J$2), 'ProductSprint Backlog'!$F7 / MAX(1, 'ProductSprint Backlog'!$J7-'ProductSprint Backlog'!$I7), AND('ProductSprint Backlog'!$J7=J$2,'ProductSprint Backlog'!$I7=J$2), 'ProductSprint Backlog'!$F7, TRUE, 0)}
B8: {=_xlfn.IFS('ProductSprint Backlog'!$F8="", "", AND('ProductSprint Backlog'!$J8>B$2,'ProductSprint Backlog'!$I8<=B$2), 'ProductSprint Backlog'!$F8 / MAX(1, 'ProductSprint Backlog'!$J8-'ProductSprint Backlog'!$I8), AND('ProductSprint Backlog'!$J8=B$2,'ProductSprint Backlog'!$I8=B$2), 'ProductSprint Backlog'!$F8, TRUE, 0)} -> 0 | C8: {=_xlfn.IFS('ProductSprint Backlog'!$F8="", "", AND('ProductSprint Backlog'!$J8>C$2,'ProductSprint Backlog'!$I8<=C$2), 'ProductSprint Backlog'!$F8 / MAX(1, 'ProductSprint Backlog'!$J8-'ProductSprint Backlog'!$I8), AND('ProductSprint Backlog'!$J8=C$2,'ProductSprint Backlog'!$I8=C$2), 'ProductSprint Backlog'!$F8, TRUE, 0)} -> 0 | D8: {=_xlfn.IFS('ProductSprint Backlog'!$F8="", "", AND('ProductSprint Backlog'!$J8>D$2,'ProductSprint Backlog'!$I8<=D$2), 'ProductSprint Backlog'!$F8 / MAX(1, 'ProductSprint Backlog'!$J8-'ProductSprint Backlog'!$I8), AND('ProductSprint Backlog'!$J8=D$2,'ProductSprint Backlog'!$I8=D$2), 'ProductSprint Backlog'!$F8, TRUE, 0)} -> 0 | E8: {=_xlfn.IFS('ProductSprint Backlog'!$F8="", "", AND('ProductSprint Backlog'!$J8>E$2,'ProductSprint Backlog'!$I8<=E$2), 'ProductSprint Backlog'!$F8 / MAX(1, 'ProductSprint Backlog'!$J8-'ProductSprint Backlog'!$I8), AND('ProductSprint Backlog'!$J8=E$2,'ProductSprint Backlog'!$I8=E$2), 'ProductSprint Backlog'!$F8, TRUE, 0)} -> 0 | F8: {=_xlfn.IFS('ProductSprint Backlog'!$F8="", "", AND('ProductSprint Backlog'!$J8>F$2,'ProductSprint Backlog'!$I8<=F$2), 'ProductSprint Backlog'!$F8 / MAX(1, 'ProductSprint Backlog'!$J8-'ProductSprint Backlog'!$I8), AND('ProductSprint Backlog'!$J8=F$2,'ProductSprint Backlog'!$I8=F$2), 'ProductSprint Backlog'!$F8, TRUE, 0)} -> 0 | G8: {=_xlfn.IFS('ProductSprint Backlog'!$F8="", "", AND('ProductSprint Backlog'!$J8>G$2,'ProductSprint Backlog'!$I8<=G$2), 'ProductSprint Backlog'!$F8 / MAX(1, 'ProductSprint Backlog'!$J8-'ProductSprint Backlog'!$I8), AND('ProductSprint Backlog'!$J8=G$2,'ProductSprint Backlog'!$I8=G$2), 'ProductSprint Backlog'!$F8, TRUE, 0)} -> 0 | H8: {=_xlfn.IFS('ProductSprint Backlog'!$F8="", "", AND('ProductSprint Backlog'!$J8>H$2,'ProductSprint Backlog'!$I8<=H$2), 'ProductSprint Backlog'!$F8 / MAX(1, 'ProductSprint Backlog'!$J8-'ProductSprint Backlog'!$I8), AND('ProductSprint Backlog'!$J8=H$2,'ProductSprint Backlog'!$I8=H$2), 'ProductSprint Backlog'!$F8, TRUE, 0)} -> 0 | I8: {=_xlfn.IFS('ProductSprint Backlog'!$F8="", "", AND('ProductSprint Backlog'!$J8>I$2,'ProductSprint Backlog'!$I8<=I$2), 'ProductSprint Backlog'!$F8 / MAX(1, 'ProductSprint Backlog'!$J8-'ProductSprint Backlog'!$I8), AND('ProductSprint Backlog'!$J8=I$2,'ProductSprint Backlog'!$I8=I$2), 'ProductSprint Backlog'!$F8, TRUE, 0)} -> 0 | J8: {=_xlfn.IFS('ProductSprint Backlog'!$F8="", "", AND('ProductSprint Backlog'!$J8>J$2,'ProductSprint Backlog'!$I8<=J$2), 'ProductSprint Backlog'!$F8 / MAX(1, 'ProductSprint Backlog'!$J8-'ProductSprint Backlog'!$I8), AND('ProductSprint Backlog'!$J8=J$2,'ProductSprint Backlog'!$I8=J$2), 'ProductSprint Backlog'!$F8, TRUE, 0)} -> 0
B9: {=_xlfn.IFS('ProductSprint Backlog'!$F9="", "", AND('ProductSprint Backlog'!$J9>B$2,'ProductSprint Backlog'!$I9<=B$2), 'ProductSprint Backlog'!$F9 / MAX(1, 'ProductSprint Backlog'!$J9-'ProductSprint Backlog'!$I9), AND('ProductSprint Backlog'!$J9=B$2,'ProductSprint Backlog'!$I9=B$2), 'ProductSprint Backlog'!$F9, TRUE, 0)} -> 0 | C9: {=_xlfn.IFS('ProductSprint Backlog'!$F9="", "", AND('ProductSprint Backlog'!$J9>C$2,'ProductSprint Backlog'!$I9<=C$2), 'ProductSprint Backlog'!$F9 / MAX(1, 'ProductSprint Backlog'!$J9-'ProductSprint Backlog'!$I9), AND('ProductSprint Backlog'!$J9=C$2,'ProductSprint Backlog'!$I9=C$2), 'ProductSprint Backlog'!$F9, TRUE, 0)} -> 0 | D9: {=_xlfn.IFS('ProductSprint Backlog'!$F9="", "", AND('ProductSprint Backlog'!$J9>D$2,'ProductSprint Backlog'!$I9<=D$2), 'ProductSprint Backlog'!$F9 / MAX(1, 'ProductSprint Backlog'!$J9-'ProductSprint Backlog'!$I9), AND('ProductSprint Backlog'!$J9=D$2,'ProductSprint Backlog'!$I9=D$2), 'ProductSprint Backlog'!$F9, TRUE, 0)} -> 0 | E9: {=_xlfn.IFS('ProductSprint Backlog'!$F9="", "", AND('ProductSprint Backlog'!$J9>E$2,'ProductSprint Backlog'!$I9<=E$2), 'ProductSprint Backlog'!$F9 / MAX(1, 'ProductSprint Backlog'!$J9-'ProductSprint Backlog'!$I9), AND('ProductSprint Backlog'!$J9=E$2,'ProductSprint Backlog'!$I9=E$2), 'ProductSprint Backlog'!$F9, TRUE, 0)} -> 0 | F9: {=_xlfn.IFS('ProductSprint Backlog'!$F9="", "", AND('ProductSprint Backlog'!$J9>F$2,'ProductSprint Backlog'!$I9<=F$2), 'ProductSprint Backlog'!$F9 / MAX(1, 'ProductSprint Backlog'!$J9-'ProductSprint Backlog'!$I9), AND('ProductSprint Backlog'!$J9=F$2,'ProductSprint Backlog'!$I9=F$2), 'ProductSprint Backlog'!$F9, TRUE, 0)} -> 0 | G9: {=_xlfn.IFS('ProductSprint Backlog'!$F9="", "", AND('ProductSprint Backlog'!$J9>G$2,'ProductSprint Backlog'!$I9<=G$2), 'ProductSprint Backlog'!$F9 / MAX(1, 'ProductSprint Backlog'!$J9-'ProductSprint Backlog'!$I9), AND('ProductSprint Backlog'!$J9=G$2,'ProductSprint Backlog'!$I9=G$2), 'ProductSprint Backlog'!$F9, TRUE, 0)} -> 0 | H9: {=_xlfn.IFS('ProductSprint Backlog'!$F9="", "", AND('ProductSprint Backlog'!$J9>H$2,'ProductSprint Backlog'!$I9<=H$2), 'ProductSprint Backlog'!$F9 / MAX(1, 'ProductSprint Backlog'!$J9-'ProductSprint Backlog'!$I9), AND('ProductSprint Backlog'!$J9=H$2,'ProductSprint Backlog'!$I9=H$2), 'ProductSprint Backlog'!$F9, TRUE, 0)} -> 0 | I9: {=_xlfn.IFS('ProductSprint Backlog'!$F9="", "", AND('ProductSprint Backlog'!$J9>I$2,'ProductSprint Backlog'!$I9<=I$2), 'ProductSprint Backlog'!$F9 / MAX(1, 'ProductSprint Backlog'!$J9-'ProductSprint Backlog'!$I9), AND('ProductSprint Backlog'!$J9=I$2,'ProductSprint Backlog'!$I9=I$2), 'ProductSprint Backlog'!$F9, TRUE, 0)} -> 0 | J9: {=_xlfn.IFS('ProductSprint Backlog'!$F9="", "", AND('ProductSprint Backlog'!$J9>J$2,'ProductSprint Backlog'!$I9<=J$2), 'ProductSprint Backlog'!$F9 / MAX(1, 'ProductSprint Backlog'!$J9-'ProductSprint Backlog'!$I9), AND('ProductSprint Backlog'!$J9=J$2,'ProductSprint Backlog'!$I9=J$2), 'ProductSprint Backlog'!$F9, TRUE, 0)} -> 0
B10: {=_xlfn.IFS('ProductSprint Backlog'!$F10="", "", AND('ProductSprint Backlog'!$J10>B$2,'ProductSprint Backlog'!$I10<=B$2), 'ProductSprint Backlog'!$F10 / MAX(1, 'ProductSprint Backlog'!$J10-'ProductSprint Backlog'!$I10), AND('ProductSprint Backlog'!$J10=B$2,'ProductSprint Backlog'!$I10=B$2), 'ProductSprint Backlog'!$F10, TRUE, 0)} -> 0 | C10: {=_xlfn.IFS('ProductSprint Backlog'!$F10="", "", AND('ProductSprint Backlog'!$J10>C$2,'ProductSprint Backlog'!$I10<=C$2), 'ProductSprint Backlog'!$F10 / MAX(1, 'ProductSprint Backlog'!$J10-'ProductSprint Backlog'!$I10), AND('ProductSprint Backlog'!$J10=C$2,'ProductSprint Backlog'!$I10=C$2), 'ProductSprint Backlog'!$F10, TRUE, 0)} -> 0 | D10: {=_xlfn.IFS('ProductSprint Backlog'!$F10="", "", AND('ProductSprint Backlog'!$J10>D$2,'ProductSprint Backlog'!$I10<=D$2), 'ProductSprint Backlog'!$F10 / MAX(1, 'ProductSprint Backlog'!$J10-'ProductSprint Backlog'!$I10), AND('ProductSprint Backlog'!$J10=D$2,'ProductSprint Backlog'!$I10=D$2), 'ProductSprint Backlog'!$F10, TRUE, 0)} -> 0 | E10: {=_xlfn.IFS('ProductSprint Backlog'!$F10="", "", AND('ProductSprint Backlog'!$J10>E$2,'ProductSprint Backlog'!$I10<=E$2), 'ProductSprint Backlog'!$F10 / MAX(1, 'ProductSprint Backlog'!$J10-'ProductSprint Backlog'!$I10), AND('ProductSprint Backlog'!$J10=E$2,'ProductSprint Backlog'!$I10=E$2), 'ProductSprint Backlog'!$F10, TRUE, 0)} -> 0 | F10: {=_xlfn.IFS('ProductSprint Backlog'!$F10="", "", AND('ProductSprint Backlog'!$J10>F$2,'ProductSprint Backlog'!$I10<=F$2), 'ProductSprint Backlog'!$F10 / MAX(1, 'ProductSprint Backlog'!$J10-'ProductSprint Backlog'!$I10), AND('ProductSprint Backlog'!$J10=F$2,'ProductSprint Backlog'!$I10=F$2), 'ProductSprint Backlog'!$F10, TRUE, 0)} -> 0 | G10: {=_xlfn.IFS('ProductSprint Backlog'!$F10="", "", AND('ProductSprint Backlog'!$J10>G$2,'ProductSprint Backlog'!$I10<=G$2), 'ProductSprint Backlog'!$F10 / MAX(1, 'ProductSprint Backlog'!$J10-'ProductSprint Backlog'!$I10), AND('ProductSprint Backlog'!$J10=G$2,'ProductSprint Backlog'!$I10=G$2), 'ProductSprint Backlog'!$F10, TRUE, 0)} -> 0 | H10: {=_xlfn.IFS('ProductSprint Backlog'!$F10="", "", AND('ProductSprint Backlog'!$J10>H$2,'ProductSprint Backlog'!$I10<=H$2), 'ProductSprint Backlog'!$F10 / MAX(1, 'ProductSprint Backlog'!$J10-'ProductSprint Backlog'!$I10), AND('ProductSprint Backlog'!$J10=H$2,'ProductSprint Backlog'!$I10=H$2), 'ProductSprint Backlog'!$F10, TRUE, 0)} -> 0 | I10: {=_xlfn.IFS('ProductSprint Backlog'!$F10="", "", AND('ProductSprint Backlog'!$J10>I$2,'ProductSprint Backlog'!$I10<=I$2), 'ProductSprint Backlog'!$F10 / MAX(1, 'ProductSprint Backlog'!$J10-'ProductSprint Backlog'!$I10), AND('ProductSprint Backlog'!$J10=I$2,'ProductSprint Backlog'!$I10=I$2), 'ProductSprint Backlog'!$F10, TRUE, 0)} -> 0 | J10: {=_xlfn.IFS('ProductSprint Backlog'!$F10="", "", AND('ProductSprint Backlog'!$J10>J$2,'ProductSprint Backlog'!$I10<=J$2), 'ProductSprint Backlog'!$F10 / MAX(1, 'ProductSprint Backlog'!$J10-'ProductSprint Backlog'!$I10), AND('ProductSprint Backlog'!$J10=J$2,'ProductSprint Backlog'!$I10=J$2), 'ProductSprint Backlog'!$F10, TRUE, 0)} -> 0
B11: {=_xlfn.IFS('ProductSprint Backlog'!$F11="", "", AND('ProductSprint Backlog'!$J11>B$2,'ProductSprint Backlog'!$I11<=B$2), 'ProductSprint Backlog'!$F11 / MAX(1, 'ProductSprint Backlog'!$J11-'ProductSprint Backlog'!$I11), AND('ProductSprint Backlog'!$J11=B$2,'ProductSprint Backlog'!$I11=B$2), 'ProductSprint Backlog'!$F11, TRUE, 0)} -> 0 | C11: {=_xlfn.IFS('ProductSprint Backlog'!$F11="", "", AND('ProductSprint Backlog'!$J11>C$2,'ProductSprint Backlog'!$I11<=C$2), 'ProductSprint Backlog'!$F11 / MAX(1, 'ProductSprint Backlog'!$J11-'ProductSprint Backlog'!$I11), AND('ProductSprint Backlog'!$J11=C$2,'ProductSprint Backlog'!$I11=C$2), 'ProductSprint Backlog'!$F11, TRUE, 0)} -> 0 | D11: {=_xlfn.IFS('ProductSprint Backlog'!$F11="", "", AND('ProductSprint Backlog'!$J11>D$2,'ProductSprint Backlog'!$I11<=D$2), 'ProductSprint Backlog'!$F11 / MAX(1, 'ProductSprint Backlog'!$J11-'ProductSprint Backlog'!$I11), AND('ProductSprint Backlog'!$J11=D$2,'ProductSprint Backlog'!$I11=D$2), 'ProductSprint Backlog'!$F11, TRUE, 0)} -> 0 | E11: {=_xlfn.IFS('ProductSprint Backlog'!$F11="", "", AND('ProductSprint Backlog'!$J11>E$2,'ProductSprint Backlog'!$I11<=E$2), 'ProductSprint Backlog'!$F11 / MAX(1, 'ProductSprint Backlog'!$J11-'ProductSprint Backlog'!$I11), AND('ProductSprint Backlog'!$J11=E$2,'ProductSprint Backlog'!$I11=E$2), 'ProductSprint Backlog'!$F11, TRUE, 0)} -> 0 | F11: {=_xlfn.IFS('ProductSprint Backlog'!$F11="", "", AND('ProductSprint Backlog'!$J11>F$2,'ProductSprint Backlog'!$I11<=F$2), 'ProductSprint Backlog'!$F11 / MAX(1, 'ProductSprint Backlog'!$J11-'ProductSprint Backlog'!$I11), AND('ProductSprint Backlog'!$J11=F$2,'ProductSprint Backlog'!$I11=F$2), 'ProductSprint Backlog'!$F11, TRUE, 0)} -> 0 | G11: {=_xlfn.IFS('ProductSprint Backlog'!$F11="", "", AND('ProductSprint Backlog'!$J11>G$2,'ProductSprint Backlog'!$I11<=G$2), 'ProductSprint Backlog'!$F11 / MAX(1, 'ProductSprint Backlog'!$J11-'ProductSprint Backlog'!$I11), AND('ProductSprint Backlog'!$J11=G$2,'ProductSprint Backlog'!$I11=G$2), 'ProductSprint Backlog'!$F11, TRUE, 0)} -> 0 | H11: {=_xlfn.IFS('ProductSprint Backlog'!$F11="", "", AND('ProductSprint Backlog'!$J11>H$2,'ProductSprint Backlog'!$I11<=H$2), 'ProductSprint Backlog'!$F11 / MAX(1, 'ProductSprint Backlog'!$J11-'ProductSprint Backlog'!$I11), AND('ProductSprint Backlog'!$J11=H$2,'ProductSprint Backlog'!$I11=H$2), 'ProductSprint Backlog'!$F11, TRUE, 0)} -> 0 | I11: {=_xlfn.IFS('ProductSprint Backlog'!$F11="", "", AND('ProductSprint Backlog'!$J11>I$2,'ProductSprint Backlog'!$I11<=I$2), 'ProductSprint Backlog'!$F11 / MAX(1, 'ProductSprint Backlog'!$J11-'ProductSprint Backlog'!$I11), AND('ProductSprint Backlog'!$J11=I$2,'ProductSprint Backlog'!$I11=I$2), 'ProductSprint Backlog'!$F11, TRUE, 0)} -> 0 | J11: {=_xlfn.IFS('ProductSprint Backlog'!$F11="", "", AND('ProductSprint Backlog'!$J11>J$2,'ProductSprint Backlog'!$I11<=J$2), 'ProductSprint Backlog'!$F11 / MAX(1, 'ProductSprint Backlog'!$J11-'ProductSprint Backlog'!$I11), AND('ProductSprint Backlog'!$J11=J$2,'ProductSprint Backlog'!$I11=J$2), 'ProductSprint Backlog'!$F11, TRUE, 0)} -> 0
B12: {=_xlfn.IFS('ProductSprint Backlog'!$F12="", "", AND('ProductSprint Backlog'!$J12>B$2,'ProductSprint Backlog'!$I12<=B$2), 'ProductSprint Backlog'!$F12 / MAX(1, 'ProductSprint Backlog'!$J12-'ProductSprint Backlog'!$I12), AND('ProductSprint Backlog'!$J12=B$2,'ProductSprint Backlog'!$I12=B$2), 'ProductSprint Backlog'!$F12, TRUE, 0)} -> 0 | C12: {=_xlfn.IFS('ProductSprint Backlog'!$F12="", "", AND('ProductSprint Backlog'!$J12>C$2,'ProductSprint Backlog'!$I12<=C$2), 'ProductSprint Backlog'!$F12 / MAX(1, 'ProductSprint Backlog'!$J12-'ProductSprint Backlog'!$I12), AND('ProductSprint Backlog'!$J12=C$2,'ProductSprint Backlog'!$I12=C$2), 'ProductSprint Backlog'!$F12, TRUE, 0)} -> 0 | D12: {=_xlfn.IFS('ProductSprint Backlog'!$F12="", "", AND('ProductSprint Backlog'!$J12>D$2,'ProductSprint Backlog'!$I12<=D$2), 'ProductSprint Backlog'!$F12 / MAX(1, 'ProductSprint Backlog'!$J12-'ProductSprint Backlog'!$I12), AND('ProductSprint Backlog'!$J12=D$2,'ProductSprint Backlog'!$I12=D$2), 'ProductSprint Backlog'!$F12, TRUE, 0)} -> 0 | E12: {=_xlfn.IFS('ProductSprint Backlog'!$F12="", "", AND('ProductSprint Backlog'!$J12>E$2,'ProductSprint Backlog'!$I12<=E$2), 'ProductSprint Backlog'!$F12 / MAX(1, 'ProductSprint Backlog'!$J12-'ProductSprint Backlog'!$I12), AND('ProductSprint Backlog'!$J12=E$2,'ProductSprint Backlog'!$I12=E$2), 'ProductSprint Backlog'!$F12, TRUE, 0)} -> 0 | F12: {=_xlfn.IFS('ProductSprint Backlog'!$F12="", "", AND('ProductSprint Backlog'!$J12>F$2,'ProductSprint Backlog'!$I12<=F$2), 'ProductSprint Backlog'!$F12 / MAX(1, 'ProductSprint Backlog'!$J12-'ProductSprint Backlog'!$I12), AND('ProductSprint Backlog'!$J12=F$2,'ProductSprint Backlog'!$I12=F$2), 'ProductSprint Backlog'!$F12, TRUE, 0)} -> 0 | G12: {=_xlfn.IFS('ProductSprint Backlog'!$F12="", "", AND('ProductSprint Backlog'!$J12>G$2,'ProductSprint Backlog'!$I12<=G$2), 'ProductSprint Backlog'!$F12 / MAX(1, 'ProductSprint Backlog'!$J12-'ProductSprint Backlog'!$I12), AND('ProductSprint Backlog'!$J12=G$2,'ProductSprint Backlog'!$I12=G$2), 'ProductSprint Backlog'!$F12, TRUE, 0)} -> 0 | H12: {=_xlfn.IFS('ProductSprint Backlog'!$F12="", "", AND('ProductSprint Backlog'!$J12>H$2,'ProductSprint Backlog'!$I12<=H$2), 'ProductSprint Backlog'!$F12 / MAX(1, 'ProductSprint Backlog'!$J12-'ProductSprint Backlog'!$I12), AND('ProductSprint Backlog'!$J12=H$2,'ProductSprint Backlog'!$I12=H$2), 'ProductSprint Backlog'!$F12, TRUE, 0)} -> 0 | I12: {=_xlfn.IFS('ProductSprint Backlog'!$F12="", "", AND('ProductSprint Backlog'!$J12>I$2,'ProductSprint Backlog'!$I12<=I$2), 'ProductSprint Backlog'!$F12 / MAX(1, 'ProductSprint Backlog'!$J12-'ProductSprint Backlog'!$I12), AND('ProductSprint Backlog'!$J12=I$2,'ProductSprint Backlog'!$I12=I$2), 'ProductSprint Backlog'!$F12, TRUE, 0)} -> 0 | J12: {=_xlfn.IFS('ProductSprint Backlog'!$F12="", "", AND('ProductSprint Backlog'!$J12>J$2,'ProductSprint Backlog'!$I12<=J$2), 'ProductSprint Backlog'!$F12 / MAX(1, 'ProductSprint Backlog'!$J12-'ProductSprint Backlog'!$I12), AND('ProductSprint Backlog'!$J12=J$2,'ProductSprint Backlog'!$I12=J$2), 'ProductSprint Backlog'!$F12, TRUE, 0)} -> 0
B13: {=_xlfn.IFS('ProductSprint Backlog'!$F13="", "", AND('ProductSprint Backlog'!$J13>B$2,'ProductSprint Backlog'!$I13<=B$2), 'ProductSprint Backlog'!$F13 / MAX(1, 'ProductSprint Backlog'!$J13-'ProductSprint Backlog'!$I13), AND('ProductSprint Backlog'!$J13=B$2,'ProductSprint Backlog'!$I13=B$2), 'ProductSprint Backlog'!$F13, TRUE, 0)} | C13: {=_xlfn.IFS('ProductSprint Backlog'!$F13="", "", AND('ProductSprint Backlog'!$J13>C$2,'ProductSprint Backlog'!$I13<=C$2), 'ProductSprint Backlog'!$F13 / MAX(1, 'ProductSprint Backlog'!$J13-'ProductSprint Backlog'!$I13), AND('ProductSprint Backlog'!$J13=C$2,'ProductSprint Backlog'!$I13=C$2), 'ProductSprint Backlog'!$F13, TRUE, 0)} | D13: {=_xlfn.IFS('ProductSprint Backlog'!$F13="", "", AND('ProductSprint Backlog'!$J13>D$2,'ProductSprint Backlog'!$I13<=D$2), 'ProductSprint Backlog'!$F13 / MAX(1, 'ProductSprint Backlog'!$J13-'ProductSprint Backlog'!$I13), AND('ProductSprint Backlog'!$J13=D$2,'ProductSprint Backlog'!$I13=D$2), 'ProductSprint Backlog'!$F13, TRUE, 0)} | E13: {=_xlfn.IFS('ProductSprint Backlog'!$F13="", "", AND('ProductSprint Backlog'!$J13>E$2,'ProductSprint Backlog'!$I13<=E$2), 'ProductSprint Backlog'!$F13 / MAX(1, 'ProductSprint Backlog'!$J13-'ProductSprint Backlog'!$I13), AND('ProductSprint Backlog'!$J13=E$2,'ProductSprint Backlog'!$I13=E$2), 'ProductSprint Backlog'!$F13, TRUE, 0)} | F13: {=_xlfn.IFS('ProductSprint Backlog'!$F13="", "", AND('ProductSprint Backlog'!$J13>F$2,'ProductSprint Backlog'!$I13<=F$2), 'ProductSprint Backlog'!$F13 / MAX(1, 'ProductSprint Backlog'!$J13-'ProductSprint Backlog'!$I13), AND('ProductSprint Backlog'!$J13=F$2,'ProductSprint Backlog'!$I13=F$2), 'ProductSprint Backlog'!$F13, TRUE, 0)} | G13: {=_xlfn.IFS('ProductSprint Backlog'!$F13="", "", AND('ProductSprint Backlog'!$J13>G$2,'ProductSprint Backlog'!$I13<=G$2), 'ProductSprint Backlog'!$F13 / MAX(1, 'ProductSprint Backlog'!$J13-'ProductSprint Backlog'!$I13), AND('ProductSprint Backlog'!$J13=G$2,'ProductSprint Backlog'!$I13=G$2), 'ProductSprint Backlog'!$F13, TRUE, 0)} | H13: {=_xlfn.IFS('ProductSprint Backlog'!$F13="", "", AND('ProductSprint Backlog'!$J13>H$2,'ProductSprint Backlog'!$I13<=H$2), 'ProductSprint Backlog'!$F13 / MAX(1, 'ProductSprint Backlog'!$J13-'ProductSprint Backlog'!$I13), AND('ProductSprint Backlog'!$J13=H$2,'ProductSprint Backlog'!$I13=H$2), 'ProductSprint Backlog'!$F13, TRUE, 0)} | I13: {=_xlfn.IFS('ProductSprint Backlog'!$F13="", "", AND('ProductSprint Backlog'!$J13>I$2,'ProductSprint Backlog'!$I13<=I$2), 'ProductSprint Backlog'!$F13 / MAX(1, 'ProductSprint Backlog'!$J13-'ProductSprint Backlog'!$I13), AND('ProductSprint Backlog'!$J13=I$2,'ProductSprint Backlog'!$I13=I$2), 'ProductSprint Backlog'!$F13, TRUE, 0)} | J13: {=_xlfn.IFS('ProductSprint Backlog'!$F13="", "", AND('ProductSprint Backlog'!$J13>J$2,'ProductSprint Backlog'!$I13<=J$2), 'ProductSprint Backlog'!$F13 / MAX(1, 'ProductSprint Backlog'!$J13-'ProductSprint Backlog'!$I13), AND('ProductSprint Backlog'!$J13=J$2,'ProductSprint Backlog'!$I13=J$2), 'ProductSprint Backlog'!$F13, TRUE, 0)}
B14: {=_xlfn.IFS('ProductSprint Backlog'!$F14="", "", AND('ProductSprint Backlog'!$J14>B$2,'ProductSprint Backlog'!$I14<=B$2), 'ProductSprint Backlog'!$F14 / MAX(1, 'ProductSprint Backlog'!$J14-'ProductSprint Backlog'!$I14), AND('ProductSprint Backlog'!$J14=B$2,'ProductSprint Backlog'!$I14=B$2), 'ProductSprint Backlog'!$F14, TRUE, 0)} -> 0 | C14: {=_xlfn.IFS('ProductSprint Backlog'!$F14="", "", AND('ProductSprint Backlog'!$J14>C$2,'ProductSprint Backlog'!$I14<=C$2), 'ProductSprint Backlog'!$F14 / MAX(1, 'ProductSprint Backlog'!$J14-'ProductSprint Backlog'!$I14), AND('ProductSprint Backlog'!$J14=C$2,'ProductSprint Backlog'!$I14=C$2), 'ProductSprint Backlog'!$F14, TRUE, 0)} -> 0 | D14: {=_xlfn.IFS('ProductSprint Backlog'!$F14="", "", AND('ProductSprint Backlog'!$J14>D$2,'ProductSprint Backlog'!$I14<=D$2), 'ProductSprint Backlog'!$F14 / MAX(1, 'ProductSprint Backlog'!$J14-'ProductSprint Backlog'!$I14), AND('ProductSprint Backlog'!$J14=D$2,'ProductSprint Backlog'!$I14=D$2), 'ProductSprint Backlog'!$F14, TRUE, 0)} -> 0 | E14: {=_xlfn.IFS('ProductSprint Backlog'!$F14="", "", AND('ProductSprint Backlog'!$J14>E$2,'ProductSprint Backlog'!$I14<=E$2), 'ProductSprint Backlog'!$F14 / MAX(1, 'ProductSprint Backlog'!$J14-'ProductSprint Backlog'!$I14), AND('ProductSprint Backlog'!$J14=E$2,'ProductSprint Backlog'!$I14=E$2), 'ProductSprint Backlog'!$F14, TRUE, 0)} -> 0 | F14: {=_xlfn.IFS('ProductSprint Backlog'!$F14="", "", AND('ProductSprint Backlog'!$J14>F$2,'ProductSprint Backlog'!$I14<=F$2), 'ProductSprint Backlog'!$F14 / MAX(1, 'ProductSprint Backlog'!$J14-'ProductSprint Backlog'!$I14), AND('ProductSprint Backlog'!$J14=F$2,'ProductSprint Backlog'!$I14=F$2), 'ProductSprint Backlog'!$F14, TRUE, 0)} -> 0 | G14: {=_xlfn.IFS('ProductSprint Backlog'!$F14="", "", AND('ProductSprint Backlog'!$J14>G$2,'ProductSprint Backlog'!$I14<=G$2), 'ProductSprint Backlog'!$F14 / MAX(1, 'ProductSprint Backlog'!$J14-'ProductSprint Backlog'!$I14), AND('ProductSprint Backlog'!$J14=G$2,'ProductSprint Backlog'!$I14=G$2), 'ProductSprint Backlog'!$F14, TRUE, 0)} -> 0 | H14: {=_xlfn.IFS('ProductSprint Backlog'!$F14="", "", AND('ProductSprint Backlog'!$J14>H$2,'ProductSprint Backlog'!$I14<=H$2), 'ProductSprint Backlog'!$F14 / MAX(1, 'ProductSprint Backlog'!$J14-'ProductSprint Backlog'!$I14), AND('ProductSprint Backlog'!$J14=H$2,'ProductSprint Backlog'!$I14=H$2), 'ProductSprint Backlog'!$F14, TRUE, 0)} -> 0 | I14: {=_xlfn.IFS('ProductSprint Backlog'!$F14="", "", AND('ProductSprint Backlog'!$J14>I$2,'ProductSprint Backlog'!$I14<=I$2), 'ProductSprint Backlog'!$F14 / MAX(1, 'ProductSprint Backlog'!$J14-'ProductSprint Backlog'!$I14), AND('ProductSprint Backlog'!$J14=I$2,'ProductSprint Backlog'!$I14=I$2), 'ProductSprint Backlog'!$F14, TRUE, 0)} -> 0 | J14: {=_xlfn.IFS('ProductSprint Backlog'!$F14="", "", AND('ProductSprint Backlog'!$J14>J$2,'ProductSprint Backlog'!$I14<=J$2), 'ProductSprint Backlog'!$F14 / MAX(1, 'ProductSprint Backlog'!$J14-'ProductSprint Backlog'!$I14), AND('ProductSprint Backlog'!$J14=J$2,'ProductSprint Backlog'!$I14=J$2), 'ProductSprint Backlog'!$F14, TRUE, 0)} -> 0
... B293: {=_xlfn.IFS('ProductSprint Backlog'!$F293="", "", AND('ProductSprint Backlog'!$J293>B$2,'ProductSprint Backlog'!$I293<=B$2), 'ProductSprint Backlog'!$F293 / MAX(1, 'ProductSprint Backlog'!$J293-'ProductSprint Backlog'!$I293), AND('ProductSprint Backlog'!$J293=B$2,'ProductSprint Backlog'!$I293=B$2), 'ProductSprint Backlog'!$F293, TRUE, 0)} | C293: {=_xlfn.IFS('ProductSprint Backlog'!$F293="", "", AND('ProductSprint Backlog'!$J293>C$2,'ProductSprint Backlog'!$I293<=C$2), 'ProductSprint Backlog'!$F293 / MAX(1, 'ProductSprint Backlog'!$J293-'ProductSprint Backlog'!$I293), AND('ProductSprint Backlog'!$J293=C$2,'ProductSprint Backlog'!$I293=C$2), 'ProductSprint Backlog'!$F293, TRUE, 0)} | D293: {=_xlfn.IFS('ProductSprint Backlog'!$F293="", "", AND('ProductSprint Backlog'!$J293>D$2,'ProductSprint Backlog'!$I293<=D$2), 'ProductSprint Backlog'!$F293 / MAX(1, 'ProductSprint Backlog'!$J293-'ProductSprint Backlog'!$I293), AND('ProductSprint Backlog'!$J293=D$2,'ProductSprint Backlog'!$I293=D$2), 'ProductSprint Backlog'!$F293, TRUE, 0)} | E293: {=_xlfn.IFS('ProductSprint Backlog'!$F293="", "", AND('ProductSprint Backlog'!$J293>E$2,'ProductSprint Backlog'!$I293<=E$2), 'ProductSprint Backlog'!$F293 / MAX(1, 'ProductSprint Backlog'!$J293-'ProductSprint Backlog'!$I293), AND('ProductSprint Backlog'!$J293=E$2,'ProductSprint Backlog'!$I293=E$2), 'ProductSprint Backlog'!$F293, TRUE, 0)} | F293: {=_xlfn.IFS('ProductSprint Backlog'!$F293="", "", AND('ProductSprint Backlog'!$J293>F$2,'ProductSprint Backlog'!$I293<=F$2), 'ProductSprint Backlog'!$F293 / MAX(1, 'ProductSprint Backlog'!$J293-'ProductSprint Backlog'!$I293), AND('ProductSprint Backlog'!$J293=F$2,'ProductSprint Backlog'!$I293=F$2), 'ProductSprint Backlog'!$F293, TRUE, 0)} | G293: {=_xlfn.IFS('ProductSprint Backlog'!$F293="", "", AND('ProductSprint Backlog'!$J293>G$2,'ProductSprint Backlog'!$I293<=G$2), 'ProductSprint Backlog'!$F293 / MAX(1, 'ProductSprint Backlog'!$J293-'ProductSprint Backlog'!$I293), AND('ProductSprint Backlog'!$J293=G$2,'ProductSprint Backlog'!$I293=G$2), 'ProductSprint Backlog'!$F293, TRUE, 0)} | H293: {=_xlfn.IFS('ProductSprint Backlog'!$F293="", "", AND('ProductSprint Backlog'!$J293>H$2,'ProductSprint Backlog'!$I293<=H$2), 'ProductSprint Backlog'!$F293 / MAX(1, 'ProductSprint Backlog'!$J293-'ProductSprint Backlog'!$I293), AND('ProductSprint Backlog'!$J293=H$2,'ProductSprint Backlog'!$I293=H$2), 'ProductSprint Backlog'!$F293, TRUE, 0)} | I293: {=_xlfn.IFS('ProductSprint Backlog'!$F293="", "", AND('ProductSprint Backlog'!$J293>I$2,'ProductSprint Backlog'!$I293<=I$2), 'ProductSprint Backlog'!$F293 / MAX(1, 'ProductSprint Backlog'!$J293-'ProductSprint Backlog'!$I293), AND('ProductSprint Backlog'!$J293=I$2,'ProductSprint Backlog'!$I293=I$2), 'ProductSprint Backlog'!$F293, TRUE, 0)} | J293: {=_xlfn.IFS('ProductSprint Backlog'!$F293="", "", AND('ProductSprint Backlog'!$J293>J$2,'ProductSprint Backlog'!$I293<=J$2), 'ProductSprint Backlog'!$F293 / MAX(1, 'ProductSprint Backlog'!$J293-'ProductSprint Backlog'!$I293), AND('ProductSprint Backlog'!$J293=J$2,'ProductSprint Backlog'!$I293=J$2), 'ProductSprint Backlog'!$F293, TRUE, 0)}

Sheet BurnUp-Down INC 3
A1: Periodo de Sprint 1 | D1: 45879 | E1: 45887 | F1: =E1-D1 -> 8
A3: BurnUp
B4: 45940 | C4: 45941 | D4: 45942 | E4: 45943 | F4: 45944 | G4: 45945 | H4: 45946 | I4: 45947 | J4: 45948
B5: Día 1 | C5: Día 2 | D5: Día 3 | E5: Día 4 | F5: Día 5 | G5: Día 6 | H5: Día 7 | I5: Día 8 | J5: Día 9
A6: Esfuerzo Real Acumulado (HH) | B6: 0 | C6: ='Registro de HH INC3'!C11 -> 1 | D6: ='Registro de HH INC3'!D11 -> 5 | E6: ='Registro de HH INC3'!E11 -> 12.5 | F6: ='Registro de HH INC3'!F11 -> 18.5 | G6: ='Registro de HH INC3'!G11 -> 29 | H6: ='Registro de HH INC3'!H11 -> 35 | I6: ='Registro de HH INC3'!I11 -> 42 | J6: ='Registro de HH INC3'!J11 -> 46
A7: Esfuerzo Estimado Acumulado (HH) | B7: 0 | C7: =SUM('Aux Esfuerzo Estimado INC3 SPT4'!B3:B1000) -> 9.5 | D7: =SUM('Aux Esfuerzo Estimado INC3 SPT4'!C3:C1000)+C7 -> 16 | E7: =SUM('Aux Esfuerzo Estimado INC3 SPT4'!D3:D1000)+D7 -> 23.5 | F7: =SUM('Aux Esfuerzo Estimado INC3 SPT4'!E3:E1000)+E7 -> 29.5 | G7: =SUM('Aux Esfuerzo Estimado INC3 SPT4'!F3:F1000)+F7 -> 36 | H7: =SUM('Aux Esfuerzo Estimado INC3 SPT4'!G3:G1000)+G7 -> 41.5 | I7: =SUM('Aux Esfuerzo Estimado INC3 SPT4'!H3:H1000)+H7 -> 47.5 | J7: =SUM('Aux Esfuerzo Estimado INC3 SPT4'!I3:I1000)+I7 -> 47.5
A9: BurnDown
B10: 45940 | C10: 45941 | D10: 45942 | E10: 45943 | F10: 45944 | G10: 45945 | H10: 45946 | I10: 45947 | J10: 45948
B11: Día 1 | C11: Día 2 | D11: Día 3 | E11: Día 4 | F11: Día 5 | G11: Día 6 | H11: Día 7 | I11: Día 8 | J11: Día 9
A12: Esfuerzo Real Restante (HH) | B12: =SUM('ProductSprint Backlog'!M240:M280) -> 46 | C12: =B12-'Registro de HH INC3'!C10 -> 45 | D12: =C12-'Registro de HH INC3'!D10 -> 41 | E12: =D12-'Registro de HH INC3'!E10 -> 33.5 | F12: =E12-'Registro de HH INC3'!F10 -> 27.5 | G12: =F12-'Registro de HH INC3'!G10 -> 17 | H12: =G12-'Registro de HH INC3'!H10 -> 11 | I12: =H12-'Registro de HH INC3'!I10 -> 4 | J12: =I12-'Registro de HH INC3'!J10 -> 0
A13: Esfuerzo Estimado Restante (HH) | B13: =SUM('ProductSprint Backlog'!F240:F280) -> 47.5 | C13: =B13-SUM('Aux Esfuerzo Estimado INC3 SPT4'!B3:B1000) -> 38 | D13: =C13-SUM('Aux Esfuerzo Estimado INC3 SPT4'!C3:C1000) -> 31.5 | E13: =D13-SUM('Aux Esfuerzo Estimado INC3 SPT4'!D3:D1000) -> 24 | F13: =E13-SUM('Aux Esfuerzo Estimado INC3 SPT4'!E3:E1000) -> 18 | G13: =F13-SUM('Aux Esfuerzo Estimado INC3 SPT4'!F3:F1000) -> 11.5 | H13: =G13-SUM('Aux Esfuerzo Estimado INC3 SPT4'!G3:G1000) -> 6 | I13: =H13-SUM('Aux Esfuerzo Estimado INC3 SPT4'!H3:H1000) -> 0 | J13: =I13-SUM('Aux Esfuerzo Estimado INC3 SPT4'!I3:I1000) -> 0

Sheet Registro de HH INC3
A1: Sprint 2
B2: Dia 0 | C2: Dia 1 | D2: Dia 2 | E2: Dia 3 | F2: Dia 4 | G2: Dia 5 | H2: Dia 6 | I2: Dia 7 | J2: Dia 8 | K2: Dia 9
A3: Persona | C3: 45941 | D3: 45942 | E3: 45943 | F3: 45944 | G3: 45945 | H3: 45946 | I3: 45947 | J3: 45948 | K3: 45949
A4: Bastian
A5: Eliam | E5: 2.5 | F5: 2 | G5: 1.5 | H5: 1
A6: Geronimo | F6: 1 | G6: 3 | H6: 1 | I6: 1 | J6: 1
A7: Manuel | G7: 3 | H7: 3 | I7: 3 | J7: 2
A8: Samir | D8: 2 | E8: 3 | F8: 2 | G8: 3 | H8: 1 | I8: 3 | J8: 1 | L8: =SUM(C8:J8) -> 15
A9: Francisco | C9: 1 | D9: 2 | E9: 2 | F9: 1
A10: Total Dia | C10: =SUM(C4:C9) -> 1 | D10: =SUM(D4:D9) -> 4 | E10: =SUM(E4:E9) -> 7.5 | F10: =SUM(F4:F9) -> 6 | G10: =SUM(G4:G9) -> 10.5 | H10: =SUM(H4:H9) -> 6 | I10: =SUM(I4:I9) -> 7 | J10: =SUM(J4:J9) -> 4 | K10: =SUM(K4:K9) -> 0
A11: Total Acumulado | C11: =SUM(C4:C9) -> 1 | D11: =SUM(D4:D9)+C11 -> 5 | E11: =SUM(E4:E9)+D11 -> 12.5 | F11: =SUM(F4:F9)+E11 -> 18.5 | G11: =SUM(G4:G9)+F11 -> 29 | H11: =SUM(H4:H9)+G11 -> 35 | I11: =SUM(I4:I9)+H11 -> 42 | J11: =SUM(J4:J9)+I11 -> 46 | K11: =SUM(K4:K9)+J11 -> 46

Sheet Tabla de Esfuerzo INC3 SPT4
B2: 45941 | C2: 45942 | D2: 45943 | E2: 45944 | F2: 45945 | G2: 45946 | H2: 45947 | I2: 45948 | J2: 45949 | K2: 45950 | L2: 45951 | M2: 45952 | N2: 45953 | O2: 45954 | P2: 45955
A3: Tareas Pendientes | B3: =COUNTIFS('ProductSprint Backlog'!$D$240:$D$280,"<>",'ProductSprint Backlog'!$L$240:$L$280,">"&DATEVALUE(B2)) -> 0 | C3: =COUNTIFS('ProductSprint Backlog'!$D$240:$D$280,"<>",'ProductSprint Backlog'!$L$240:$L$280,">"&DATEVALUE(C2)) -> 0 | D3: =COUNTIFS('ProductSprint Backlog'!$D$240:$D$280,"<>",'ProductSprint Backlog'!$L$240:$L$280,">"&DATEVALUE(D2)) -> 0 | E3: =COUNTIFS('ProductSprint Backlog'!$D$240:$D$280,"<>",'ProductSprint Backlog'!$L$240:$L$280,">"&DATEVALUE(E2)) -> 0 | F3: =COUNTIFS('ProductSprint Backlog'!$D$240:$D$280,"<>",'ProductSprint Backlog'!$L$240:$L$280,">"&DATEVALUE(F2)) -> 0 | G3: =COUNTIFS('ProductSprint Backlog'!$D$240:$D$280,"<>",'ProductSprint Backlog'!$L$240:$L$280,">"&DATEVALUE(G2)) -> 0 | H3: =COUNTIFS('ProductSprint Backlog'!$D$240:$D$280,"<>",'ProductSprint Backlog'!$L$240:$L$280,">"&DATEVALUE(H2)) -> 0 | I3: =COUNTIFS('ProductSprint Backlog'!$D$240:$D$280,"<>",'ProductSprint Backlog'!$L$240:$L$280,">"&DATEVALUE(I2)) -> 0 | ... P3: =COUNTIFS('ProductSprint Backlog'!$D$240:$D$280,"<>",'ProductSprint Backlog'!$L$240:$L$280,">"&DATEVALUE(P2)) -> 0
A6: Tarea | B6: Esfuerzo
A7: Incluir el botón de creación de informe técnico en la vista de administrador. | B7: =IF('ProductSprint Backlog'!$L240>B$2,'ProductSprint Backlog'!$M240,0) -> 0.5 | C7: =IF('ProductSprint Backlog'!$L240>C$2,'ProductSprint Backlog'!$M240,0) -> 0 | D7: =IF('ProductSprint Backlog'!$L240>D$2,'ProductSprint Backlog'!$M240,0) -> 0 | E7: =IF('ProductSprint Backlog'!$L240>E$2,'ProductSprint Backlog'!$M240,0) -> 0 | F7: =IF('ProductSprint Backlog'!$L240>F$2,'ProductSprint Backlog'!$M240,0) -> 0 | G7: =IF('ProductSprint Backlog'!$L240>G$2,'ProductSprint Backlog'!$M240,0) -> 0 | H7: =IF('ProductSprint Backlog'!$L240>H$2,'ProductSprint Backlog'!$M240,0) -> 0 | I7: =IF('ProductSprint Backlog'!$L240>I$2,'ProductSprint Backlog'!$M240,0) -> 0 | ... P7: =IF('ProductSprint Backlog'!$L240>P$2,'ProductSprint Backlog'!$M240,0) -> 0
A8: Diseñar el formulario de creación de informe técnico para el administrador y sus validaciones | B8: =IF('ProductSprint Backlog'!$L241>B$2,'ProductSprint Backlog'!$M241,0) -> 1 | C8: =IF('ProductSprint Backlog'!$L241>C$2,'ProductSprint Backlog'!$M241,0) -> 0 | D8: =IF('ProductSprint Backlog'!$L241>D$2,'ProductSprint Backlog'!$M241,0) -> 0 | E8: =IF('ProductSprint Backlog'!$L241>E$2,'ProductSprint Backlog'!$M241,0) -> 0 | F8: =IF('ProductSprint Backlog'!$L241>F$2,'ProductSprint Backlog'!$M241,0) -> 0 | G8: =IF('ProductSprint Backlog'!$L241>G$2,'ProductSprint Backlog'!$M241,0) -> 0 | H8: =IF('ProductSprint Backlog'!$L241>H$2,'ProductSprint Backlog'!$M241,0) -> 0 | I8: =IF('ProductSprint Backlog'!$L241>I$2,'ProductSprint Backlog'!$M241,0) -> 0 | ... P8: =IF('ProductSprint Backlog'!$L241>P$2,'ProductSprint Backlog'!$M241,0) -> 0
A9: Asegurar el registro en auditoria para mantener la trazabilidad de las acciones | B9: =IF('ProductSprint Backlog'!$L242>B$2,'ProductSprint Backlog'!$M242,0) -> 1 | C9: =IF('ProductSprint Backlog'!$L242>C$2,'ProductSprint Backlog'!$M242,0) -> 0 | D9: =IF('ProductSprint Backlog'!$L242>D$2,'ProductSprint Backlog'!$M242,0) -> 0 | E9: =IF('ProductSprint Backlog'!$L242>E$2,'ProductSprint Backlog'!$M242,0) -> 0 | F9: =IF('ProductSprint Backlog'!$L242>F$2,'ProductSprint Backlog'!$M242,0) -> 0 | G9: =IF('ProductSprint Backlog'!$L242>G$2,'ProductSprint Backlog'!$M242,0) -> 0 | H9: =IF('ProductSprint Backlog'!$L242>H$2,'ProductSprint Backlog'!$M242,0) -> 0 | I9: =IF('ProductSprint Backlog'!$L242>I$2,'ProductSprint Backlog'!$M242,0) -> 0 | ... P9: =IF('ProductSprint Backlog'!$L242>P$2,'ProductSprint Backlog'!$M242,0) -> 0
A10: Diseñar y mostrar un mensaje de éxito al completar el proceso, o un mensaje de error si falla una validación | B10: =IF('ProductSprint Backlog'!$L243>B$2,'ProductSprint Backlog'!$M243,0) -> 1 | C10: =IF('ProductSprint Backlog'!$L243>C$2,'ProductSprint Backlog'!$M243,0) -> 1 | D10: =IF('ProductSprint Backlog'!$L243>D$2,'ProductSprint Backlog'!$M243,0) -> 1 | E10: =IF('ProductSprint Backlog'!$L243>E$2,'ProductSprint Backlog'!$M243,0) -> 0 | F10: =IF('ProductSprint Backlog'!$L243>F$2,'ProductSprint Backlog'!$M243,0) -> 0 | G10: =IF('ProductSprint Backlog'!$L243>G$2,'ProductSprint Backlog'!$M243,0) -> 0 | H10: =IF('ProductSprint Backlog'!$L243>H$2,'ProductSprint Backlog'!$M243,0) -> 0 | I10: =IF('ProductSprint Backlog'!$L243>I$2,'ProductSprint Backlog'!$M243,0) -> 0 | ... P10: =IF('ProductSprint Backlog'!$L243>P$2,'ProductSprint Backlog'!$M243,0) -> 0
A11: Diseñar la vista de informe técnico para administrador, incluyendo la información detallada del documento en sí. | B11: =IF('ProductSprint Backlog'!$L244>B$2,'ProductSprint Backlog'!$M244,0) -> 0.5 | C11: =IF('ProductSprint Backlog'!$L244>C$2,'ProductSprint Backlog'!$M244,0) -> 0 | D11: =IF('ProductSprint Backlog'!$L244>D$2,'ProductSprint Backlog'!$M244,0) -> 0 | E11: =IF('ProductSprint Backlog'!$L244>E$2,'ProductSprint Backlog'!$M244,0) -> 0 | F11: =IF('ProductSprint Backlog'!$L244>F$2,'ProductSprint Backlog'!$M244,0) -> 0 | G11: =IF('ProductSprint Backlog'!$L244>G$2,'ProductSprint Backlog'!$M244,0) -> 0 | H11: =IF('ProductSprint Backlog'!$L244>H$2,'ProductSprint Backlog'!$M244,0) -> 0 | I11: =IF('ProductSprint Backlog'!$L244>I$2,'ProductSprint Backlog'!$M244,0) -> 0 | ... P11: =IF('ProductSprint Backlog'!$L244>P$2,'ProductSprint Backlog'!$M244,0) -> 0
A12: Asegurar la visibilidad de los botones de interacción del informe | B12: =IF('ProductSprint Backlog'!$L245>B$2,'ProductSprint Backlog'!$M245,0) -> 0.5 | C12: =IF('ProductSprint Backlog'!$L245>C$2,'ProductSprint Backlog'!$M245,0) -> 0 | D12: =IF('ProductSprint Backlog'!$L245>D$2,'ProductSprint Backlog'!$M245,0) -> 0 | E12: =IF('ProductSprint Backlog'!$L245>E$2,'ProductSprint Backlog'!$M245,0) -> 0 | F12: =IF('ProductSprint Backlog'!$L245>F$2,'ProductSprint Backlog'!$M245,0) -> 0 | G12: =IF('ProductSprint Backlog'!$L245>G$2,'ProductSprint Backlog'!$M245,0) -> 0 | H12: =IF('ProductSprint Backlog'!$L245>H$2,'ProductSprint Backlog'!$M245,0) -> 0 | I12: =IF('ProductSprint Backlog'!$L245>I$2,'ProductSprint Backlog'!$M245,0) -> 0 | ... P12: =IF('ProductSprint Backlog'!$L245>P$2,'ProductSprint Backlog'!$M245,0) -> 0
A13: Incluir el botón de creación de cotización en la vista de administrador. | B13: =IF('ProductSprint Backlog'!$L246>B$2,'ProductSprint Backlog'!$M246,0) -> 1 | C13: =IF('ProductSprint Backlog'!$L246>C$2,'ProductSprint Backlog'!$M246,0) -> 1 | D13: =IF('ProductSprint Backlog'!$L246>D$2,'ProductSprint Backlog'!$M246,0) -> 0 | E13: =IF('ProductSprint Backlog'!$L246>E$2,'ProductSprint Backlog'!$M246,0) -> 0 | F13: =IF('ProductSprint Backlog'!$L246>F$2,'ProductSprint Backlog'!$M246,0) -> 0 | G13: =IF('ProductSprint Backlog'!$L246>G$2,'ProductSprint Backlog'!$M246,0) -> 0 | H13: =IF('ProductSprint Backlog'!$L246>H$2,'ProductSprint Backlog'!$M246,0) -> 0 | I13: =IF('ProductSprint Backlog'!$L246>I$2,'ProductSprint Backlog'!$M246,0) -> 0 | ... P13: =IF('ProductSprint Backlog'!$L246>P$2,'ProductSprint Backlog'!$M246,0) -> 0
A14: Diseñar el formulario de creación de cotización para el administrador y sus validaciones | B14: =IF('ProductSprint Backlog'!$L247>B$2,'ProductSprint Backlog'!$M247,0) -> 1 | C14: =IF('ProductSprint Backlog'!$L247>C$2,'ProductSprint Backlog'!$M247,0) -> 1 | D14: =IF('ProductSprint Backlog'!$L247>D$2,'ProductSprint Backlog'!$M247,0) -> 0 | E14: =IF('ProductSprint Backlog'!$L247>E$2,'ProductSprint Backlog'!$M247,0) -> 0 | F14: =IF('ProductSprint Backlog'!$L247>F$2,'ProductSprint Backlog'!$M247,0) -> 0 | G14: =IF('ProductSprint Backlog'!$L247>G$2,'ProductSprint Backlog'!$M247,0) -> 0 | H14: =IF('ProductSprint Backlog'!$L247>H$2,'ProductSprint Backlog'!$M247,0) -> 0 | I14: =IF('ProductSprint Backlog'!$L247>I$2,'ProductSprint Backlog'!$M247,0) -> 0 | ... P14: =IF('ProductSprint Backlog'!$L247>P$2,'ProductSprint Backlog'!$M247,0) -> 0
A15: Asegurar el registro en auditoria para mantener la trazabilidad de las acciones | B15: =IF('ProductSprint Backlog'!$L248>B$2,'ProductSprint Backlog'!$M248,0) -> 0.5 | C15: =IF('ProductSprint Backlog'!$L248>C$2,'ProductSprint Backlog'!$M248,0) -> 0.5 | D15: =IF('ProductSprint Backlog'!$L248>D$2,'ProductSprint Backlog'!$M248,0) -> 0 | E15: =IF('ProductSprint Backlog'!$L248>E$2,'ProductSprint Backlog'!$M248,0) -> 0 | F15: =IF('ProductSprint Backlog'!$L248>F$2,'ProductSprint Backlog'!$M248,0) -> 0 | G15: =IF('ProductSprint Backlog'!$L248>G$2,'ProductSprint Backlog'!$M248,0) -> 0 | H15: =IF('ProductSprint Backlog'!$L248>H$2,'ProductSprint Backlog'!$M248,0) -> 0 | I15: =IF('ProductSprint Backlog'!$L248>I$2,'ProductSprint Backlog'!$M248,0) -> 0 | ... P15: =IF('ProductSprint Backlog'!$L248>P$2,'ProductSprint Backlog'!$M248,0) -> 0
A16: Diseñar y mostrar un mensaje de éxito al completar el proceso, o un mensaje de error si falla una validación | B16: =IF('ProductSprint Backlog'!$L249>B$2,'ProductSprint Backlog'!$M249,0) -> 0.5 | C16: =IF('ProductSprint Backlog'!$L249>C$2,'ProductSprint Backlog'!$M249,0) -> 0.5 | D16: =IF('ProductSprint Backlog'!$L249>D$2,'ProductSprint Backlog'!$M249,0) -> 0.5 | E16: =IF('ProductSprint Backlog'!$L249>E$2,'ProductSprint Backlog'!$M249,0) -> 0 | F16: =IF('ProductSprint Backlog'!$L249>F$2,'ProductSprint Backlog'!$M249,0) -> 0 | G16: =IF('ProductSprint Backlog'!$L249>G$2,'ProductSprint Backlog'!$M249,0) -> 0 | H16: =IF('ProductSprint Backlog'!$L249>H$2,'ProductSprint Backlog'!$M249,0) -> 0 | I16: =IF('ProductSprint Backlog'!$L249>I$2,'ProductSprint Backlog'!$M249,0) -> 0 | ... P16: =IF('ProductSprint Backlog'!$L249>P$2,'ProductSprint Backlog'!$M249,0) -> 0
A17: Diseñar la vista de cotización para administrador, incluyendo la información detallada del documento en sí. | B17: =IF('ProductSprint Backlog'!$L250>B$2,'ProductSprint Backlog'!$M250,0) -> 1 | C17: =IF('ProductSprint Backlog'!$L250>C$2,'ProductSprint Backlog'!$M250,0) -> 1 | D17: =IF('ProductSprint Backlog'!$L250>D$2,'ProductSprint Backlog'!$M250,0) -> 0 | E17: =IF('ProductSprint Backlog'!$L250>E$2,'ProductSprint Backlog'!$M250,0) -> 0 | F17: =IF('ProductSprint Backlog'!$L250>F$2,'ProductSprint Backlog'!$M250,0) -> 0 | G17: =IF('ProductSprint Backlog'!$L250>G$2,'ProductSprint Backlog'!$M250,0) -> 0 | H17: =IF('ProductSprint Backlog'!$L250>H$2,'ProductSprint Backlog'!$M250,0) -> 0 | I17: =IF('ProductSprint Backlog'!$L250>I$2,'ProductSprint Backlog'!$M250,0) -> 0 | ... P17: =IF('ProductSprint Backlog'!$L250>P$2,'ProductSprint Backlog'!$M250,0) -> 0
A18: Asegurar la visibilidad de los botones de interacción de cotización | B18: =IF('ProductSprint Backlog'!$L251>B$2,'ProductSprint Backlog'!$M251,0) -> 1 | C18: =IF('ProductSprint Backlog'!$L251>C$2,'ProductSprint Backlog'!$M251,0) -> 1 | D18: =IF('ProductSprint Backlog'!$L251>D$2,'ProductSprint Backlog'!$M251,0) -> 0 | E18: =IF('ProductSprint Backlog'!$L251>E$2,'ProductSprint Backlog'!$M251,0) -> 0 | F18: =IF('ProductSprint Backlog'!$L251>F$2,'ProductSprint Backlog'!$M251,0) -> 0 | G18: =IF('ProductSprint Backlog'!$L251>G$2,'ProductSprint Backlog'!$M251,0) -> 0 | H18: =IF('ProductSprint Backlog'!$L251>H$2,'ProductSprint Backlog'!$M251,0) -> 0 | I18: =IF('ProductSprint Backlog'!$L251>I$2,'ProductSprint Backlog'!$M251,0) -> 0 | ... P18: =IF('ProductSprint Backlog'!$L251>P$2,'ProductSprint Backlog'!$M251,0) -> 0
... A47: Asegurar que se actualice la vista de registros de auditoría cada cierto tiempo | B47: =IF('ProductSprint Backlog'!$L280>B$2,'ProductSprint Backlog'!$M280,0) -> 1 | C47: =IF('ProductSprint Backlog'!$L280>C$2,'ProductSprint Backlog'!$M280,0) -> 1 | D47: =IF('ProductSprint Backlog'!$L280>D$2,'ProductSprint Backlog'!$M280,0) -> 1 | E47: =IF('ProductSprint Backlog'!$L280>E$2,'ProductSprint Backlog'!$M280,0) -> 1 | F47: =IF('ProductSprint Backlog'!$L280>F$2,'ProductSprint Backlog'!$M280,0) -> 1 | G47: =IF('ProductSprint Backlog'!$L280>G$2,'ProductSprint Backlog'!$M280,0) -> 1 | H47: =IF('ProductSprint Backlog'!$L280>H$2,'ProductSprint Backlog'!$M280,0) -> 1 | I47: =IF('ProductSprint Backlog'!$L280>I$2,'ProductSprint Backlog'!$M280,0) -> 0 | ... P47: =IF('ProductSprint Backlog'!$L280>P$2,'ProductSprint Backlog'!$M280,0) -> 0

Sheet Aux Esfuerzo Estimado INC3 SPT4
B1: Dia 1 | C1: Dia 2 | D1: Dia 3 | E1: Dia 4 | F1: Dia 5 | G1: Dia 6 | H1: Dia 7 | I1: Dia 8 | J1: Dia 9 | K1: Dia 10 | L1: Dia 11 | M1: Dia 12 | N1: Dia 13 | O1: Dia 14 | P1: Dia 15 | Q1: Dia 16
B2: 45941 | C2: 45942 | D2: 45943 | E2: 45944 | F2: 45945 | G2: 45946 | H2: 45947 | I2: 45948 | J2: 45949 | K2: 45950 | L2: 45951 | M2: 45952 | N2: 45953 | O2: 45954 | P2: 45955 | Q2: 45956 | R2: <------------------ | S2: Modificar esto para que calcular los esfuersos en el tiempo
B3: {=_xlfn.IFS('ProductSprint Backlog'!$F3="", "", AND('ProductSprint Backlog'!$J3>B$2,'ProductSprint Backlog'!$I3<=B$2), 'ProductSprint Backlog'!$F3 / MAX(1, 'ProductSprint Backlog'!$J3-'ProductSprint Backlog'!$I3), AND('ProductSprint Backlog'!$J3=B$2,'ProductSprint Backlog'!$I3=B$2), 'ProductSprint Backlog'!$F3, TRUE, 0)} -> 0 | C3: {=_xlfn.IFS('ProductSprint Backlog'!$F3="", "", AND('ProductSprint Backlog'!$J3>C$2,'ProductSprint Backlog'!$I3<=C$2), 'ProductSprint Backlog'!$F3 / MAX(1, 'ProductSprint Backlog'!$J3-'ProductSprint Backlog'!$I3), AND('ProductSprint Backlog'!$J3=C$2,'ProductSprint Backlog'!$I3=C$2), 'ProductSprint Backlog'!$F3, TRUE, 0)} -> 0 | D3: {=_xlfn.IFS('ProductSprint Backlog'!$F3="", "", AND('ProductSprint Backlog'!$J3>D$2,'ProductSprint Backlog'!$I3<=D$2), 'ProductSprint Backlog'!$F3 / MAX(1, 'ProductSprint Backlog'!$J3-'ProductSprint Backlog'!$I3), AND('ProductSprint Backlog'!$J3=D$2,'ProductSprint Backlog'!$I3=D$2), 'ProductSprint Backlog'!$F3, TRUE, 0)} -> 0 | E3: {=_xlfn.IFS('ProductSprint Backlog'!$F3="", "", AND('ProductSprint Backlog'!$J3>E$2,'ProductSprint Backlog'!$I3<=E$2), 'ProductSprint Backlog'!$F3 / MAX(1, 'ProductSprint Backlog'!$J3-'ProductSprint Backlog'!$I3), AND('ProductSprint Backlog'!$J3=E$2,'ProductSprint Backlog'!$I3=E$2), 'ProductSprint Backlog'!$F3, TRUE, 0)} -> 0 | F3: {=_xlfn.IFS('ProductSprint Backlog'!$F3="", "", AND('ProductSprint Backlog'!$J3>F$2,'ProductSprint Backlog'!$I3<=F$2), 'ProductSprint Backlog'!$F3 / MAX(1, 'ProductSprint Backlog'!$J3-'ProductSprint Backlog'!$I3), AND('ProductSprint Backlog'!$J3=F$2,'ProductSprint Backlog'!$I3=F$2), 'ProductSprint Backlog'!$F3, TRUE, 0)} -> 0 | G3: {=_xlfn.IFS('ProductSprint Backlog'!$F3="", "", AND('ProductSprint Backlog'!$J3>G$2,'ProductSprint Backlog'!$I3<=G$2), 'ProductSprint Backlog'!$F3 / MAX(1, 'ProductSprint Backlog'!$J3-'ProductSprint Backlog'!$I3), AND('ProductSprint Backlog'!$J3=G$2,'ProductSprint Backlog'!$I3=G$2), 'ProductSprint Backlog'!$F3, TRUE, 0)} -> 0 | H3: {=_xlfn.IFS('ProductSprint Backlog'!$F3="", "", AND('ProductSprint Backlog'!$J3>H$2,'ProductSprint Backlog'!$I3<=H$2), 'ProductSprint Backlog'!$F3 / MAX(1, 'ProductSprint Backlog'!$J3-'ProductSprint Backlog'!$I3), AND('ProductSprint Backlog'!$J3=H$2,'ProductSprint Backlog'!$I3=H$2), 'ProductSprint Backlog'!$F3, TRUE, 0)} -> 0 | I3: {=_xlfn.IFS('ProductSprint Backlog'!$F3="", "", AND('ProductSprint Backlog'!$J3>I$2,'ProductSprint Backlog'!$I3<=I$2), 'ProductSprint Backlog'!$F3 / MAX(1, 'ProductSprint Backlog'!$J3-'ProductSprint Backlog'!$I3), AND('ProductSprint Backlog'!$J3=I$2,'ProductSprint Backlog'!$I3=I$2), 'ProductSprint Backlog'!$F3, TRUE, 0)} -> 0 | ... Q3: {=_xlfn.IFS('ProductSprint Backlog'!$F3="", "", AND('ProductSprint Backlog'!$J3>Q$2,'ProductSprint Backlog'!$I3<=Q$2), 'ProductSprint Backlog'!$F3 / MAX(1, 'ProductSprint Backlog'!$J3-'ProductSprint Backlog'!$I3), AND('ProductSprint Backlog'!$J3=Q$2,'ProductSprint Backlog'!$I3=Q$2), 'ProductSprint Backlog'!$F3, TRUE, 0)} -> 0
B4: {=_xlfn.IFS('ProductSprint Backlog'!$F4="", "", AND('ProductSprint Backlog'!$J4>B$2,'ProductSprint Backlog'!$I4<=B$2), 'ProductSprint Backlog'!$F4 / MAX(1, 'ProductSprint Backlog'!$J4-'ProductSprint Backlog'!$I4), AND('ProductSprint Backlog'!$J4=B$2,'ProductSprint Backlog'!$I4=B$2), 'ProductSprint Backlog'!$F4, TRUE, 0)} -> 0 | C4: {=_xlfn.IFS('ProductSprint Backlog'!$F4="", "", AND('ProductSprint Backlog'!$J4>C$2,'ProductSprint Backlog'!$I4<=C$2), 'ProductSprint Backlog'!$F4 / MAX(1, 'ProductSprint Backlog'!$J4-'ProductSprint Backlog'!$I4), AND('ProductSprint Backlog'!$J4=C$2,'ProductSprint Backlog'!$I4=C$2), 'ProductSprint Backlog'!$F4, TRUE, 0)} -> 0 | D4: {=_xlfn.IFS('ProductSprint Backlog'!$F4="", "", AND('ProductSprint Backlog'!$J4>D$2,'ProductSprint Backlog'!$I4<=D$2), 'ProductSprint Backlog'!$F4 / MAX(1, 'ProductSprint Backlog'!$J4-'ProductSprint Backlog'!$I4), AND('ProductSprint Backlog'!$J4=D$2,'ProductSprint Backlog'!$I4=D$2), 'ProductSprint Backlog'!$F4, TRUE, 0)} -> 0 | E4: {=_xlfn.IFS('ProductSprint Backlog'!$F4="", "", AND('ProductSprint Backlog'!$J4>E$2,'ProductSprint Backlog'!$I4<=E$2), 'ProductSprint Backlog'!$F4 / MAX(1, 'ProductSprint Backlog'!$J4-'ProductSprint Backlog'!$I4), AND('ProductSprint Backlog'!$J4=E$2,'ProductSprint Backlog'!$I4=E$2), 'ProductSprint Backlog'!$F4, TRUE, 0)} -> 0 | F4: {=_xlfn.IFS('ProductSprint Backlog'!$F4="", "", AND('ProductSprint Backlog'!$J4>F$2,'ProductSprint Backlog'!$I4<=F$2), 'ProductSprint Backlog'!$F4 / MAX(1, 'ProductSprint Backlog'!$J4-'ProductSprint Backlog'!$I4), AND('ProductSprint Backlog'!$J4=F$2,'ProductSprint Backlog'!$I4=F$2), 'ProductSprint Backlog'!$F4, TRUE, 0)} -> 0 | G4: {=_xlfn.IFS('ProductSprint Backlog'!$F4="", "", AND('ProductSprint Backlog'!$J4>G$2,'ProductSprint Backlog'!$I4<=G$2), 'ProductSprint Backlog'!$F4 / MAX(1, 'ProductSprint Backlog'!$J4-'ProductSprint Backlog'!$I4), AND('ProductSprint Backlog'!$J4=G$2,'ProductSprint Backlog'!$I4=G$2), 'ProductSprint Backlog'!$F4, TRUE, 0)} -> 0 | H4: {=_xlfn.IFS('ProductSprint Backlog'!$F4="", "", AND('ProductSprint Backlog'!$J4>H$2,'ProductSprint Backlog'!$I4<=H$2), 'ProductSprint Backlog'!$F4 / MAX(1, 'ProductSprint Backlog'!$J4-'ProductSprint Backlog'!$I4), AND('ProductSprint Backlog'!$J4=H$2,'ProductSprint Backlog'!$I4=H$2), 'ProductSprint Backlog'!$F4, TRUE, 0)} -> 0 | I4: {=_xlfn.IFS('ProductSprint Backlog'!$F4="", "", AND('ProductSprint Backlog'!$J4>I$2,'ProductSprint Backlog'!$I4<=I$2), 'ProductSprint Backlog'!$F4 / MAX(1, 'ProductSprint Backlog'!$J4-'ProductSprint Backlog'!$I4), AND('ProductSprint Backlog'!$J4=I$2,'ProductSprint Backlog'!$I4=I$2), 'ProductSprint Backlog'!$F4, TRUE, 0)} -> 0 | ... Q4: {=_xlfn.IFS('ProductSprint Backlog'!$F4="", "", AND('ProductSprint Backlog'!$J4>Q$2,'ProductSprint Backlog'!$I4<=Q$2), 'ProductSprint Backlog'!$F4 / MAX(1, 'ProductSprint Backlog'!$J4-'ProductSprint Backlog'!$I4), AND('ProductSprint Backlog'!$J4=Q$2,'ProductSprint Backlog'!$I4=Q$2), 'ProductSprint Backlog'!$F4, TRUE, 0)} -> 0
B5: {=_xlfn.IFS('ProductSprint Backlog'!$F5="", "", AND('ProductSprint Backlog'!$J5>B$2,'ProductSprint Backlog'!$I5<=B$2), 'ProductSprint Backlog'!$F5 / MAX(1, 'ProductSprint Backlog'!$J5-'ProductSprint Backlog'!$I5), AND('ProductSprint Backlog'!$J5=B$2,'ProductSprint Backlog'!$I5=B$2), 'ProductSprint Backlog'!$F5, TRUE, 0)} -> 0 | C5: {=_xlfn.IFS('ProductSprint Backlog'!$F5="", "", AND('ProductSprint Backlog'!$J5>C$2,'ProductSprint Backlog'!$I5<=C$2), 'ProductSprint Backlog'!$F5 / MAX(1, 'ProductSprint Backlog'!$J5-'ProductSprint Backlog'!$I5), AND('ProductSprint Backlog'!$J5=C$2,'ProductSprint Backlog'!$I5=C$2), 'ProductSprint Backlog'!$F5, TRUE, 0)} -> 0 | D5: {=_xlfn.IFS('ProductSprint Backlog'!$F5="", "", AND('ProductSprint Backlog'!$J5>D$2,'ProductSprint Backlog'!$I5<=D$2), 'ProductSprint Backlog'!$F5 / MAX(1, 'ProductSprint Backlog'!$J5-'ProductSprint Backlog'!$I5), AND('ProductSprint Backlog'!$J5=D$2,'ProductSprint Backlog'!$I5=D$2), 'ProductSprint Backlog'!$F5, TRUE, 0)} -> 0 | E5: {=_xlfn.IFS('ProductSprint Backlog'!$F5="", "", AND('ProductSprint Backlog'!$J5>E$2,'ProductSprint Backlog'!$I5<=E$2), 'ProductSprint Backlog'!$F5 / MAX(1, 'ProductSprint Backlog'!$J5-'ProductSprint Backlog'!$I5), AND('ProductSprint Backlog'!$J5=E$2,'ProductSprint Backlog'!$I5=E$2), 'ProductSprint Backlog'!$F5, TRUE, 0)} -> 0 | F5: {=_xlfn.IFS('ProductSprint Backlog'!$F5="", "", AND('ProductSprint Backlog'!$J5>F$2,'ProductSprint Backlog'!$I5<=F$2), 'ProductSprint Backlog'!$F5 / MAX(1, 'ProductSprint Backlog'!$J5-'ProductSprint Backlog'!$I5), AND('ProductSprint Backlog'!$J5=F$2,'ProductSprint Backlog'!$I5=F$2), 'ProductSprint Backlog'!$F5, TRUE, 0)} -> 0 | G5: {=_xlfn.IFS('ProductSprint Backlog'!$F5="", "", AND('ProductSprint Backlog'!$J5>G$2,'ProductSprint Backlog'!$I5<=G$2), 'ProductSprint Backlog'!$F5 / MAX(1, 'ProductSprint Backlog'!$J5-'ProductSprint Backlog'!$I5), AND('ProductSprint Backlog'!$J5=G$2,'ProductSprint Backlog'!$I5=G$2), 'ProductSprint Backlog'!$F5, TRUE, 0)} -> 0 | H5: {=_xlfn.IFS('ProductSprint Backlog'!$F5="", "", AND('ProductSprint Backlog'!$J5>H$2,'ProductSprint Backlog'!$I5<=H$2), 'ProductSprint Backlog'!$F5 / MAX(1, 'ProductSprint Backlog'!$J5-'ProductSprint Backlog'!$I5), AND('ProductSprint Backlog'!$J5=H$2,'ProductSprint Backlog'!$I5=H$2), 'ProductSprint Backlog'!$F5, TRUE, 0)} -> 0 | I5: {=_xlfn.IFS('ProductSprint Backlog'!$F5="", "", AND('ProductSprint Backlog'!$J5>I$2,'ProductSprint Backlog'!$I5<=I$2), 'ProductSprint Backlog'!$F5 / MAX(1, 'ProductSprint Backlog'!$J5-'ProductSprint Backlog'!$I5), AND('ProductSprint Backlog'!$J5=I$2,'ProductSprint Backlog'!$I5=I$2), 'ProductSprint Backlog'!$F5, TRUE, 0)} -> 0 | ... Q5: {=_xlfn.IFS('ProductSprint Backlog'!$F5="", "", AND('ProductSprint Backlog'!$J5>Q$2,'ProductSprint Backlog'!$I5<=Q$2), 'ProductSprint Backlog'!$F5 / MAX(1, 'ProductSprint Backlog'!$J5-'ProductSprint Backlog'!$I5), AND('ProductSprint Backlog'!$J5=Q$2,'ProductSprint Backlog'!$I5=Q$2), 'ProductSprint Backlog'!$F5, TRUE, 0)} -> 0
B6: {=_xlfn.IFS('ProductSprint Backlog'!$F6="", "", AND('ProductSprint Backlog'!$J6>B$2,'ProductSprint Backlog'!$I6<=B$2), 'ProductSprint Backlog'!$F6 / MAX(1, 'ProductSprint Backlog'!$J6-'ProductSprint Backlog'!$I6), AND('ProductSprint Backlog'!$J6=B$2,'ProductSprint Backlog'!$I6=B$2), 'ProductSprint Backlog'!$F6, TRUE, 0)} -> 0 | C6: {=_xlfn.IFS('ProductSprint Backlog'!$F6="", "", AND('ProductSprint Backlog'!$J6>C$2,'ProductSprint Backlog'!$I6<=C$2), 'ProductSprint Backlog'!$F6 / MAX(1, 'ProductSprint Backlog'!$J6-'ProductSprint Backlog'!$I6), AND('ProductSprint Backlog'!$J6=C$2,'ProductSprint Backlog'!$I6=C$2), 'ProductSprint Backlog'!$F6, TRUE, 0)} -> 0 | D6: {=_xlfn.IFS('ProductSprint Backlog'!$F6="", "", AND('ProductSprint Backlog'!$J6>D$2,'ProductSprint Backlog'!$I6<=D$2), 'ProductSprint Backlog'!$F6 / MAX(1, 'ProductSprint Backlog'!$J6-'ProductSprint Backlog'!$I6), AND('ProductSprint Backlog'!$J6=D$2,'ProductSprint Backlog'!$I6=D$2), 'ProductSprint Backlog'!$F6, TRUE, 0)} -> 0 | E6: {=_xlfn.IFS('ProductSprint Backlog'!$F6="", "", AND('ProductSprint Backlog'!$J6>E$2,'ProductSprint Backlog'!$I6<=E$2), 'ProductSprint Backlog'!$F6 / MAX(1, 'ProductSprint Backlog'!$J6-'ProductSprint Backlog'!$I6), AND('ProductSprint Backlog'!$J6=E$2,'ProductSprint Backlog'!$I6=E$2), 'ProductSprint Backlog'!$F6, TRUE, 0)} -> 0 | F6: {=_xlfn.IFS('ProductSprint Backlog'!$F6="", "", AND('ProductSprint Backlog'!$J6>F$2,'ProductSprint Backlog'!$I6<=F$2), 'ProductSprint Backlog'!$F6 / MAX(1, 'ProductSprint Backlog'!$J6-'ProductSprint Backlog'!$I6), AND('ProductSprint Backlog'!$J6=F$2,'ProductSprint Backlog'!$I6=F$2), 'ProductSprint Backlog'!$F6, TRUE, 0)} -> 0 | G6: {=_xlfn.IFS('ProductSprint Backlog'!$F6="", "", AND('ProductSprint Backlog'!$J6>G$2,'ProductSprint Backlog'!$I6<=G$2), 'ProductSprint Backlog'!$F6 / MAX(1, 'ProductSprint Backlog'!$J6-'ProductSprint Backlog'!$I6), AND('ProductSprint Backlog'!$J6=G$2,'ProductSprint Backlog'!$I6=G$2), 'ProductSprint Backlog'!$F6, TRUE, 0)} -> 0 | H6: {=_xlfn.IFS('ProductSprint Backlog'!$F6="", "", AND('ProductSprint Backlog'!$J6>H$2,'ProductSprint Backlog'!$I6<=H$2), 'ProductSprint Backlog'!$F6 / MAX(1, 'ProductSprint Backlog'!$J6-'ProductSprint Backlog'!$I6), AND('ProductSprint Backlog'!$J6=H$2,'ProductSprint Backlog'!$I6=H$2), 'ProductSprint Backlog'!$F6, TRUE, 0)} -> 0 | I6: {=_xlfn.IFS('ProductSprint Backlog'!$F6="", "", AND('ProductSprint Backlog'!$J6>I$2,'ProductSprint Backlog'!$I6<=I$2), 'ProductSprint Backlog'!$F6 / MAX(1, 'ProductSprint Backlog'!$J6-'ProductSprint Backlog'!$I6), AND('ProductSprint Backlog'!$J6=I$2,'ProductSprint Backlog'!$I6=I$2), 'ProductSprint Backlog'!$F6, TRUE, 0)} -> 0 | ... Q6: {=_xlfn.IFS('ProductSprint Backlog'!$F6="", "", AND('ProductSprint Backlog'!$J6>Q$2,'ProductSprint Backlog'!$I6<=Q$2), 'ProductSprint Backlog'!$F6 / MAX(1, 'ProductSprint Backlog'!$J6-'ProductSprint Backlog'!$I6), AND('ProductSprint Backlog'!$J6=Q$2,'ProductSprint Backlog'!$I6=Q$2), 'ProductSprint Backlog'!$F6, TRUE, 0)} -> 0
B7: {=_xlfn.IFS('ProductSprint Backlog'!$F7="", "", AND('ProductSprint Backlog'!$J7>B$2,'ProductSprint Backlog'!$I7<=B$2), 'ProductSprint Backlog'!$F7 / MAX(1, 'ProductSprint Backlog'!$J7-'ProductSprint Backlog'!$I7), AND('ProductSprint Backlog'!$J7=B$2,'ProductSprint Backlog'!$I7=B$2), 'ProductSprint Backlog'!$F7, TRUE, 0)} | C7: {=_xlfn.IFS('ProductSprint Backlog'!$F7="", "", AND('ProductSprint Backlog'!$J7>C$2,'ProductSprint Backlog'!$I7<=C$2), 'ProductSprint Backlog'!$F7 / MAX(1, 'ProductSprint Backlog'!$J7-'ProductSprint Backlog'!$I7), AND('ProductSprint Backlog'!$J7=C$2,'ProductSprint Backlog'!$I7=C$2), 'ProductSprint Backlog'!$F7, TRUE, 0)} | D7: {=_xlfn.IFS('ProductSprint Backlog'!$F7="", "", AND('ProductSprint Backlog'!$J7>D$2,'ProductSprint Backlog'!$I7<=D$2), 'ProductSprint Backlog'!$F7 / MAX(1, 'ProductSprint Backlog'!$J7-'ProductSprint Backlog'!$I7), AND('ProductSprint Backlog'!$J7=D$2,'ProductSprint Backlog'!$I7=D$2), 'ProductSprint Backlog'!$F7, TRUE, 0)} | E7: {=_xlfn.IFS('ProductSprint Backlog'!$F7="", "", AND('ProductSprint Backlog'!$J7>E$2,'ProductSprint Backlog'!$I7<=E$2), 'ProductSprint Backlog'!$F7 / MAX(1, 'ProductSprint Backlog'!$J7-'ProductSprint Backlog'!$I7), AND('ProductSprint Backlog'!$J7=E$2,'ProductSprint Backlog'!$I7=E$2), 'ProductSprint Backlog'!$F7, TRUE, 0)} | F7: {=_xlfn.IFS('ProductSprint Backlog'!$F7="", "", AND('ProductSprint Backlog'!$J7>F$2,'ProductSprint Backlog'!$I7<=F$2), 'ProductSprint Backlog'!$F7 / MAX(1, 'ProductSprint Backlog'!$J7-'ProductSprint Backlog'!$I7), AND('ProductSprint Backlog'!$J7=F$2,'ProductSprint Backlog'!$I7=F$2), 'ProductSprint Backlog'!$F7, TRUE, 0)} | G7: {=_xlfn.IFS('ProductSprint Backlog'!$F7="", "", AND('ProductSprint Backlog'!$J7>G$2,'ProductSprint Backlog'!$I7<=G$2), 'ProductSprint Backlog'!$F7 / MAX(1, 'ProductSprint Backlog'!$J7-'ProductSprint Backlog'!$I7), AND('ProductSprint Backlog'!$J7=G$2,'ProductSprint Backlog'!$I7=G$2), 'ProductSprint Backlog'!$F7, TRUE, 0)} | H7: {=_xlfn.IFS('ProductSprint Backlog'!$F7="", "", AND('ProductSprint Backlog'!$J7>H$2,'ProductSprint Backlog'!$I7<=H$2), 'ProductSprint Backlog'!$F7 / MAX(1, 'ProductSprint Backlog'!$J7-'ProductSprint Backlog'!$I7), AND('ProductSprint Backlog'!$J7=H$2,'ProductSprint Backlog'!$I7=H$2), 'ProductSprint Backlog'!$F7, TRUE, 0)} | I7: {=_xlfn.IFS('ProductSprint Backlog'!$F7="", "", AND('ProductSprint Backlog'!$J7>I$2,'ProductSprint Backlog'!$I7<=I$2), 'ProductSprint Backlog'!$F7 / MAX(1, 'ProductSprint Backlog'!$J7-'ProductSprint Backlog'!$I7), AND('ProductSprint Backlog'!$J7=I$2,'ProductSprint Backlog'!$I7=I$2), 'ProductSprint Backlog'!$F7, TRUE, 0)} | ... Q7: {=_xlfn.IFS('ProductSprint Backlog'!$F7="", "", AND('ProductSprint Backlog'!$J7>Q$2,'ProductSprint Backlog'!$I7<=Q$2), 'ProductSprint Backlog'!$F7 / MAX(1, 'ProductSprint Backlog'!$J7-'ProductSprint Backlog'!$I7), AND('ProductSprint Backlog'!$J7=Q$2,'ProductSprint Backlog'!$I7=Q$2), 'ProductSprint Backlog'!$F7, TRUE, 0)}
B8: {=_xlfn.IFS('ProductSprint Backlog'!$F8="", "", AND('ProductSprint Backlog'!$J8>B$2,'ProductSprint Backlog'!$I8<=B$2), 'ProductSprint Backlog'!$F8 / MAX(1, 'ProductSprint Backlog'!$J8-'ProductSprint Backlog'!$I8), AND('ProductSprint Backlog'!$J8=B$2,'ProductSprint Backlog'!$I8=B$2), 'ProductSprint Backlog'!$F8, TRUE, 0)} -> 0 | C8: {=_xlfn.IFS('ProductSprint Backlog'!$F8="", "", AND('ProductSprint Backlog'!$J8>C$2,'ProductSprint Backlog'!$I8<=C$2), 'ProductSprint Backlog'!$F8 / MAX(1, 'ProductSprint Backlog'!$J8-'ProductSprint Backlog'!$I8), AND('ProductSprint Backlog'!$J8=C$2,'ProductSprint Backlog'!$I8=C$2), 'ProductSprint Backlog'!$F8, TRUE, 0)} -> 0 | D8: {=_xlfn.IFS('ProductSprint Backlog'!$F8="", "", AND('ProductSprint Backlog'!$J8>D$2,'ProductSprint Backlog'!$I8<=D$2), 'ProductSprint Backlog'!$F8 / MAX(1, 'ProductSprint Backlog'!$J8-'ProductSprint Backlog'!$I8), AND('ProductSprint Backlog'!$J8=D$2,'ProductSprint Backlog'!$I8=D$2), 'ProductSprint Backlog'!$F8, TRUE, 0)} -> 0 | E8: {=_xlfn.IFS('ProductSprint Backlog'!$F8="", "", AND('ProductSprint Backlog'!$J8>E$2,'ProductSprint Backlog'!$I8<=E$2), 'ProductSprint Backlog'!$F8 / MAX(1, 'ProductSprint Backlog'!$J8-'ProductSprint Backlog'!$I8), AND('ProductSprint Backlog'!$J8=E$2,'ProductSprint Backlog'!$I8=E$2), 'ProductSprint Backlog'!$F8, TRUE, 0)} -> 0 | F8: {=_xlfn.IFS('ProductSprint Backlog'!$F8="", "", AND('ProductSprint Backlog'!$J8>F$2,'ProductSprint Backlog'!$I8<=F$2), 'ProductSprint Backlog'!$F8 / MAX(1, 'ProductSprint Backlog'!$J8-'ProductSprint Backlog'!$I8), AND('ProductSprint Backlog'!$J8=F$2,'ProductSprint Backlog'!$I8=F$2), 'ProductSprint Backlog'!$F8, TRUE, 0)} -> 0 | G8: {=_xlfn.IFS('ProductSprint Backlog'!$F8="", "", AND('ProductSprint Backlog'!$J8>G$2,'ProductSprint Backlog'!$I8<=G$2), 'ProductSprint Backlog'!$F8 / MAX(1, 'ProductSprint Backlog'!$J8-'ProductSprint Backlog'!$I8), AND('ProductSprint Backlog'!$J8=G$2,'ProductSprint Backlog'!$I8=G$2), 'ProductSprint Backlog'!$F8, TRUE, 0)} -> 0 | H8: {=_xlfn.IFS('ProductSprint Backlog'!$F8="", "", AND('ProductSprint Backlog'!$J8>H$2,'ProductSprint Backlog'!$I8<=H$2), 'ProductSprint Backlog'!$F8 / MAX(1, 'ProductSprint Backlog'!$J8-'ProductSprint Backlog'!$I8), AND('ProductSprint Backlog'!$J8=H$2,'ProductSprint Backlog'!$I8=H$2), 'ProductSprint Backlog'!$F8, TRUE, 0)} -> 0 | I8: {=_xlfn.IFS('ProductSprint Backlog'!$F8="", "", AND('ProductSprint Backlog'!$J8>I$2,'ProductSprint Backlog'!$I8<=I$2), 'ProductSprint Backlog'!$F8 / MAX(1, 'ProductSprint Backlog'!$J8-'ProductSprint Backlog'!$I8), AND('ProductSprint Backlog'!$J8=I$2,'ProductSprint Backlog'!$I8=I$2), 'ProductSprint Backlog'!$F8, TRUE, 0)} -> 0 | ... Q8: {=_xlfn.IFS('ProductSprint Backlog'!$F8="", "", AND('ProductSprint Backlog'!$J8>Q$2,'ProductSprint Backlog'!$I8<=Q$2), 'ProductSprint Backlog'!$F8 / MAX(1, 'ProductSprint Backlog'!$J8-'ProductSprint Backlog'!$I8), AND('ProductSprint Backlog'!$J8=Q$2,'ProductSprint Backlog'!$I8=Q$2), 'ProductSprint Backlog'!$F8, TRUE, 0)} -> 0
B9: {=_xlfn.IFS('ProductSprint Backlog'!$F9="", "", AND('ProductSprint Backlog'!$J9>B$2,'ProductSprint Backlog'!$I9<=B$2), 'ProductSprint Backlog'!$F9 / MAX(1, 'ProductSprint Backlog'!$J9-'ProductSprint Backlog'!$I9), AND('ProductSprint Backlog'!$J9=B$2,'ProductSprint Backlog'!$I9=B$2), 'ProductSprint Backlog'!$F9, TRUE, 0)} -> 0 | C9: {=_xlfn.IFS('ProductSprint Backlog'!$F9="", "", AND('ProductSprint Backlog'!$J9>C$2,'ProductSprint Backlog'!$I9<=C$2), 'ProductSprint Backlog'!$F9 / MAX(1, 'ProductSprint Backlog'!$J9-'ProductSprint Backlog'!$I9), AND('ProductSprint Backlog'!$J9=C$2,'ProductSprint Backlog'!$I9=C$2), 'ProductSprint Backlog'!$F9, TRUE, 0)} -> 0 | D9: {=_xlfn.IFS('ProductSprint Backlog'!$F9="", "", AND('ProductSprint Backlog'!$J9>D$2,'ProductSprint Backlog'!$I9<=D$2), 'ProductSprint Backlog'!$F9 / MAX(1, 'ProductSprint Backlog'!$J9-'ProductSprint Backlog'!$I9), AND('ProductSprint Backlog'!$J9=D$2,'ProductSprint Backlog'!$I9=D$2), 'ProductSprint Backlog'!$F9, TRUE, 0)} -> 0 | E9: {=_xlfn.IFS('ProductSprint Backlog'!$F9="", "", AND('ProductSprint Backlog'!$J9>E$2,'ProductSprint Backlog'!$I9<=E$2), 'ProductSprint Backlog'!$F9 / MAX(1, 'ProductSprint Backlog'!$J9-'ProductSprint Backlog'!$I9), AND('ProductSprint Backlog'!$J9=E$2,'ProductSprint Backlog'!$I9=E$2), 'ProductSprint Backlog'!$F9, TRUE, 0)} -> 0 | F9: {=_xlfn.IFS('ProductSprint Backlog'!$F9="", "", AND('ProductSprint Backlog'!$J9>F$2,'ProductSprint Backlog'!$I9<=F$2), 'ProductSprint Backlog'!$F9 / MAX(1, 'ProductSprint Backlog'!$J9-'ProductSprint Backlog'!$I9), AND('ProductSprint Backlog'!$J9=F$2,'ProductSprint Backlog'!$I9=F$2), 'ProductSprint Backlog'!$F9, TRUE, 0)} -> 0 | G9: {=_xlfn.IFS('ProductSprint Backlog'!$F9="", "", AND('ProductSprint Backlog'!$J9>G$2,'ProductSprint Backlog'!$I9<=G$2), 'ProductSprint Backlog'!$F9 / MAX(1, 'ProductSprint Backlog'!$J9-'ProductSprint Backlog'!$I9), AND('ProductSprint Backlog'!$J9=G$2,'ProductSprint Backlog'!$I9=G$2), 'ProductSprint Backlog'!$F9, TRUE, 0)} -> 0 | H9: {=_xlfn.IFS('ProductSprint Backlog'!$F9="", "", AND('ProductSprint Backlog'!$J9>H$2,'ProductSprint Backlog'!$I9<=H$2), 'ProductSprint Backlog'!$F9 / MAX(1, 'ProductSprint Backlog'!$J9-'ProductSprint Backlog'!$I9), AND('ProductSprint Backlog'!$J9=H$2,'ProductSprint Backlog'!$I9=H$2), 'ProductSprint Backlog'!$F9, TRUE, 0)} -> 0 | I9: {=_xlfn.IFS('ProductSprint Backlog'!$F9="", "", AND('ProductSprint Backlog'!$J9>I$2,'ProductSprint Backlog'!$I9<=I$2), 'ProductSprint Backlog'!$F9 / MAX(1, 'ProductSprint Backlog'!$J9-'ProductSprint Backlog'!$I9), AND('ProductSprint Backlog'!$J9=I$2,'ProductSprint Backlog'!$I9=I$2), 'ProductSprint Backlog'!$F9, TRUE, 0)} -> 0 | ... Q9: {=_xlfn.IFS('ProductSprint Backlog'!$F9="", "", AND('ProductSprint Backlog'!$J9>Q$2,'ProductSprint Backlog'!$I9<=Q$2), 'ProductSprint Backlog'!$F9 / MAX(1, 'ProductSprint Backlog'!$J9-'ProductSprint Backlog'!$I9), AND('ProductSprint Backlog'!$J9=Q$2,'ProductSprint Backlog'!$I9=Q$2), 'ProductSprint Backlog'!$F9, TRUE, 0)} -> 0
B10: {=_xlfn.IFS('ProductSprint Backlog'!$F10="", "", AND('ProductSprint Backlog'!$J10>B$2,'ProductSprint Backlog'!$I10<=B$2), 'ProductSprint Backlog'!$F10 / MAX(1, 'ProductSprint Backlog'!$J10-'ProductSprint Backlog'!$I10), AND('ProductSprint Backlog'!$J10=B$2,'ProductSprint Backlog'!$I10=B$2), 'ProductSprint Backlog'!$F10, TRUE, 0)} -> 0 | C10: {=_xlfn.IFS('ProductSprint Backlog'!$F10="", "", AND('ProductSprint Backlog'!$J10>C$2,'ProductSprint Backlog'!$I10<=C$2), 'ProductSprint Backlog'!$F10 / MAX(1, 'ProductSprint Backlog'!$J10-'ProductSprint Backlog'!$I10), AND('ProductSprint Backlog'!$J10=C$2,'ProductSprint Backlog'!$I10=C$2), 'ProductSprint Backlog'!$F10, TRUE, 0)} -> 0 | D10: {=_xlfn.IFS('ProductSprint Backlog'!$F10="", "", AND('ProductSprint Backlog'!$J10>D$2,'ProductSprint Backlog'!$I10<=D$2), 'ProductSprint Backlog'!$F10 / MAX(1, 'ProductSprint Backlog'!$J10-'ProductSprint Backlog'!$I10), AND('ProductSprint Backlog'!$J10=D$2,'ProductSprint Backlog'!$I10=D$2), 'ProductSprint Backlog'!$F10, TRUE, 0)} -> 0 | E10: {=_xlfn.IFS('ProductSprint Backlog'!$F10="", "", AND('ProductSprint Backlog'!$J10>E$2,'ProductSprint Backlog'!$I10<=E$2), 'ProductSprint Backlog'!$F10 / MAX(1, 'ProductSprint Backlog'!$J10-'ProductSprint Backlog'!$I10), AND('ProductSprint Backlog'!$J10=E$2,'ProductSprint Backlog'!$I10=E$2), 'ProductSprint Backlog'!$F10, TRUE, 0)} -> 0 | F10: {=_xlfn.IFS('ProductSprint Backlog'!$F10="", "", AND('ProductSprint Backlog'!$J10>F$2,'ProductSprint Backlog'!$I10<=F$2), 'ProductSprint Backlog'!$F10 / MAX(1, 'ProductSprint Backlog'!$J10-'ProductSprint Backlog'!$I10), AND('ProductSprint Backlog'!$J10=F$2,'ProductSprint Backlog'!$I10=F$2), 'ProductSprint Backlog'!$F10, TRUE, 0)} -> 0 | G10: {=_xlfn.IFS('ProductSprint Backlog'!$F10="", "", AND('ProductSprint Backlog'!$J10>G$2,'ProductSprint Backlog'!$I10<=G$2), 'ProductSprint Backlog'!$F10 / MAX(1, 'ProductSprint Backlog'!$J10-'ProductSprint Backlog'!$I10), AND('ProductSprint Backlog'!$J10=G$2,'ProductSprint Backlog'!$I10=G$2), 'ProductSprint Backlog'!$F10, TRUE, 0)} -> 0 | H10: {=_xlfn.IFS('ProductSprint Backlog'!$F10="", "", AND('ProductSprint Backlog'!$J10>H$2,'ProductSprint Backlog'!$I10<=H$2), 'ProductSprint Backlog'!$F10 / MAX(1, 'ProductSprint Backlog'!$J10-'ProductSprint Backlog'!$I10), AND('ProductSprint Backlog'!$J10=H$2,'ProductSprint Backlog'!$I10=H$2), 'ProductSprint Backlog'!$F10, TRUE, 0)} -> 0 | I10: {=_xlfn.IFS('ProductSprint Backlog'!$F10="", "", AND('ProductSprint Backlog'!$J10>I$2,'ProductSprint Backlog'!$I10<=I$2), 'ProductSprint Backlog'!$F10 / MAX(1, 'ProductSprint Backlog'!$J10-'ProductSprint Backlog'!$I10), AND('ProductSprint Backlog'!$J10=I$2,'ProductSprint Backlog'!$I10=I$2), 'ProductSprint Backlog'!$F10, TRUE, 0)} -> 0 | ... Q10: {=_xlfn.IFS('ProductSprint Backlog'!$F10="", "", AND('ProductSprint Backlog'!$J10>Q$2,'ProductSprint Backlog'!$I10<=Q$2), 'ProductSprint Backlog'!$F10 / MAX(1, 'ProductSprint Backlog'!$J10-'ProductSprint Backlog'!$I10), AND('ProductSprint Backlog'!$J10=Q$2,'ProductSprint Backlog'!$I10=Q$2), 'ProductSprint Backlog'!$F10, TRUE, 0)} -> 0
B11: {=_xlfn.IFS('ProductSprint Backlog'!$F11="", "", AND('ProductSprint Backlog'!$J11>B$2,'ProductSprint Backlog'!$I11<=B$2), 'ProductSprint Backlog'!$F11 / MAX(1, 'ProductSprint Backlog'!$J11-'ProductSprint Backlog'!$I11), AND('ProductSprint Backlog'!$J11=B$2,'ProductSprint Backlog'!$I11=B$2), 'ProductSprint Backlog'!$F11, TRUE, 0)} -> 0 | C11: {=_xlfn.IFS('ProductSprint Backlog'!$F11="", "", AND('ProductSprint Backlog'!$J11>C$2,'ProductSprint Backlog'!$I11<=C$2), 'ProductSprint Backlog'!$F11 / MAX(1, 'ProductSprint Backlog'!$J11-'ProductSprint Backlog'!$I11), AND('ProductSprint Backlog'!$J11=C$2,'ProductSprint Backlog'!$I11=C$2), 'ProductSprint Backlog'!$F11, TRUE, 0)} -> 0 | D11: {=_xlfn.IFS('ProductSprint Backlog'!$F11="", "", AND('ProductSprint Backlog'!$J11>D$2,'ProductSprint Backlog'!$I11<=D$2), 'ProductSprint Backlog'!$F11 / MAX(1, 'ProductSprint Backlog'!$J11-'ProductSprint Backlog'!$I11), AND('ProductSprint Backlog'!$J11=D$2,'ProductSprint Backlog'!$I11=D$2), 'ProductSprint Backlog'!$F11, TRUE, 0)} -> 0 | E11: {=_xlfn.IFS('ProductSprint Backlog'!$F11="", "", AND('ProductSprint Backlog'!$J11>E$2,'ProductSprint Backlog'!$I11<=E$2), 'ProductSprint Backlog'!$F11 / MAX(1, 'ProductSprint Backlog'!$J11-'ProductSprint Backlog'!$I11), AND('ProductSprint Backlog'!$J11=E$2,'ProductSprint Backlog'!$I11=E$2), 'ProductSprint Backlog'!$F11, TRUE, 0)} -> 0 | F11: {=_xlfn.IFS('ProductSprint Backlog'!$F11="", "", AND('ProductSprint Backlog'!$J11>F$2,'ProductSprint Backlog'!$I11<=F$2), 'ProductSprint Backlog'!$F11 / MAX(1, 'ProductSprint Backlog'!$J11-'ProductSprint Backlog'!$I11), AND('ProductSprint Backlog'!$J11=F$2,'ProductSprint Backlog'!$I11=F$2), 'ProductSprint Backlog'!$F11, TRUE, 0)} -> 0 | G11: {=_xlfn.IFS('ProductSprint Backlog'!$F11="", "", AND('ProductSprint Backlog'!$J11>G$2,'ProductSprint Backlog'!$I11<=G$2), 'ProductSprint Backlog'!$F11 / MAX(1, 'ProductSprint Backlog'!$J11-'ProductSprint Backlog'!$I11), AND('ProductSprint Backlog'!$J11=G$2,'ProductSprint Backlog'!$I11=G$2), 'ProductSprint Backlog'!$F11, TRUE, 0)} -> 0 | H11: {=_xlfn.IFS('ProductSprint Backlog'!$F11="", "", AND('ProductSprint Backlog'!$J11>H$2,'ProductSprint Backlog'!$I11<=H$2), 'ProductSprint Backlog'!$F11 / MAX(1, 'ProductSprint Backlog'!$J11-'ProductSprint Backlog'!$I11), AND('ProductSprint Backlog'!$J11=H$2,'ProductSprint Backlog'!$I11=H$2), 'ProductSprint Backlog'!$F11, TRUE, 0)} -> 0 | I11: {=_xlfn.IFS('ProductSprint Backlog'!$F11="", "", AND('ProductSprint Backlog'!$J11>I$2,'ProductSprint Backlog'!$I11<=I$2), 'ProductSprint Backlog'!$F11 / MAX(1, 'ProductSprint Backlog'!$J11-'ProductSprint Backlog'!$I11), AND('ProductSprint Backlog'!$J11=I$2,'ProductSprint Backlog'!$I11=I$2), 'ProductSprint Backlog'!$F11, TRUE, 0)} -> 0 | ... Q11: {=_xlfn.IFS('ProductSprint Backlog'!$F11="", "", AND('ProductSprint Backlog'!$J11>Q$2,'ProductSprint Backlog'!$I11<=Q$2), 'ProductSprint Backlog'!$F11 / MAX(1, 'ProductSprint Backlog'!$J11-'ProductSprint Backlog'!$I11), AND('ProductSprint Backlog'!$J11=Q$2,'ProductSprint Backlog'!$I11=Q$2), 'ProductSprint Backlog'!$F11, TRUE, 0)} -> 0
B12: {=_xlfn.IFS('ProductSprint Backlog'!$F12="", "", AND('ProductSprint Backlog'!$J12>B$2,'ProductSprint Backlog'!$I12<=B$2), 'ProductSprint Backlog'!$F12 / MAX(1, 'ProductSprint Backlog'!$J12-'ProductSprint Backlog'!$I12), AND('ProductSprint Backlog'!$J12=B$2,'ProductSprint Backlog'!$I12=B$2), 'ProductSprint Backlog'!$F12, TRUE, 0)} -> 0 | C12: {=_xlfn.IFS('ProductSprint Backlog'!$F12="", "", AND('ProductSprint Backlog'!$J12>C$2,'ProductSprint Backlog'!$I12<=C$2), 'ProductSprint Backlog'!$F12 / MAX(1, 'ProductSprint Backlog'!$J12-'ProductSprint Backlog'!$I12), AND('ProductSprint Backlog'!$J12=C$2,'ProductSprint Backlog'!$I12=C$2), 'ProductSprint Backlog'!$F12, TRUE, 0)} -> 0 | D12: {=_xlfn.IFS('ProductSprint Backlog'!$F12="", "", AND('ProductSprint Backlog'!$J12>D$2,'ProductSprint Backlog'!$I12<=D$2), 'ProductSprint Backlog'!$F12 / MAX(1, 'ProductSprint Backlog'!$J12-'ProductSprint Backlog'!$I12), AND('ProductSprint Backlog'!$J12=D$2,'ProductSprint Backlog'!$I12=D$2), 'ProductSprint Backlog'!$F12, TRUE, 0)} -> 0 | E12: {=_xlfn.IFS('ProductSprint Backlog'!$F12="", "", AND('ProductSprint Backlog'!$J12>E$2,'ProductSprint Backlog'!$I12<=E$2), 'ProductSprint Backlog'!$F12 / MAX(1, 'ProductSprint Backlog'!$J12-'ProductSprint Backlog'!$I12), AND('ProductSprint Backlog'!$J12=E$2,'ProductSprint Backlog'!$I12=E$2), 'ProductSprint Backlog'!$F12, TRUE, 0)} -> 0 | F12: {=_xlfn.IFS('ProductSprint Backlog'!$F12="", "", AND('ProductSprint Backlog'!$J12>F$2,'ProductSprint Backlog'!$I12<=F$2), 'ProductSprint Backlog'!$F12 / MAX(1, 'ProductSprint Backlog'!$J12-'ProductSprint Backlog'!$I12), AND('ProductSprint Backlog'!$J12=F$2,'ProductSprint Backlog'!$I12=F$2), 'ProductSprint Backlog'!$F12, TRUE, 0)} -> 0 | G12: {=_xlfn.IFS('ProductSprint Backlog'!$F12="", "", AND('ProductSprint Backlog'!$J12>G$2,'ProductSprint Backlog'!$I12<=G$2), 'ProductSprint Backlog'!$F12 / MAX(1, 'ProductSprint Backlog'!$J12-'ProductSprint Backlog'!$I12), AND('ProductSprint Backlog'!$J12=G$2,'ProductSprint Backlog'!$I12=G$2), 'ProductSprint Backlog'!$F12, TRUE, 0)} -> 0 | H12: {=_xlfn.IFS('ProductSprint Backlog'!$F12="", "", AND('ProductSprint Backlog'!$J12>H$2,'ProductSprint Backlog'!$I12<=H$2), 'ProductSprint Backlog'!$F12 / MAX(1, 'ProductSprint Backlog'!$J12-'ProductSprint Backlog'!$I12), AND('ProductSprint Backlog'!$J12=H$2,'ProductSprint Backlog'!$I12=H$2), 'ProductSprint Backlog'!$F12, TRUE, 0)} -> 0 | I12: {=_xlfn.IFS('ProductSprint Backlog'!$F12="", "", AND('ProductSprint Backlog'!$J12>I$2,'ProductSprint Backlog'!$I12<=I$2), 'ProductSprint Backlog'!$F12 / MAX(1, 'ProductSprint Backlog'!$J12-'ProductSprint Backlog'!$I12), AND('ProductSprint Backlog'!$J12=I$2,'ProductSprint Backlog'!$I12=I$2), 'ProductSprint Backlog'!$F12, TRUE, 0)} -> 0 | ... Q12: {=_xlfn.IFS('ProductSprint Backlog'!$F12="", "", AND('ProductSprint Backlog'!$J12>Q$2,'ProductSprint Backlog'!$I12<=Q$2), 'ProductSprint Backlog'!$F12 / MAX(1, 'ProductSprint Backlog'!$J12-'ProductSprint Backlog'!$I12), AND('ProductSprint Backlog'!$J12=Q$2,'ProductSprint Backlog'!$I12=Q$2), 'ProductSprint Backlog'!$F12, TRUE, 0)} -> 0
B13: {=_xlfn.IFS('ProductSprint Backlog'!$F13="", "", AND('ProductSprint Backlog'!$J13>B$2,'ProductSprint Backlog'!$I13<=B$2), 'ProductSprint Backlog'!$F13 / MAX(1, 'ProductSprint Backlog'!$J13-'ProductSprint Backlog'!$I13), AND('ProductSprint Backlog'!$J13=B$2,'ProductSprint Backlog'!$I13=B$2), 'ProductSprint Backlog'!$F13, TRUE, 0)} | C13: {=_xlfn.IFS('ProductSprint Backlog'!$F13="", "", AND('ProductSprint Backlog'!$J13>C$2,'ProductSprint Backlog'!$I13<=C$2), 'ProductSprint Backlog'!$F13 / MAX(1, 'ProductSprint Backlog'!$J13-'ProductSprint Backlog'!$I13), AND('ProductSprint Backlog'!$J13=C$2,'ProductSprint Backlog'!$I13=C$2), 'ProductSprint Backlog'!$F13, TRUE, 0)} | D13: {=_xlfn.IFS('ProductSprint Backlog'!$F13="", "", AND('ProductSprint Backlog'!$J13>D$2,'ProductSprint Backlog'!$I13<=D$2), 'ProductSprint Backlog'!$F13 / MAX(1, 'ProductSprint Backlog'!$J13-'ProductSprint Backlog'!$I13), AND('ProductSprint Backlog'!$J13=D$2,'ProductSprint Backlog'!$I13=D$2), 'ProductSprint Backlog'!$F13, TRUE, 0)} | E13: {=_xlfn.IFS('ProductSprint Backlog'!$F13="", "", AND('ProductSprint Backlog'!$J13>E$2,'ProductSprint Backlog'!$I13<=E$2), 'ProductSprint Backlog'!$F13 / MAX(1, 'ProductSprint Backlog'!$J13-'ProductSprint Backlog'!$I13), AND('ProductSprint Backlog'!$J13=E$2,'ProductSprint Backlog'!$I13=E$2), 'ProductSprint Backlog'!$F13, TRUE, 0)} | F13: {=_xlfn.IFS('ProductSprint Backlog'!$F13="", "", AND('ProductSprint Backlog'!$J13>F$2,'ProductSprint Backlog'!$I13<=F$2), 'ProductSprint Backlog'!$F13 / MAX(1, 'ProductSprint Backlog'!$J13-'ProductSprint Backlog'!$I13), AND('ProductSprint Backlog'!$J13=F$2,'ProductSprint Backlog'!$I13=F$2), 'ProductSprint Backlog'!$F13, TRUE, 0)} | G13: {=_xlfn.IFS('ProductSprint Backlog'!$F13="", "", AND('ProductSprint Backlog'!$J13>G$2,'ProductSprint Backlog'!$I13<=G$2), 'ProductSprint Backlog'!$F13 / MAX(1, 'ProductSprint Backlog'!$J13-'ProductSprint Backlog'!$I13), AND('ProductSprint Backlog'!$J13=G$2,'ProductSprint Backlog'!$I13=G$2), 'ProductSprint Backlog'!$F13, TRUE, 0)} | H13: {=_xlfn.IFS('ProductSprint Backlog'!$F13="", "", AND('ProductSprint Backlog'!$J13>H$2,'ProductSprint Backlog'!$I13<=H$2), 'ProductSprint Backlog'!$F13 / MAX(1, 'ProductSprint Backlog'!$J13-'ProductSprint Backlog'!$I13), AND('ProductSprint Backlog'!$J13=H$2,'ProductSprint Backlog'!$I13=H$2), 'ProductSprint Backlog'!$F13, TRUE, 0)} | I13: {=_xlfn.IFS('ProductSprint Backlog'!$F13="", "", AND('ProductSprint Backlog'!$J13>I$2,'ProductSprint Backlog'!$I13<=I$2), 'ProductSprint Backlog'!$F13 / MAX(1, 'ProductSprint Backlog'!$J13-'ProductSprint Backlog'!$I13), AND('ProductSprint Backlog'!$J13=I$2,'ProductSprint Backlog'!$I13=I$2), 'ProductSprint Backlog'!$F13, TRUE, 0)} | ... Q13: {=_xlfn.IFS('ProductSprint Backlog'!$F13="", "", AND('ProductSprint Backlog'!$J13>Q$2,'ProductSprint Backlog'!$I13<=Q$2), 'ProductSprint Backlog'!$F13 / MAX(1, 'ProductSprint Backlog'!$J13-'ProductSprint Backlog'!$I13), AND('ProductSprint Backlog'!$J13=Q$2,'ProductSprint Backlog'!$I13=Q$2), 'ProductSprint Backlog'!$F13, TRUE, 0)}
B14: {=_xlfn.IFS('ProductSprint Backlog'!$F14="", "", AND('ProductSprint Backlog'!$J14>B$2,'ProductSprint Backlog'!$I14<=B$2), 'ProductSprint Backlog'!$F14 / MAX(1, 'ProductSprint Backlog'!$J14-'ProductSprint Backlog'!$I14), AND('ProductSprint Backlog'!$J14=B$2,'ProductSprint Backlog'!$I14=B$2), 'ProductSprint Backlog'!$F14, TRUE, 0)} -> 0 | C14: {=_xlfn.IFS('ProductSprint Backlog'!$F14="", "", AND('ProductSprint Backlog'!$J14>C$2,'ProductSprint Backlog'!$I14<=C$2), 'ProductSprint Backlog'!$F14 / MAX(1, 'ProductSprint Backlog'!$J14-'ProductSprint Backlog'!$I14), AND('ProductSprint Backlog'!$J14=C$2,'ProductSprint Backlog'!$I14=C$2), 'ProductSprint Backlog'!$F14, TRUE, 0)} -> 0 | D14: {=_xlfn.IFS('ProductSprint Backlog'!$F14="", "", AND('ProductSprint Backlog'!$J14>D$2,'ProductSprint Backlog'!$I14<=D$2), 'ProductSprint Backlog'!$F14 / MAX(1, 'ProductSprint Backlog'!$J14-'ProductSprint Backlog'!$I14), AND('ProductSprint Backlog'!$J14=D$2,'ProductSprint Backlog'!$I14=D$2), 'ProductSprint Backlog'!$F14, TRUE, 0)} -> 0 | E14: {=_xlfn.IFS('ProductSprint Backlog'!$F14="", "", AND('ProductSprint Backlog'!$J14>E$2,'ProductSprint Backlog'!$I14<=E$2), 'ProductSprint Backlog'!$F14 / MAX(1, 'ProductSprint Backlog'!$J14-'ProductSprint Backlog'!$I14), AND('ProductSprint Backlog'!$J14=E$2,'ProductSprint Backlog'!$I14=E$2), 'ProductSprint Backlog'!$F14, TRUE, 0)} -> 0 | F14: {=_xlfn.IFS('ProductSprint Backlog'!$F14="", "", AND('ProductSprint Backlog'!$J14>F$2,'ProductSprint Backlog'!$I14<=F$2), 'ProductSprint Backlog'!$F14 / MAX(1, 'ProductSprint Backlog'!$J14-'ProductSprint Backlog'!$I14), AND('ProductSprint Backlog'!$J14=F$2,'ProductSprint Backlog'!$I14=F$2), 'ProductSprint Backlog'!$F14, TRUE, 0)} -> 0 | G14: {=_xlfn.IFS('ProductSprint Backlog'!$F14="", "", AND('ProductSprint Backlog'!$J14>G$2,'ProductSprint Backlog'!$I14<=G$2), 'ProductSprint Backlog'!$F14 / MAX(1, 'ProductSprint Backlog'!$J14-'ProductSprint Backlog'!$I14), AND('ProductSprint Backlog'!$J14=G$2,'ProductSprint Backlog'!$I14=G$2), 'ProductSprint Backlog'!$F14, TRUE, 0)} -> 0 | H14: {=_xlfn.IFS('ProductSprint Backlog'!$F14="", "", AND('ProductSprint Backlog'!$J14>H$2,'ProductSprint Backlog'!$I14<=H$2), 'ProductSprint Backlog'!$F14 / MAX(1, 'ProductSprint Backlog'!$J14-'ProductSprint Backlog'!$I14), AND('ProductSprint Backlog'!$J14=H$2,'ProductSprint Backlog'!$I14=H$2), 'ProductSprint Backlog'!$F14, TRUE, 0)} -> 0 | I14: {=_xlfn.IFS('ProductSprint Backlog'!$F14="", "", AND('ProductSprint Backlog'!$J14>I$2,'ProductSprint Backlog'!$I14<=I$2), 'ProductSprint Backlog'!$F14 / MAX(1, 'ProductSprint Backlog'!$J14-'ProductSprint Backlog'!$I14), AND('ProductSprint Backlog'!$J14=I$2,'ProductSprint Backlog'!$I14=I$2), 'ProductSprint Backlog'!$F14, TRUE, 0)} -> 0 | ... Q14: {=_xlfn.IFS('ProductSprint Backlog'!$F14="", "", AND('ProductSprint Backlog'!$J14>Q$2,'ProductSprint Backlog'!$I14<=Q$2), 'ProductSprint Backlog'!$F14 / MAX(1, 'ProductSprint Backlog'!$J14-'ProductSprint Backlog'!$I14), AND('ProductSprint Backlog'!$J14=Q$2,'ProductSprint Backlog'!$I14=Q$2), 'ProductSprint Backlog'!$F14, TRUE, 0)} -> 0
... B453: {=_xlfn.IFS('ProductSprint Backlog'!$F453="", "", AND('ProductSprint Backlog'!$J453>B$2,'ProductSprint Backlog'!$I453<=B$2), 'ProductSprint Backlog'!$F453 / MAX(1, 'ProductSprint Backlog'!$J453-'ProductSprint Backlog'!$I453), AND('ProductSprint Backlog'!$J453=B$2,'ProductSprint Backlog'!$I453=B$2), 'ProductSprint Backlog'!$F453, TRUE, 0)} | C453: {=_xlfn.IFS('ProductSprint Backlog'!$F453="", "", AND('ProductSprint Backlog'!$J453>C$2,'ProductSprint Backlog'!$I453<=C$2), 'ProductSprint Backlog'!$F453 / MAX(1, 'ProductSprint Backlog'!$J453-'ProductSprint Backlog'!$I453), AND('ProductSprint Backlog'!$J453=C$2,'ProductSprint Backlog'!$I453=C$2), 'ProductSprint Backlog'!$F453, TRUE, 0)} | D453: {=_xlfn.IFS('ProductSprint Backlog'!$F453="", "", AND('ProductSprint Backlog'!$J453>D$2,'ProductSprint Backlog'!$I453<=D$2), 'ProductSprint Backlog'!$F453 / MAX(1, 'ProductSprint Backlog'!$J453-'ProductSprint Backlog'!$I453), AND('ProductSprint Backlog'!$J453=D$2,'ProductSprint Backlog'!$I453=D$2), 'ProductSprint Backlog'!$F453, TRUE, 0)} | E453: {=_xlfn.IFS('ProductSprint Backlog'!$F453="", "", AND('ProductSprint Backlog'!$J453>E$2,'ProductSprint Backlog'!$I453<=E$2), 'ProductSprint Backlog'!$F453 / MAX(1, 'ProductSprint Backlog'!$J453-'ProductSprint Backlog'!$I453), AND('ProductSprint Backlog'!$J453=E$2,'ProductSprint Backlog'!$I453=E$2), 'ProductSprint Backlog'!$F453, TRUE, 0)} | F453: {=_xlfn.IFS('ProductSprint Backlog'!$F453="", "", AND('ProductSprint Backlog'!$J453>F$2,'ProductSprint Backlog'!$I453<=F$2), 'ProductSprint Backlog'!$F453 / MAX(1, 'ProductSprint Backlog'!$J453-'ProductSprint Backlog'!$I453), AND('ProductSprint Backlog'!$J453=F$2,'ProductSprint Backlog'!$I453=F$2), 'ProductSprint Backlog'!$F453, TRUE, 0)} | G453: {=_xlfn.IFS('ProductSprint Backlog'!$F453="", "", AND('ProductSprint Backlog'!$J453>G$2,'ProductSprint Backlog'!$I453<=G$2), 'ProductSprint Backlog'!$F453 / MAX(1, 'ProductSprint Backlog'!$J453-'ProductSprint Backlog'!$I453), AND('ProductSprint Backlog'!$J453=G$2,'ProductSprint Backlog'!$I453=G$2), 'ProductSprint Backlog'!$F453, TRUE, 0)} | H453: {=_xlfn.IFS('ProductSprint Backlog'!$F453="", "", AND('ProductSprint Backlog'!$J453>H$2,'ProductSprint Backlog'!$I453<=H$2), 'ProductSprint Backlog'!$F453 / MAX(1, 'ProductSprint Backlog'!$J453-'ProductSprint Backlog'!$I453), AND('ProductSprint Backlog'!$J453=H$2,'ProductSprint Backlog'!$I453=H$2), 'ProductSprint Backlog'!$F453, TRUE, 0)} | I453: {=_xlfn.IFS('ProductSprint Backlog'!$F453="", "", AND('ProductSprint Backlog'!$J453>I$2,'ProductSprint Backlog'!$I453<=I$2), 'ProductSprint Backlog'!$F453 / MAX(1, 'ProductSprint Backlog'!$J453-'ProductSprint Backlog'!$I453), AND('ProductSprint Backlog'!$J453=I$2,'ProductSprint Backlog'!$I453=I$2), 'ProductSprint Backlog'!$F453, TRUE, 0)} | ... Q453: {=_xlfn.IFS('ProductSprint Backlog'!$F453="", "", AND('ProductSprint Backlog'!$J453>Q$2,'ProductSprint Backlog'!$I453<=Q$2), 'ProductSprint Backlog'!$F453 / MAX(1, 'ProductSprint Backlog'!$J453-'ProductSprint Backlog'!$I453), AND('ProductSprint Backlog'!$J453=Q$2,'ProductSprint Backlog'!$I453=Q$2), 'ProductSprint Backlog'!$F453, TRUE, 0)}

Sheet BurnUp-Down INC 2
A1: Periodo de Sprint 1 | D1: 45875 | E1: 45892 | F1: =E1-D1 -> 17
A3: BurnUp
B4: 45875 | C4: 45876 | D4: 45877 | E4: 45878 | F4: 45879 | G4: 45880 | H4: 45881 | I4: 45882 | J4: 45883 | K4: 45884 | L4: 45885 | M4: 45886 | N4: 45887 | O4: 45888 | P4: 45889 | Q4: 45890 | R4: 45891 | S4: 45892
B5: Día 1 | C5: Día 2 | D5: Día 3 | E5: Día 4 | F5: Día 5 | G5: Día 6 | H5: Día 7 | I5: Día 8 | J5: Día 9 | K5: Día 10 | L5: Día 11 | M5: Día 12 | N5: Día 13 | O5: Día 14 | P5: Día 15 | Q5: Día 16 | R5: Día 17 | S5: Día 18
A6: Esfuerzo Real Acumulado (HH) | B6: 0 | C6: ='Registro de HH INC2'!C11 -> 4 | D6: ='Registro de HH INC2'!D11 -> 11 | E6: ='Registro de HH INC2'!E11 -> 14 | F6: ='Registro de HH INC2'!F11 -> 14 | G6: ='Registro de HH INC2'!G11 -> 25 | H6: ='Registro de HH INC2'!H11 -> 33 | I6: ='Registro de HH INC2'!I11 -> 42 | J6: ='Registro de HH INC2'!J11 -> 48 | ... S6: ='Registro de HH INC2'!S11 -> 74
A7: Esfuerzo Estimado Acumulado (HH) | B7: 0 | C7: =SUM('Aux Esfuerzo Estimado INC2 SPT1'!B3:B1000) -> 5.7333333 | D7: =SUM('Aux Esfuerzo Estimado INC2 SPT1'!C3:C1000)+C7 -> 11.466667 | E7: =SUM('Aux Esfuerzo Estimado INC2 SPT1'!D3:D1000)+D7 -> 17.2 | F7: =SUM('Aux Esfuerzo Estimado INC2 SPT1'!E3:E1000)+E7 -> 20.266667 | G7: =SUM('Aux Esfuerzo Estimado INC2 SPT1'!F3:F1000)+F7 -> 24.333333 | H7: =SUM('Aux Esfuerzo Estimado INC2 SPT1'!G3:G1000)+G7 -> 31.066667 | I7: =SUM('Aux Esfuerzo Estimado INC2 SPT1'!H3:H1000)+H7 -> 34.133333 | J7: =SUM('Aux Esfuerzo Estimado INC2 SPT1'!I3:I1000)+I7 -> 41.033333 | K7: =SUM('Aux Esfuerzo Estimado INC2 SPT1'!J3:J1000)+J7 -> 46.933333 | ... S7: =SUM('Aux Esfuerzo Estimado INC2 SPT1'!R3:R1000)+R7 -> 82
A9: BurnDown
B10: 45876 | C10: 45877 | D10: 45878 | E10: 45879 | F10: 45880 | G10: 45881 | H10: 45882 | I10: 45883 | J10: 45884 | K10: 45885 | L10: 45886 | M10: 45887 | N10: 45888 | O10: 45889 | P10: 45890 | Q10: 45891 | R10: 45892 | S10: 45893
B11: Día 1 | C11: Día 2 | D11: Día 3 | E11: Día 4 | F11: Día 5 | G11: Día 6 | H11: Día 7 | I11: Día 8 | J11: Día 9 | K11: Día 10 | L11: Día 11 | M11: Día 12 | N11: Día 13 | O11: Día 14 | P11: Día 15 | Q11: Día 16 | R11: Día 17 | S11: Día 18
A12: Esfuerzo Real Restante (HH) | B12: =SUM('ProductSprint Backlog'!M86:M166) -> 74 | C12: =B12-'Registro de HH INC2'!C10 -> 70 | D12: =C12-'Registro de HH INC2'!D10 -> 63 | E12: =D12-'Registro de HH INC2'!E10 -> 60 | F12: =E12-'Registro de HH INC2'!F10 -> 60 | G12: =F12-'Registro de HH INC2'!G10 -> 49 | H12: =G12-'Registro de HH INC2'!H10 -> 41 | I12: =H12-'Registro de HH INC2'!I10 -> 32 | J12: =I12-'Registro de HH INC2'!J10 -> 26 | ... S12: =R12-'Registro de HH INC2'!S10 -> 0
A13: Esfuerzo Estimado Restante (HH) | B13: =SUM('ProductSprint Backlog'!F86:F166) -> 82 | C13: =B13-SUM('Aux Esfuerzo Estimado INC2 SPT1'!B3:B1000) -> 76.266667 | D13: =C13-SUM('Aux Esfuerzo Estimado INC2 SPT1'!C3:C1000) -> 70.533333 | E13: =D13-SUM('Aux Esfuerzo Estimado INC2 SPT1'!D3:D1000) -> 64.8 | F13: =E13-SUM('Aux Esfuerzo Estimado INC2 SPT1'!E3:E1000) -> 61.733333 | G13: =F13-SUM('Aux Esfuerzo Estimado INC2 SPT1'!F3:F1000) -> 57.666667 | H13: =G13-SUM('Aux Esfuerzo Estimado INC2 SPT1'!G3:G1000) -> 50.933333 | I13: =H13-SUM('Aux Esfuerzo Estimado INC2 SPT1'!H3:H1000) -> 47.866667 | J13: =I13-SUM('Aux Esfuerzo Estimado INC2 SPT1'!I3:I1000) -> 40.966667 | ... S13: =R13-SUM('Aux Esfuerzo Estimado INC2 SPT1'!R3:R1000) -> -1.4654944e-14
A17: Periodo de Sprint 2 | D17: 45900 | E17: 45917 | F17: =E17-D17 -> 17
A20: BurnUp
B21: 45901 | C21: 45902 | D21: 45903 | E21: 45904 | F21: 45905 | G21: 45906 | H21: 45907 | I21: 45908 | J21: 45909 | K21: 45910 | L21: 45911 | M21: 45912 | N21: 45913 | O21: 45914 | P21: 45915 | Q21: 45916 | R21: 45917
B22: Día 1 | C22: Día 2 | D22: Día 3 | E22: Día 4 | F22: Día 5 | G22: Día 6 | H22: Día 7 | I22: Día 8 | J22: Día 9 | K22: Día 10 | L22: Día 11 | M22: Día 12 | N22: Día 13 | O22: Día 14 | P22: Día 15 | Q22: Día 16 | R22: Día 17 | S22: Día 18
A23: Esfuerzo Real Acumulado (HH) | B23: 0 | C23: ='Registro de HH INC2'!D23 -> 2 | D23: ='Registro de HH INC2'!E23 -> 4 | E23: ='Registro de HH INC2'!F23 -> 8 | F23: ='Registro de HH INC2'!G23 -> 14 | G23: ='Registro de HH INC2'!H23 -> 19 | H23: ='Registro de HH INC2'!I23 -> 22 | I23: ='Registro de HH INC2'!J23 -> 33 | J23: ='Registro de HH INC2'!K23 -> 43 | ... R23: ='Registro de HH INC2'!S23 -> 79
A24: Esfuerzo Estimado Acumulado (HH) | B24: 0 | C24: =SUM('Aux Esfuerzo Estimado INC2 SPT2'!B3:B1000) -> 5.8714286 | D24: =SUM('Aux Esfuerzo Estimado INC2 SPT2'!C3:C1000)+C24 -> 11.742857 | E24: =SUM('Aux Esfuerzo Estimado INC2 SPT2'!D3:D1000)+D24 -> 17.614286 | F24: =SUM('Aux Esfuerzo Estimado INC2 SPT2'!E3:E1000)+E24 -> 21.485714 | G24: =SUM('Aux Esfuerzo Estimado INC2 SPT2'!F3:F1000)+F24 -> 26.857143 | H24: =SUM('Aux Esfuerzo Estimado INC2 SPT2'!G3:G1000)+G24 -> 31.761905 | I24: =SUM('Aux Esfuerzo Estimado INC2 SPT2'!H3:H1000)+H24 -> 39 | J24: =SUM('Aux Esfuerzo Estimado INC2 SPT2'!I3:I1000)+I24 -> 42.666667 | K24: =SUM('Aux Esfuerzo Estimado INC2 SPT2'!J3:J1000)+J24 -> 48.571429 | ... S24: =SUM('Aux Esfuerzo Estimado INC2 SPT2'!R3:R1000)+R24 -> 81
A26: BurnDown
B27: 45901 | C27: 45902 | D27: 45903 | E27: 45904 | F27: 45905 | G27: 45906 | H27: 45907 | I27: 45908 | J27: 45909 | K27: 45910 | L27: 45911 | M27: 45912 | N27: 45913 | O27: 45914 | P27: 45915 | Q27: 45916 | R27: 45917
B28: Día 1 | C28: Día 2 | D28: Día 3 | E28: Día 4 | F28: Día 5 | G28: Día 6 | H28: Día 7 | I28: Día 8 | J28: Día 9 | K28: Día 10 | L28: Día 11 | M28: Día 12 | N28: Día 13 | O28: Día 14 | P28: Día 15 | Q28: Día 16 | R28: Día 17 | S28: Día 18
A29: Esfuerzo Real Restante (HH) | B29: =SUM('ProductSprint Backlog'!M168:M238) -> 79 | C29: =B29-'Registro de HH INC2'!D22 -> 77 | D29: =C29-'Registro de HH INC2'!E22 -> 75 | E29: =D29-'Registro de HH INC2'!F22 -> 71 | F29: =E29-'Registro de HH INC2'!G22 -> 65 | G29: =F29-'Registro de HH INC2'!H22 -> 60 | H29: =G29-'Registro de HH INC2'!I22 -> 57 | I29: =H29-'Registro de HH INC2'!J22 -> 46 | J29: =I29-'Registro de HH INC2'!K22 -> 36 | ... S29: =R29-'Registro de HH INC2'!T22 -> 0
A30: Esfuerzo Estimado Restante (HH) | B30: =SUM('ProductSprint Backlog'!F168:F238) -> 81 | C30: =B30-SUM('Aux Esfuerzo Estimado INC2 SPT2'!B3:B1000) -> 75.128571 | D30: =C30-SUM('Aux Esfuerzo Estimado INC2 SPT2'!C3:C1000) -> 69.257143 | E30: =D30-SUM('Aux Esfuerzo Estimado INC2 SPT2'!D3:D1000) -> 63.385714 | F30: =E30-SUM('Aux Esfuerzo Estimado INC2 SPT2'!E3:E1000) -> 59.514286 | G30: =F30-SUM('Aux Esfuerzo Estimado INC2 SPT2'!F3:F1000) -> 54.142857 | H30: =G30-SUM('Aux Esfuerzo Estimado INC2 SPT2'!G3:G1000) -> 49.238095 | I30: =H30-SUM('Aux Esfuerzo Estimado INC2 SPT2'!H3:H1000) -> 42 | J30: =I30-SUM('Aux Esfuerzo Estimado INC2 SPT2'!I3:I1000) -> 38.333333 | ... R30: =Q30-SUM('Aux Esfuerzo Estimado INC2 SPT2'!Q3:Q1000) -> -1.0658141e-14

Sheet Registro de HH INC2
A1: Sprint 2
B2: Dia 0 | C2: Dia 1 | D2: Dia 2 | E2: Dia 3 | F2: Dia 4 | G2: Dia 5 | H2: Dia 6 | I2: Dia 7 | J2: Dia 8 | K2: Dia 9 | L2: Dia 10 | M2: Dia 11 | N2: Dia 12 | O2: Dia 13 | P2: Dia 14 | Q2: Dia 15 | R2: Dia 16 | S2: Dia 17
A3: Persona | B3: 45875 | C3: 45876 | D3: 45877 | E3: 45878 | F3: 45879 | G3: 45880 | H3: 45881 | I3: 45882 | J3: 45883 | K3: 45884 | L3: 45885 | M3: 45886 | N3: 45887 | O3: 45888 | P3: 45889 | Q3: 45890 | R3: 45891 | S3: 45892 | T3: 45893 | U3: 45894 | V3: 45895 | W3: 45896
A4: Bastian | D4: 1 | G4: 4 | H4: 3 | I4: 4 | J4: 3 | K4: 1
A5: Eliam | C5: 2 | G5: 3 | K5: 1
A6: Geronimo | C6: 2 | D6: 5 | E6: 3 | S6: 4
A7: Manuel | D7: 1 | G7: 4 | H7: 3 | I7: 4 | J7: 3 | K7: 1
A8: Samir | H8: 2 | I8: 1 | K8: 2 | M8: 3 | N8: 2 | O8: 2
A9: Francisco | N9: 2 | O9: 2 | P9: 3 | Q9: 3
A10: Total Dia | C10: =SUM(C4:C9) -> 4 | D10: =SUM(D4:D9) -> 7 | E10: =SUM(E4:E9) -> 3 | F10: =SUM(F4:F9) -> 0 | G10: =SUM(G4:G9) -> 11 | H10: =SUM(H4:H9) -> 8 | I10: =SUM(I4:I9) -> 9 | J10: =SUM(J4:J9) -> 6 | ... S10: =SUM(S4:S9) -> 4
A11: Total Acumulado | B11: =SUM(B4:B9) -> 0 | C11: =SUM(C4:C9)+B11 -> 4 | D11: =SUM(D4:D9)+C11 -> 11 | E11: =SUM(E4:E9)+D11 -> 14 | F11: =SUM(F4:F9)+E11 -> 14 | G11: =SUM(G4:G9)+F11 -> 25 | H11: =SUM(H4:H9)+G11 -> 33 | I11: =SUM(I4:I9)+H11 -> 42 | J11: =SUM(J4:J9)+I11 -> 48 | ... S11: =SUM(S4:S9)+R11 -> 74
A13: Sprint 3
C14: Dia 1 | D14: Dia 2 | E14: Dia 3 | F14: Dia 4 | G14: Dia 5 | H14: Dia 6 | I14: Dia 7 | J14: Dia 8 | K14: Dia 9 | L14: Dia 10 | M14: Dia 11 | N14: Dia 12 | O14: Dia 13 | P14: Dia 14 | Q14: Dia 15 | R14: Dia 16 | S14: Dia 17 | T14: Dia 18
A15: Persona | C15: 45901 | D15: 45902 | E15: 45903 | F15: 45904 | G15: 45905 | H15: 45906 | I15: 45907 | J15: 45908 | K15: 45909 | L15: 45910 | M15: 45911 | N15: 45912 | O15: 45913 | P15: 45914 | Q15: 45915 | R15: 45916 | S15: 45917 | T15: 45918 | U15: 45919
A16: Bastian | C16: 0 | H16: 5 | J16: 3 | K16: 2 | N16: 3 | P16: 4
A17: Eliam | F17: 1 | G17: 3 | K17: 5 | O17: 3
A18: Geronimo | J18: 8 | Q18: 6 | R18: 5
A19: Manuel | D19: 2 | E19: 2 | F19: 3 | G19: 3 | I19: 3 | K19: 3 | M19: 2 | P19: 2
A20: Samir | N20: 3 | O20: 2 | P20: 3 | Q20: 2 | R20: 1
A21: Francisco
A22: Total Dia | D22: =SUM(D16:D21) -> 2 | E22: =SUM(E16:E21) -> 2 | F22: =SUM(F16:F21) -> 4 | G22: =SUM(G16:G21) -> 6 | H22: =SUM(H16:H21) -> 5 | I22: =SUM(I16:I21) -> 3 | J22: =SUM(J16:J21) -> 11 | K22: =SUM(K16:K21) -> 10 | ... T22: =SUM(T16:T21) -> 0
A23: Total Acumulado | C23: =SUM(C16:C21) -> 0 | D23: =SUM(D16:D21)+B23 -> 2 | E23: =SUM(E16:E21)+D23 -> 4 | F23: =SUM(F16:F21)+E23 -> 8 | G23: =SUM(G16:G21)+F23 -> 14 | H23: =SUM(H16:H21)+G23 -> 19 | I23: =SUM(I16:I21)+H23 -> 22 | J23: =SUM(J16:J21)+I23 -> 33 | K23: =SUM(K16:K21)+J23 -> 43 | L23: =SUM(L16:L21)+K23 -> 43 | ... T23: =SUM(T16:T21)+S23 -> 79

Sheet Tabla de Esfuerzo INC2 SPT2
B2: 45901 | C2: 45902 | D2: 45903 | E2: 45904 | F2: 45905 | G2: 45906 | H2: 45907 | I2: 45908 | J2: 45909 | K2: 45910 | L2: 45911 | M2: 45912 | N2: 45913 | O2: 45914 | P2: 45915
A3: Tareas Pendientes | B3: =COUNTIFS('ProductSprint Backlog'!$D$168:$D$238,"<>",'ProductSprint Backlog'!$L$168:$L$238,">"&DATEVALUE(B2)) -> 0 | C3: =COUNTIFS('ProductSprint Backlog'!$D$168:$D$238,"<>",'ProductSprint Backlog'!$L$168:$L$238,">"&DATEVALUE(C2)) -> 0 | D3: =COUNTIFS('ProductSprint Backlog'!$D$168:$D$238,"<>",'ProductSprint Backlog'!$L$168:$L$238,">"&DATEVALUE(D2)) -> 0 | E3: =COUNTIFS('ProductSprint Backlog'!$D$168:$D$238,"<>",'ProductSprint Backlog'!$L$168:$L$238,">"&DATEVALUE(E2)) -> 0 | F3: =COUNTIFS('ProductSprint Backlog'!$D$168:$D$238,"<>",'ProductSprint Backlog'!$L$168:$L$238,">"&DATEVALUE(F2)) -> 0 | G3: =COUNTIFS('ProductSprint Backlog'!$D$168:$D$238,"<>",'ProductSprint Backlog'!$L$168:$L$238,">"&DATEVALUE(G2)) -> 0 | H3: =COUNTIFS('ProductSprint Backlog'!$D$168:$D$238,"<>",'ProductSprint Backlog'!$L$168:$L$238,">"&DATEVALUE(H2)) -> 0 | I3: =COUNTIFS('ProductSprint Backlog'!$D$168:$D$238,"<>",'ProductSprint Backlog'!$L$168:$L$238,">"&DATEVALUE(I2)) -> 0 | ... P3: =COUNTIFS('ProductSprint Backlog'!$D$168:$D$238,"<>",'ProductSprint Backlog'!$L$168:$L$238,">"&DATEVALUE(P2)) -> 0
A6: Tarea | B6: Esfuerzo
A7: Diseñar la interfaz de lista de clientes en solo lectura (RUN/RUT, nombre/razón social, correo, teléfono, dirección). | B7: =IF('ProductSprint Backlog'!$L168>B$2,'ProductSprint Backlog'!$M168,0) -> 1 | C7: =IF('ProductSprint Backlog'!$L168>C$2,'ProductSprint Backlog'!$M168,0) -> 0 | D7: =IF('ProductSprint Backlog'!$L168>D$2,'ProductSprint Backlog'!$M168,0) -> 0 | E7: =IF('ProductSprint Backlog'!$L168>E$2,'ProductSprint Backlog'!$M168,0) -> 0 | F7: =IF('ProductSprint Backlog'!$L168>F$2,'ProductSprint Backlog'!$M168,0) -> 0 | G7: =IF('ProductSprint Backlog'!$L168>G$2,'ProductSprint Backlog'!$M168,0) -> 0 | H7: =IF('ProductSprint Backlog'!$L168>H$2,'ProductSprint Backlog'!$M168,0) -> 0 | I7: =IF('ProductSprint Backlog'!$L168>I$2,'ProductSprint Backlog'!$M168,0) -> 0 | ... P7: =IF('ProductSprint Backlog'!$L168>P$2,'ProductSprint Backlog'!$M168,0) -> 0
A8: Desarrollar navegación al detalle del cliente (equipos, órdenes, cotizaciones, informes). | B8: =IF('ProductSprint Backlog'!$L169>B$2,'ProductSprint Backlog'!$M169,0) -> 1 | C8: =IF('ProductSprint Backlog'!$L169>C$2,'ProductSprint Backlog'!$M169,0) -> 0 | D8: =IF('ProductSprint Backlog'!$L169>D$2,'ProductSprint Backlog'!$M169,0) -> 0 | E8: =IF('ProductSprint Backlog'!$L169>E$2,'ProductSprint Backlog'!$M169,0) -> 0 | F8: =IF('ProductSprint Backlog'!$L169>F$2,'ProductSprint Backlog'!$M169,0) -> 0 | G8: =IF('ProductSprint Backlog'!$L169>G$2,'ProductSprint Backlog'!$M169,0) -> 0 | H8: =IF('ProductSprint Backlog'!$L169>H$2,'ProductSprint Backlog'!$M169,0) -> 0 | I8: =IF('ProductSprint Backlog'!$L169>I$2,'ProductSprint Backlog'!$M169,0) -> 0 | ... P8: =IF('ProductSprint Backlog'!$L169>P$2,'ProductSprint Backlog'!$M169,0) -> 0
A9: Implementar lógica de backend para listar clientes y ver detalle. | B9: =IF('ProductSprint Backlog'!$L170>B$2,'ProductSprint Backlog'!$M170,0) -> 0.5 | C9: =IF('ProductSprint Backlog'!$L170>C$2,'ProductSprint Backlog'!$M170,0) -> 0 | D9: =IF('ProductSprint Backlog'!$L170>D$2,'ProductSprint Backlog'!$M170,0) -> 0 | E9: =IF('ProductSprint Backlog'!$L170>E$2,'ProductSprint Backlog'!$M170,0) -> 0 | F9: =IF('ProductSprint Backlog'!$L170>F$2,'ProductSprint Backlog'!$M170,0) -> 0 | G9: =IF('ProductSprint Backlog'!$L170>G$2,'ProductSprint Backlog'!$M170,0) -> 0 | H9: =IF('ProductSprint Backlog'!$L170>H$2,'ProductSprint Backlog'!$M170,0) -> 0 | I9: =IF('ProductSprint Backlog'!$L170>I$2,'ProductSprint Backlog'!$M170,0) -> 0 | ... P9: =IF('ProductSprint Backlog'!$L170>P$2,'ProductSprint Backlog'!$M170,0) -> 0
A10: Diseñar filtrado por el nombre/razón social, por medio de una caja de texto | B10: =IF('ProductSprint Backlog'!$L171>B$2,'ProductSprint Backlog'!$M171,0) -> 1 | C10: =IF('ProductSprint Backlog'!$L171>C$2,'ProductSprint Backlog'!$M171,0) -> 0 | D10: =IF('ProductSprint Backlog'!$L171>D$2,'ProductSprint Backlog'!$M171,0) -> 0 | E10: =IF('ProductSprint Backlog'!$L171>E$2,'ProductSprint Backlog'!$M171,0) -> 0 | F10: =IF('ProductSprint Backlog'!$L171>F$2,'ProductSprint Backlog'!$M171,0) -> 0 | G10: =IF('ProductSprint Backlog'!$L171>G$2,'ProductSprint Backlog'!$M171,0) -> 0 | H10: =IF('ProductSprint Backlog'!$L171>H$2,'ProductSprint Backlog'!$M171,0) -> 0 | I10: =IF('ProductSprint Backlog'!$L171>I$2,'ProductSprint Backlog'!$M171,0) -> 0 | ... P10: =IF('ProductSprint Backlog'!$L171>P$2,'ProductSprint Backlog'!$M171,0) -> 0
A11: Implementar la funcionalidad del filtro, cumpliendo las condiciones seleccionadas | B11: =IF('ProductSprint Backlog'!$L172>B$2,'ProductSprint Backlog'!$M172,0) -> 1 | C11: =IF('ProductSprint Backlog'!$L172>C$2,'ProductSprint Backlog'!$M172,0) -> 0 | D11: =IF('ProductSprint Backlog'!$L172>D$2,'ProductSprint Backlog'!$M172,0) -> 0 | E11: =IF('ProductSprint Backlog'!$L172>E$2,'ProductSprint Backlog'!$M172,0) -> 0 | F11: =IF('ProductSprint Backlog'!$L172>F$2,'ProductSprint Backlog'!$M172,0) -> 0 | G11: =IF('ProductSprint Backlog'!$L172>G$2,'ProductSprint Backlog'!$M172,0) -> 0 | H11: =IF('ProductSprint Backlog'!$L172>H$2,'ProductSprint Backlog'!$M172,0) -> 0 | I11: =IF('ProductSprint Backlog'!$L172>I$2,'ProductSprint Backlog'!$M172,0) -> 0 | ... P11: =IF('ProductSprint Backlog'!$L172>P$2,'ProductSprint Backlog'!$M172,0) -> 0
A12: Agregar la funcionalidad de eliminar el filtro, llevando a la recarga del listado completo | B12: =IF('ProductSprint Backlog'!$L173>B$2,'ProductSprint Backlog'!$M173,0) -> 0.5 | C12: =IF('ProductSprint Backlog'!$L173>C$2,'ProductSprint Backlog'!$M173,0) -> 0 | D12: =IF('ProductSprint Backlog'!$L173>D$2,'ProductSprint Backlog'!$M173,0) -> 0 | E12: =IF('ProductSprint Backlog'!$L173>E$2,'ProductSprint Backlog'!$M173,0) -> 0 | F12: =IF('ProductSprint Backlog'!$L173>F$2,'ProductSprint Backlog'!$M173,0) -> 0 | G12: =IF('ProductSprint Backlog'!$L173>G$2,'ProductSprint Backlog'!$M173,0) -> 0 | H12: =IF('ProductSprint Backlog'!$L173>H$2,'ProductSprint Backlog'!$M173,0) -> 0 | I12: =IF('ProductSprint Backlog'!$L173>I$2,'ProductSprint Backlog'!$M173,0) -> 0 | ... P12: =IF('ProductSprint Backlog'!$L173>P$2,'ProductSprint Backlog'!$M173,0) -> 0
A13: Mostrar estados “sin coincidencias” y pruebas básicas de validación del filtro. | B13: =IF('ProductSprint Backlog'!$L174>B$2,'ProductSprint Backlog'!$M174,0) -> 0.5 | C13: =IF('ProductSprint Backlog'!$L174>C$2,'ProductSprint Backlog'!$M174,0) -> 0 | D13: =IF('ProductSprint Backlog'!$L174>D$2,'ProductSprint Backlog'!$M174,0) -> 0 | E13: =IF('ProductSprint Backlog'!$L174>E$2,'ProductSprint Backlog'!$M174,0) -> 0 | F13: =IF('ProductSprint Backlog'!$L174>F$2,'ProductSprint Backlog'!$M174,0) -> 0 | G13: =IF('ProductSprint Backlog'!$L174>G$2,'ProductSprint Backlog'!$M174,0) -> 0 | H13: =IF('ProductSprint Backlog'!$L174>H$2,'ProductSprint Backlog'!$M174,0) -> 0 | I13: =IF('ProductSprint Backlog'!$L174>I$2,'ProductSprint Backlog'!$M174,0) -> 0 | ... P13: =IF('ProductSprint Backlog'!$L174>P$2,'ProductSprint Backlog'!$M174,0) -> 0
A14: Agregar control de orden A-Z / Z-A en la lista (UI) y persistir la elección en el sistema | B14: =IF('ProductSprint Backlog'!$L175>B$2,'ProductSprint Backlog'!$M175,0) -> 0.5 | C14: =IF('ProductSprint Backlog'!$L175>C$2,'ProductSprint Backlog'!$M175,0) -> 0.5 | D14: =IF('ProductSprint Backlog'!$L175>D$2,'ProductSprint Backlog'!$M175,0) -> 0 | E14: =IF('ProductSprint Backlog'!$L175>E$2,'ProductSprint Backlog'!$M175,0) -> 0 | F14: =IF('ProductSprint Backlog'!$L175>F$2,'ProductSprint Backlog'!$M175,0) -> 0 | G14: =IF('ProductSprint Backlog'!$L175>G$2,'ProductSprint Backlog'!$M175,0) -> 0 | H14: =IF('ProductSprint Backlog'!$L175>H$2,'ProductSprint Backlog'!$M175,0) -> 0 | I14: =IF('ProductSprint Backlog'!$L175>I$2,'ProductSprint Backlog'!$M175,0) -> 0 | ... P14: =IF('ProductSprint Backlog'!$L175>P$2,'ProductSprint Backlog'!$M175,0) -> 0
A15: Implementar en backend el parámetro sort=name:asc|desc con paginación consistente. | B15: =IF('ProductSprint Backlog'!$L176>B$2,'ProductSprint Backlog'!$M176,0) -> 0.5 | C15: =IF('ProductSprint Backlog'!$L176>C$2,'ProductSprint Backlog'!$M176,0) -> 0.5 | D15: =IF('ProductSprint Backlog'!$L176>D$2,'ProductSprint Backlog'!$M176,0) -> 0 | E15: =IF('ProductSprint Backlog'!$L176>E$2,'ProductSprint Backlog'!$M176,0) -> 0 | F15: =IF('ProductSprint Backlog'!$L176>F$2,'ProductSprint Backlog'!$M176,0) -> 0 | G15: =IF('ProductSprint Backlog'!$L176>G$2,'ProductSprint Backlog'!$M176,0) -> 0 | H15: =IF('ProductSprint Backlog'!$L176>H$2,'ProductSprint Backlog'!$M176,0) -> 0 | I15: =IF('ProductSprint Backlog'!$L176>I$2,'ProductSprint Backlog'!$M176,0) -> 0 | ... P15: =IF('ProductSprint Backlog'!$L176>P$2,'ProductSprint Backlog'!$M176,0) -> 0
A16: Implementar acción “Eliminar cliente” (eliminación lógica) en la ficha/listado de clientes con diálogo de confirmación y motivo (marcar estado “Inactivo/Eliminado”). | B16: =IF('ProductSprint Backlog'!$L177>B$2,'ProductSprint Backlog'!$M177,0) -> 1 | C16: =IF('ProductSprint Backlog'!$L177>C$2,'ProductSprint Backlog'!$M177,0) -> 1 | D16: =IF('ProductSprint Backlog'!$L177>D$2,'ProductSprint Backlog'!$M177,0) -> 1 | E16: =IF('ProductSprint Backlog'!$L177>E$2,'ProductSprint Backlog'!$M177,0) -> 1 | F16: =IF('ProductSprint Backlog'!$L177>F$2,'ProductSprint Backlog'!$M177,0) -> 1 | G16: =IF('ProductSprint Backlog'!$L177>G$2,'ProductSprint Backlog'!$M177,0) -> 1 | H16: =IF('ProductSprint Backlog'!$L177>H$2,'ProductSprint Backlog'!$M177,0) -> 1 | I16: =IF('ProductSprint Backlog'!$L177>I$2,'ProductSprint Backlog'!$M177,0) -> 0 | ... P16: =IF('ProductSprint Backlog'!$L177>P$2,'ProductSprint Backlog'!$M177,0) -> 0
A17: Desarrollar endpoint de backend para baja lógica con validaciones: usuario con rol administrador | B17: =IF('ProductSprint Backlog'!$L178>B$2,'ProductSprint Backlog'!$M178,0) -> 1 | C17: =IF('ProductSprint Backlog'!$L178>C$2,'ProductSprint Backlog'!$M178,0) -> 1 | D17: =IF('ProductSprint Backlog'!$L178>D$2,'ProductSprint Backlog'!$M178,0) -> 1 | E17: =IF('ProductSprint Backlog'!$L178>E$2,'ProductSprint Backlog'!$M178,0) -> 1 | F17: =IF('ProductSprint Backlog'!$L178>F$2,'ProductSprint Backlog'!$M178,0) -> 1 | G17: =IF('ProductSprint Backlog'!$L178>G$2,'ProductSprint Backlog'!$M178,0) -> 1 | H17: =IF('ProductSprint Backlog'!$L178>H$2,'ProductSprint Backlog'!$M178,0) -> 1 | I17: =IF('ProductSprint Backlog'!$L178>I$2,'ProductSprint Backlog'!$M178,0) -> 0 | ... P17: =IF('ProductSprint Backlog'!$L178>P$2,'ProductSprint Backlog'!$M178,0) -> 0
A18: Ajustar consultas/listados para excluir clientes inactivos en búsquedas y operaciones habituales . | B18: =IF('ProductSprint Backlog'!$L179>B$2,'ProductSprint Backlog'!$M179,0) -> 1 | C18: =IF('ProductSprint Backlog'!$L179>C$2,'ProductSprint Backlog'!$M179,0) -> 1 | D18: =IF('ProductSprint Backlog'!$L179>D$2,'ProductSprint Backlog'!$M179,0) -> 1 | E18: =IF('ProductSprint Backlog'!$L179>E$2,'ProductSprint Backlog'!$M179,0) -> 1 | F18: =IF('ProductSprint Backlog'!$L179>F$2,'ProductSprint Backlog'!$M179,0) -> 1 | G18: =IF('ProductSprint Backlog'!$L179>G$2,'ProductSprint Backlog'!$M179,0) -> 1 | H18: =IF('ProductSprint Backlog'!$L179>H$2,'ProductSprint Backlog'!$M179,0) -> 1 | I18: =IF('ProductSprint Backlog'!$L179>I$2,'ProductSprint Backlog'!$M179,0) -> 0 | ... P18: =IF('ProductSprint Backlog'!$L179>P$2,'ProductSprint Backlog'!$M179,0) -> 0
... A77: Auditoría y trazabilidad: registrar usuario, fecha/hora, estado previo, estado nuevo = Rechazado, motivo y id del informe. | B77: =IF('ProductSprint Backlog'!$L238>B$2,'ProductSprint Backlog'!$M238,0) -> 1 | C77: =IF('ProductSprint Backlog'!$L238>C$2,'ProductSprint Backlog'!$M238,0) -> 1 | D77: =IF('ProductSprint Backlog'!$L238>D$2,'ProductSprint Backlog'!$M238,0) -> 1 | E77: =IF('ProductSprint Backlog'!$L238>E$2,'ProductSprint Backlog'!$M238,0) -> 1 | F77: =IF('ProductSprint Backlog'!$L238>F$2,'ProductSprint Backlog'!$M238,0) -> 1 | G77: =IF('ProductSprint Backlog'!$L238>G$2,'ProductSprint Backlog'!$M238,0) -> 1 | H77: =IF('ProductSprint Backlog'!$L238>H$2,'ProductSprint Backlog'!$M238,0) -> 1 | I77: =IF('ProductSprint Backlog'!$L238>I$2,'ProductSprint Backlog'!$M238,0) -> 1 | ... P77: =IF('ProductSprint Backlog'!$L238>P$2,'ProductSprint Backlog'!$M238,0) -> 0

Sheet Tabla de Esfuerzo INC2 SPT1
B2: 45875 | C2: 45876 | D2: 45877 | E2: 45878 | F2: 45879 | G2: 45880 | H2: 45881 | I2: 45882 | J2: 45883 | K2: 45884 | L2: 45885 | M2: 45886 | N2: 45887 | O2: 45888 | P2: 45889 | Q2: 45890 | R2: 45891 | S2: 45892
A3: Tareas Pendientes | B3: =COUNTIFS('ProductSprint Backlog'!$D$86:$D$166,"<>",'ProductSprint Backlog'!$L$86:$L$166,">"&DATEVALUE(B2)) -> 0 | C3: =COUNTIFS('ProductSprint Backlog'!$D$86:$D$166,"<>",'ProductSprint Backlog'!$L$86:$L$166,">"&DATEVALUE(C2)) -> 0 | D3: =COUNTIFS('ProductSprint Backlog'!$D$86:$D$166,"<>",'ProductSprint Backlog'!$L$86:$L$166,">"&DATEVALUE(D2)) -> 0 | E3: =COUNTIFS('ProductSprint Backlog'!$D$86:$D$166,"<>",'ProductSprint Backlog'!$L$86:$L$166,">"&DATEVALUE(E2)) -> 0 | F3: =COUNTIFS('ProductSprint Backlog'!$D$86:$D$166,"<>",'ProductSprint Backlog'!$L$86:$L$166,">"&DATEVALUE(F2)) -> 0 | G3: =COUNTIFS('ProductSprint Backlog'!$D$86:$D$166,"<>",'ProductSprint Backlog'!$L$86:$L$166,">"&DATEVALUE(G2)) -> 0 | H3: =COUNTIFS('ProductSprint Backlog'!$D$86:$D$166,"<>",'ProductSprint Backlog'!$L$86:$L$166,">"&DATEVALUE(H2)) -> 0 | I3: =COUNTIFS('ProductSprint Backlog'!$D$86:$D$166,"<>",'ProductSprint Backlog'!$L$86:$L$166,">"&DATEVALUE(I2)) -> 0 | ... S3: =COUNTIFS('ProductSprint Backlog'!$D$86:$D$166,"<>",'ProductSprint Backlog'!$L$86:$L$166,">"&DATEVALUE(S2)) -> 0
A6: Tarea | B6: Esfuerzo
A7: Implementar boton para la aprobación de la cotización, y que este habilitado sólo si la cotización la orden de trabajo asociada está en estado "Cotización Enviada" | B7: =IF('ProductSprint Backlog'!$L86>B$2,'ProductSprint Backlog'!$M86,0) -> 0.5 | C7: =IF('ProductSprint Backlog'!$L86>C$2,'ProductSprint Backlog'!$M86,0) -> 0.5 | D7: =IF('ProductSprint Backlog'!$L86>D$2,'ProductSprint Backlog'!$M86,0) -> 0.5 | E7: =IF('ProductSprint Backlog'!$L86>E$2,'ProductSprint Backlog'!$M86,0) -> 0.5 | F7: =IF('ProductSprint Backlog'!$L86>F$2,'ProductSprint Backlog'!$M86,0) -> 0.5 | G7: =IF('ProductSprint Backlog'!$L86>G$2,'ProductSprint Backlog'!$M86,0) -> 0.5 | H7: =IF('ProductSprint Backlog'!$L86>H$2,'ProductSprint Backlog'!$M86,0) -> 0.5 | I7: =IF('ProductSprint Backlog'!$L86>I$2,'ProductSprint Backlog'!$M86,0) -> 0 | ... S7: =IF('ProductSprint Backlog'!$L86>S$2,'ProductSprint Backlog'!$M86,0) -> 0
A8: Implementar la confirmación de la aprobación de la cotización, que puede ser en forma de modal | B8: =IF('ProductSprint Backlog'!$L87>B$2,'ProductSprint Backlog'!$M87,0) -> 1 | C8: =IF('ProductSprint Backlog'!$L87>C$2,'ProductSprint Backlog'!$M87,0) -> 1 | D8: =IF('ProductSprint Backlog'!$L87>D$2,'ProductSprint Backlog'!$M87,0) -> 1 | E8: =IF('ProductSprint Backlog'!$L87>E$2,'ProductSprint Backlog'!$M87,0) -> 1 | F8: =IF('ProductSprint Backlog'!$L87>F$2,'ProductSprint Backlog'!$M87,0) -> 1 | G8: =IF('ProductSprint Backlog'!$L87>G$2,'ProductSprint Backlog'!$M87,0) -> 1 | H8: =IF('ProductSprint Backlog'!$L87>H$2,'ProductSprint Backlog'!$M87,0) -> 1 | I8: =IF('ProductSprint Backlog'!$L87>I$2,'ProductSprint Backlog'!$M87,0) -> 0 | ... S8: =IF('ProductSprint Backlog'!$L87>S$2,'ProductSprint Backlog'!$M87,0) -> 0
A9: Cambiar el estado de la orden de trabajo a "En reparación" | B9: =IF('ProductSprint Backlog'!$L88>B$2,'ProductSprint Backlog'!$M88,0) -> 0.5 | C9: =IF('ProductSprint Backlog'!$L88>C$2,'ProductSprint Backlog'!$M88,0) -> 0.5 | D9: =IF('ProductSprint Backlog'!$L88>D$2,'ProductSprint Backlog'!$M88,0) -> 0.5 | E9: =IF('ProductSprint Backlog'!$L88>E$2,'ProductSprint Backlog'!$M88,0) -> 0.5 | F9: =IF('ProductSprint Backlog'!$L88>F$2,'ProductSprint Backlog'!$M88,0) -> 0.5 | G9: =IF('ProductSprint Backlog'!$L88>G$2,'ProductSprint Backlog'!$M88,0) -> 0.5 | H9: =IF('ProductSprint Backlog'!$L88>H$2,'ProductSprint Backlog'!$M88,0) -> 0.5 | I9: =IF('ProductSprint Backlog'!$L88>I$2,'ProductSprint Backlog'!$M88,0) -> 0 | ... S9: =IF('ProductSprint Backlog'!$L88>S$2,'ProductSprint Backlog'!$M88,0) -> 0
A10: Registrar el evento en el log del sistema | B10: =IF('ProductSprint Backlog'!$L89>B$2,'ProductSprint Backlog'!$M89,0) -> 1 | C10: =IF('ProductSprint Backlog'!$L89>C$2,'ProductSprint Backlog'!$M89,0) -> 1 | D10: =IF('ProductSprint Backlog'!$L89>D$2,'ProductSprint Backlog'!$M89,0) -> 1 | E10: =IF('ProductSprint Backlog'!$L89>E$2,'ProductSprint Backlog'!$M89,0) -> 1 | F10: =IF('ProductSprint Backlog'!$L89>F$2,'ProductSprint Backlog'!$M89,0) -> 1 | G10: =IF('ProductSprint Backlog'!$L89>G$2,'ProductSprint Backlog'!$M89,0) -> 1 | H10: =IF('ProductSprint Backlog'!$L89>H$2,'ProductSprint Backlog'!$M89,0) -> 1 | I10: =IF('ProductSprint Backlog'!$L89>I$2,'ProductSprint Backlog'!$M89,0) -> 0 | ... S10: =IF('ProductSprint Backlog'!$L89>S$2,'ProductSprint Backlog'!$M89,0) -> 0
A11: Diseñar mensaje de confirmación luego de la realización de la acción de forma correcta, y su implementación | B11: =IF('ProductSprint Backlog'!$L90>B$2,'ProductSprint Backlog'!$M90,0) -> 0.5 | C11: =IF('ProductSprint Backlog'!$L90>C$2,'ProductSprint Backlog'!$M90,0) -> 0.5 | D11: =IF('ProductSprint Backlog'!$L90>D$2,'ProductSprint Backlog'!$M90,0) -> 0.5 | E11: =IF('ProductSprint Backlog'!$L90>E$2,'ProductSprint Backlog'!$M90,0) -> 0.5 | F11: =IF('ProductSprint Backlog'!$L90>F$2,'ProductSprint Backlog'!$M90,0) -> 0.5 | G11: =IF('ProductSprint Backlog'!$L90>G$2,'ProductSprint Backlog'!$M90,0) -> 0.5 | H11: =IF('ProductSprint Backlog'!$L90>H$2,'ProductSprint Backlog'!$M90,0) -> 0.5 | I11: =IF('ProductSprint Backlog'!$L90>I$2,'ProductSprint Backlog'!$M90,0) -> 0 | ... S11: =IF('ProductSprint Backlog'!$L90>S$2,'ProductSprint Backlog'!$M90,0) -> 0
A12: Implementar botón para el rechazo de la cotización, y que esté habilitado sólo si la cotización la orden de trabajo asociada está en estado "Cotización Enviada" | B12: =IF('ProductSprint Backlog'!$L91>B$2,'ProductSprint Backlog'!$M91,0) -> 0.5 | C12: =IF('ProductSprint Backlog'!$L91>C$2,'ProductSprint Backlog'!$M91,0) -> 0.5 | D12: =IF('ProductSprint Backlog'!$L91>D$2,'ProductSprint Backlog'!$M91,0) -> 0.5 | E12: =IF('ProductSprint Backlog'!$L91>E$2,'ProductSprint Backlog'!$M91,0) -> 0.5 | F12: =IF('ProductSprint Backlog'!$L91>F$2,'ProductSprint Backlog'!$M91,0) -> 0.5 | G12: =IF('ProductSprint Backlog'!$L91>G$2,'ProductSprint Backlog'!$M91,0) -> 0.5 | H12: =IF('ProductSprint Backlog'!$L91>H$2,'ProductSprint Backlog'!$M91,0) -> 0.5 | I12: =IF('ProductSprint Backlog'!$L91>I$2,'ProductSprint Backlog'!$M91,0) -> 0.5 | ... S12: =IF('ProductSprint Backlog'!$L91>S$2,'ProductSprint Backlog'!$M91,0) -> 0
A13: Implementar la confirmación del rechazo de la cotización, que puede ser en forma de modal. Además, incluir un campo opcional para ingresar el motivo del rechazo | B13: =IF('ProductSprint Backlog'!$L92>B$2,'ProductSprint Backlog'!$M92,0) -> 0.5 | C13: =IF('ProductSprint Backlog'!$L92>C$2,'ProductSprint Backlog'!$M92,0) -> 0.5 | D13: =IF('ProductSprint Backlog'!$L92>D$2,'ProductSprint Backlog'!$M92,0) -> 0.5 | E13: =IF('ProductSprint Backlog'!$L92>E$2,'ProductSprint Backlog'!$M92,0) -> 0.5 | F13: =IF('ProductSprint Backlog'!$L92>F$2,'ProductSprint Backlog'!$M92,0) -> 0.5 | G13: =IF('ProductSprint Backlog'!$L92>G$2,'ProductSprint Backlog'!$M92,0) -> 0.5 | H13: =IF('ProductSprint Backlog'!$L92>H$2,'ProductSprint Backlog'!$M92,0) -> 0.5 | I13: =IF('ProductSprint Backlog'!$L92>I$2,'ProductSprint Backlog'!$M92,0) -> 0.5 | ... S13: =IF('ProductSprint Backlog'!$L92>S$2,'ProductSprint Backlog'!$M92,0) -> 0
A14: Cambiar el estado de la orden de trabajo a "Cotización Rechazada" | B14: =IF('ProductSprint Backlog'!$L93>B$2,'ProductSprint Backlog'!$M93,0) -> 0.5 | C14: =IF('ProductSprint Backlog'!$L93>C$2,'ProductSprint Backlog'!$M93,0) -> 0.5 | D14: =IF('ProductSprint Backlog'!$L93>D$2,'ProductSprint Backlog'!$M93,0) -> 0.5 | E14: =IF('ProductSprint Backlog'!$L93>E$2,'ProductSprint Backlog'!$M93,0) -> 0.5 | F14: =IF('ProductSprint Backlog'!$L93>F$2,'ProductSprint Backlog'!$M93,0) -> 0.5 | G14: =IF('ProductSprint Backlog'!$L93>G$2,'ProductSprint Backlog'!$M93,0) -> 0.5 | H14: =IF('ProductSprint Backlog'!$L93>H$2,'ProductSprint Backlog'!$M93,0) -> 0.5 | I14: =IF('ProductSprint Backlog'!$L93>I$2,'ProductSprint Backlog'!$M93,0) -> 0.5 | ... S14: =IF('ProductSprint Backlog'!$L93>S$2,'ProductSprint Backlog'!$M93,0) -> 0
A15: Registrar el evento en el log del sistema | B15: =IF('ProductSprint Backlog'!$L94>B$2,'ProductSprint Backlog'!$M94,0) -> 0.5 | C15: =IF('ProductSprint Backlog'!$L94>C$2,'ProductSprint Backlog'!$M94,0) -> 0.5 | D15: =IF('ProductSprint Backlog'!$L94>D$2,'ProductSprint Backlog'!$M94,0) -> 0.5 | E15: =IF('ProductSprint Backlog'!$L94>E$2,'ProductSprint Backlog'!$M94,0) -> 0.5 | F15: =IF('ProductSprint Backlog'!$L94>F$2,'ProductSprint Backlog'!$M94,0) -> 0.5 | G15: =IF('ProductSprint Backlog'!$L94>G$2,'ProductSprint Backlog'!$M94,0) -> 0.5 | H15: =IF('ProductSprint Backlog'!$L94>H$2,'ProductSprint Backlog'!$M94,0) -> 0.5 | I15: =IF('ProductSprint Backlog'!$L94>I$2,'ProductSprint Backlog'!$M94,0) -> 0.5 | ... S15: =IF('ProductSprint Backlog'!$L94>S$2,'ProductSprint Backlog'!$M94,0) -> 0
A16: Diseñar mensaje de confirmación luego de la realización de la acción de forma correcta, y su implementación | B16: =IF('ProductSprint Backlog'!$L95>B$2,'ProductSprint Backlog'!$M95,0) -> 0.5 | C16: =IF('ProductSprint Backlog'!$L95>C$2,'ProductSprint Backlog'!$M95,0) -> 0.5 | D16: =IF('ProductSprint Backlog'!$L95>D$2,'ProductSprint Backlog'!$M95,0) -> 0.5 | E16: =IF('ProductSprint Backlog'!$L95>E$2,'ProductSprint Backlog'!$M95,0) -> 0.5 | F16: =IF('ProductSprint Backlog'!$L95>F$2,'ProductSprint Backlog'!$M95,0) -> 0.5 | G16: =IF('ProductSprint Backlog'!$L95>G$2,'ProductSprint Backlog'!$M95,0) -> 0.5 | H16: =IF('ProductSprint Backlog'!$L95>H$2,'ProductSprint Backlog'!$M95,0) -> 0.5 | I16: =IF('ProductSprint Backlog'!$L95>I$2,'ProductSprint Backlog'!$M95,0) -> 0.5 | ... S16: =IF('ProductSprint Backlog'!$L95>S$2,'ProductSprint Backlog'!$M95,0) -> 0
A18: Implementar botón para la declaración de no reparable, y que esté habilitado sólo si la cotización la orden de trabajo asociada está en estado "Recibido" | B18: =IF('ProductSprint Backlog'!$L97>B$2,'ProductSprint Backlog'!$M97,0) -> 0.5 | C18: =IF('ProductSprint Backlog'!$L97>C$2,'ProductSprint Backlog'!$M97,0) -> 0.5 | D18: =IF('ProductSprint Backlog'!$L97>D$2,'ProductSprint Backlog'!$M97,0) -> 0.5 | E18: =IF('ProductSprint Backlog'!$L97>E$2,'ProductSprint Backlog'!$M97,0) -> 0.5 | F18: =IF('ProductSprint Backlog'!$L97>F$2,'ProductSprint Backlog'!$M97,0) -> 0.5 | G18: =IF('ProductSprint Backlog'!$L97>G$2,'ProductSprint Backlog'!$M97,0) -> 0.5 | H18: =IF('ProductSprint Backlog'!$L97>H$2,'ProductSprint Backlog'!$M97,0) -> 0.5 | I18: =IF('ProductSprint Backlog'!$L97>I$2,'ProductSprint Backlog'!$M97,0) -> 0.5 | ... S18: =IF('ProductSprint Backlog'!$L97>S$2,'ProductSprint Backlog'!$M97,0) -> 0
A19: Implementar la confirmación de la declaración de abandono, que puede ser en forma de modal. Además, incluir un campo opcional para ingresar justificación o comentarios | B19: =IF('ProductSprint Backlog'!$L98>B$2,'ProductSprint Backlog'!$M98,0) -> 1 | C19: =IF('ProductSprint Backlog'!$L98>C$2,'ProductSprint Backlog'!$M98,0) -> 1 | D19: =IF('ProductSprint Backlog'!$L98>D$2,'ProductSprint Backlog'!$M98,0) -> 1 | E19: =IF('ProductSprint Backlog'!$L98>E$2,'ProductSprint Backlog'!$M98,0) -> 1 | F19: =IF('ProductSprint Backlog'!$L98>F$2,'ProductSprint Backlog'!$M98,0) -> 1 | G19: =IF('ProductSprint Backlog'!$L98>G$2,'ProductSprint Backlog'!$M98,0) -> 1 | H19: =IF('ProductSprint Backlog'!$L98>H$2,'ProductSprint Backlog'!$M98,0) -> 1 | I19: =IF('ProductSprint Backlog'!$L98>I$2,'ProductSprint Backlog'!$M98,0) -> 1 | ... S19: =IF('ProductSprint Backlog'!$L98>S$2,'ProductSprint Backlog'!$M98,0) -> 0
... A48: Asegurar actualización dinámica de los cambios visuales | B48: =IF('ProductSprint Backlog'!$L127>B$2,'ProductSprint Backlog'!$M127,0) -> 1 | C48: =IF('ProductSprint Backlog'!$L127>C$2,'ProductSprint Backlog'!$M127,0) -> 1 | D48: =IF('ProductSprint Backlog'!$L127>D$2,'ProductSprint Backlog'!$M127,0) -> 1 | E48: =IF('ProductSprint Backlog'!$L127>E$2,'ProductSprint Backlog'!$M127,0) -> 1 | F48: =IF('ProductSprint Backlog'!$L127>F$2,'ProductSprint Backlog'!$M127,0) -> 0 | G48: =IF('ProductSprint Backlog'!$L127>G$2,'ProductSprint Backlog'!$M127,0) -> 0 | H48: =IF('ProductSprint Backlog'!$L127>H$2,'ProductSprint Backlog'!$M127,0) -> 0 | I48: =IF('ProductSprint Backlog'!$L127>I$2,'ProductSprint Backlog'!$M127,0) -> 0 | ... S48: =IF('ProductSprint Backlog'!$L127>S$2,'ProductSprint Backlog'!$M127,0) -> 0
B49: =IF('ProductSprint Backlog'!$L128>B$2,'ProductSprint Backlog'!$M128,0) -> 0 | C49: =IF('ProductSprint Backlog'!$L128>C$2,'ProductSprint Backlog'!$M128,0) -> 0 | D49: =IF('ProductSprint Backlog'!$L128>D$2,'ProductSprint Backlog'!$M128,0) -> 0 | E49: =IF('ProductSprint Backlog'!$L128>E$2,'ProductSprint Backlog'!$M128,0) -> 0 | F49: =IF('ProductSprint Backlog'!$L128>F$2,'ProductSprint Backlog'!$M128,0) -> 0 | G49: =IF('ProductSprint Backlog'!$L128>G$2,'ProductSprint Backlog'!$M128,0) -> 0 | H49: =IF('ProductSprint Backlog'!$L128>H$2,'ProductSprint Backlog'!$M128,0) -> 0 | I49: =IF('ProductSprint Backlog'!$L128>I$2,'ProductSprint Backlog'!$M128,0) -> 0 | ... S49: =IF('ProductSprint Backlog'!$L128>S$2,'ProductSprint Backlog'!$M128,0) -> 0
A50: Diseñar menú de filtrado de órdenes de trabajo y opción de fecha, donde pueda seleccionar una fecha o un rango de fechas de ingreso | B50: =IF('ProductSprint Backlog'!$L129>B$2,'ProductSprint Backlog'!$M129,0) -> 0 | C50: =IF('ProductSprint Backlog'!$L129>C$2,'ProductSprint Backlog'!$M129,0) -> 0 | D50: =IF('ProductSprint Backlog'!$L129>D$2,'ProductSprint Backlog'!$M129,0) -> 0 | E50: =IF('ProductSprint Backlog'!$L129>E$2,'ProductSprint Backlog'!$M129,0) -> 0 | F50: =IF('ProductSprint Backlog'!$L129>F$2,'ProductSprint Backlog'!$M129,0) -> 0 | G50: =IF('ProductSprint Backlog'!$L129>G$2,'ProductSprint Backlog'!$M129,0) -> 0 | H50: =IF('ProductSprint Backlog'!$L129>H$2,'ProductSprint Backlog'!$M129,0) -> 0 | I50: =IF('ProductSprint Backlog'!$L129>I$2,'ProductSprint Backlog'!$M129,0) -> 0 | ... S50: =IF('ProductSprint Backlog'!$L129>S$2,'ProductSprint Backlog'!$M129,0) -> 0
A51: Implementar la funcionalidad del filtro, cumpliendo las condiciones seleccionadas | B51: =IF('ProductSprint Backlog'!$L130>B$2,'ProductSprint Backlog'!$M130,0) -> 0 | C51: =IF('ProductSprint Backlog'!$L130>C$2,'ProductSprint Backlog'!$M130,0) -> 0 | D51: =IF('ProductSprint Backlog'!$L130>D$2,'ProductSprint Backlog'!$M130,0) -> 0 | E51: =IF('ProductSprint Backlog'!$L130>E$2,'ProductSprint Backlog'!$M130,0) -> 0 | F51: =IF('ProductSprint Backlog'!$L130>F$2,'ProductSprint Backlog'!$M130,0) -> 0 | G51: =IF('ProductSprint Backlog'!$L130>G$2,'ProductSprint Backlog'!$M130,0) -> 0 | H51: =IF('ProductSprint Backlog'!$L130>H$2,'ProductSprint Backlog'!$M130,0) -> 0 | I51: =IF('ProductSprint Backlog'!$L130>I$2,'ProductSprint Backlog'!$M130,0) -> 0 | ... S51: =IF('ProductSprint Backlog'!$L130>S$2,'ProductSprint Backlog'!$M130,0) -> 0
A52: Agregar la funcionalidad de eliminar el filtro, llevando a la recarga del listado completo | B52: =IF('ProductSprint Backlog'!$L131>B$2,'ProductSprint Backlog'!$M131,0) -> 0 | C52: =IF('ProductSprint Backlog'!$L131>C$2,'ProductSprint Backlog'!$M131,0) -> 0 | D52: =IF('ProductSprint Backlog'!$L131>D$2,'ProductSprint Backlog'!$M131,0) -> 0 | E52: =IF('ProductSprint Backlog'!$L131>E$2,'ProductSprint Backlog'!$M131,0) -> 0 | F52: =IF('ProductSprint Backlog'!$L131>F$2,'ProductSprint Backlog'!$M131,0) -> 0 | G52: =IF('ProductSprint Backlog'!$L131>G$2,'ProductSprint Backlog'!$M131,0) -> 0 | H52: =IF('ProductSprint Backlog'!$L131>H$2,'ProductSprint Backlog'!$M131,0) -> 0 | I52: =IF('ProductSprint Backlog'!$L131>I$2,'ProductSprint Backlog'!$M131,0) -> 0 | ... S52: =IF('ProductSprint Backlog'!$L131>S$2,'ProductSprint Backlog'!$M131,0) -> 0
A53: Diseñar filtrado por prioridad, donde pueda seleccionar, por medio de checkbox o similar, las prioridades a filtrar | B53: =IF('ProductSprint Backlog'!$L132>B$2,'ProductSprint Backlog'!$M132,0) -> 1 | C53: =IF('ProductSprint Backlog'!$L132>C$2,'ProductSprint Backlog'!$M132,0) -> 1 | D53: =IF('ProductSprint Backlog'!$L132>D$2,'ProductSprint Backlog'!$M132,0) -> 1 | E53: =IF('ProductSprint Backlog'!$L132>E$2,'ProductSprint Backlog'!$M132,0) -> 1 | F53: =IF('ProductSprint Backlog'!$L132>F$2,'ProductSprint Backlog'!$M132,0) -> 1 | G53: =IF('ProductSprint Backlog'!$L132>G$2,'ProductSprint Backlog'!$M132,0) -> 1 | H53: =IF('ProductSprint Backlog'!$L132>H$2,'ProductSprint Backlog'!$M132,0) -> 1 | I53: =IF('ProductSprint Backlog'!$L132>I$2,'ProductSprint Backlog'!$M132,0) -> 0 | ... S53: =IF('ProductSprint Backlog'!$L132>S$2,'ProductSprint Backlog'!$M132,0) -> 0
A54: Implementar la funcionalidad del filtro, cumpliendo las condiciones seleccionadas | B54: =IF('ProductSprint Backlog'!$L133>B$2,'ProductSprint Backlog'!$M133,0) -> 0.5 | C54: =IF('ProductSprint Backlog'!$L133>C$2,'ProductSprint Backlog'!$M133,0) -> 0.5 | D54: =IF('ProductSprint Backlog'!$L133>D$2,'ProductSprint Backlog'!$M133,0) -> 0.5 | E54: =IF('ProductSprint Backlog'!$L133>E$2,'ProductSprint Backlog'!$M133,0) -> 0.5 | F54: =IF('ProductSprint Backlog'!$L133>F$2,'ProductSprint Backlog'!$M133,0) -> 0.5 | G54: =IF('ProductSprint Backlog'!$L133>G$2,'ProductSprint Backlog'!$M133,0) -> 0.5 | H54: =IF('ProductSprint Backlog'!$L133>H$2,'ProductSprint Backlog'!$M133,0) -> 0.5 | I54: =IF('ProductSprint Backlog'!$L133>I$2,'ProductSprint Backlog'!$M133,0) -> 0 | ... S54: =IF('ProductSprint Backlog'!$L133>S$2,'ProductSprint Backlog'!$M133,0) -> 0
A55: Agregar la funcionalidad de eliminar el filtro, llevando a la recarga del listado completo | B55: =IF('ProductSprint Backlog'!$L134>B$2,'ProductSprint Backlog'!$M134,0) -> 0.5 | C55: =IF('ProductSprint Backlog'!$L134>C$2,'ProductSprint Backlog'!$M134,0) -> 0.5 | D55: =IF('ProductSprint Backlog'!$L134>D$2,'ProductSprint Backlog'!$M134,0) -> 0.5 | E55: =IF('ProductSprint Backlog'!$L134>E$2,'ProductSprint Backlog'!$M134,0) -> 0.5 | F55: =IF('ProductSprint Backlog'!$L134>F$2,'ProductSprint Backlog'!$M134,0) -> 0.5 | G55: =IF('ProductSprint Backlog'!$L134>G$2,'ProductSprint Backlog'!$M134,0) -> 0.5 | H55: =IF('ProductSprint Backlog'!$L134>H$2,'ProductSprint Backlog'!$M134,0) -> 0.5 | I55: =IF('ProductSprint Backlog'!$L134>I$2,'ProductSprint Backlog'!$M134,0) -> 0 | ... S55: =IF('ProductSprint Backlog'!$L134>S$2,'ProductSprint Backlog'!$M134,0) -> 0
A56: Diseñar filtrado por marca, donde pueda seleccionar, por medio de radiobuttons o similar, la marca con la que filtrar | B56: =IF('ProductSprint Backlog'!$L135>B$2,'ProductSprint Backlog'!$M135,0) -> 1 | C56: =IF('ProductSprint Backlog'!$L135>C$2,'ProductSprint Backlog'!$M135,0) -> 1 | D56: =IF('ProductSprint Backlog'!$L135>D$2,'ProductSprint Backlog'!$M135,0) -> 1 | E56: =IF('ProductSprint Backlog'!$L135>E$2,'ProductSprint Backlog'!$M135,0) -> 1 | F56: =IF('ProductSprint Backlog'!$L135>F$2,'ProductSprint Backlog'!$M135,0) -> 1 | G56: =IF('ProductSprint Backlog'!$L135>G$2,'ProductSprint Backlog'!$M135,0) -> 1 | H56: =IF('ProductSprint Backlog'!$L135>H$2,'ProductSprint Backlog'!$M135,0) -> 1 | I56: =IF('ProductSprint Backlog'!$L135>I$2,'ProductSprint Backlog'!$M135,0) -> 1 | ... S56: =IF('ProductSprint Backlog'!$L135>S$2,'ProductSprint Backlog'!$M135,0) -> 0
A57: Implementar la funcionalidad del filtro, cumpliendo las condiciones seleccionadas | B57: =IF('ProductSprint Backlog'!$L136>B$2,'ProductSprint Backlog'!$M136,0) -> 1 | C57: =IF('ProductSprint Backlog'!$L136>C$2,'ProductSprint Backlog'!$M136,0) -> 1 | D57: =IF('ProductSprint Backlog'!$L136>D$2,'ProductSprint Backlog'!$M136,0) -> 1 | E57: =IF('ProductSprint Backlog'!$L136>E$2,'ProductSprint Backlog'!$M136,0) -> 1 | F57: =IF('ProductSprint Backlog'!$L136>F$2,'ProductSprint Backlog'!$M136,0) -> 1 | G57: =IF('ProductSprint Backlog'!$L136>G$2,'ProductSprint Backlog'!$M136,0) -> 1 | H57: =IF('ProductSprint Backlog'!$L136>H$2,'ProductSprint Backlog'!$M136,0) -> 1 | I57: =IF('ProductSprint Backlog'!$L136>I$2,'ProductSprint Backlog'!$M136,0) -> 1 | ... S57: =IF('ProductSprint Backlog'!$L136>S$2,'ProductSprint Backlog'!$M136,0) -> 0
A58: Agregar la funcionalidad de eliminar el filtro, llevando a la recarga del listado completo | B58: =IF('ProductSprint Backlog'!$L137>B$2,'ProductSprint Backlog'!$M137,0) -> 1 | C58: =IF('ProductSprint Backlog'!$L137>C$2,'ProductSprint Backlog'!$M137,0) -> 1 | D58: =IF('ProductSprint Backlog'!$L137>D$2,'ProductSprint Backlog'!$M137,0) -> 1 | E58: =IF('ProductSprint Backlog'!$L137>E$2,'ProductSprint Backlog'!$M137,0) -> 1 | F58: =IF('ProductSprint Backlog'!$L137>F$2,'ProductSprint Backlog'!$M137,0) -> 1 | G58: =IF('ProductSprint Backlog'!$L137>G$2,'ProductSprint Backlog'!$M137,0) -> 1 | H58: =IF('ProductSprint Backlog'!$L137>H$2,'ProductSprint Backlog'!$M137,0) -> 1 | I58: =IF('ProductSprint Backlog'!$L137>I$2,'ProductSprint Backlog'!$M137,0) -> 1 | ... S58: =IF('ProductSprint Backlog'!$L137>S$2,'ProductSprint Backlog'!$M137,0) -> 0
A59: Diseñar filtrado por modelo, donde pueda seleccionar, por medio de texto, el modelo con el que filtrar | B59: =IF('ProductSprint Backlog'!$L138>B$2,'ProductSprint Backlog'!$M138,0) -> 1 | C59: =IF('ProductSprint Backlog'!$L138>C$2,'ProductSprint Backlog'!$M138,0) -> 1 | D59: =IF('ProductSprint Backlog'!$L138>D$2,'ProductSprint Backlog'!$M138,0) -> 1 | E59: =IF('ProductSprint Backlog'!$L138>E$2,'ProductSprint Backlog'!$M138,0) -> 1 | F59: =IF('ProductSprint Backlog'!$L138>F$2,'ProductSprint Backlog'!$M138,0) -> 1 | G59: =IF('ProductSprint Backlog'!$L138>G$2,'ProductSprint Backlog'!$M138,0) -> 1 | H59: =IF('ProductSprint Backlog'!$L138>H$2,'ProductSprint Backlog'!$M138,0) -> 1 | I59: =IF('ProductSprint Backlog'!$L138>I$2,'ProductSprint Backlog'!$M138,0) -> 1 | ... S59: =IF('ProductSprint Backlog'!$L138>S$2,'ProductSprint Backlog'!$M138,0) -> 0
A60: Implementar la funcionalidad del filtro, cumpliendo las condiciones seleccionadas | B60: =IF('ProductSprint Backlog'!$L139>B$2,'ProductSprint Backlog'!$M139,0) -> 1 | C60: =IF('ProductSprint Backlog'!$L139>C$2,'ProductSprint Backlog'!$M139,0) -> 1 | D60: =IF('ProductSprint Backlog'!$L139>D$2,'ProductSprint Backlog'!$M139,0) -> 1 | E60: =IF('ProductSprint Backlog'!$L139>E$2,'ProductSprint Backlog'!$M139,0) -> 1 | F60: =IF('ProductSprint Backlog'!$L139>F$2,'ProductSprint Backlog'!$M139,0) -> 1 | G60: =IF('ProductSprint Backlog'!$L139>G$2,'ProductSprint Backlog'!$M139,0) -> 1 | H60: =IF('ProductSprint Backlog'!$L139>H$2,'ProductSprint Backlog'!$M139,0) -> 1 | I60: =IF('ProductSprint Backlog'!$L139>I$2,'ProductSprint Backlog'!$M139,0) -> 1 | ... S60: =IF('ProductSprint Backlog'!$L139>S$2,'ProductSprint Backlog'!$M139,0) -> 0
A61: Agregar la funcionalidad de eliminar el filtro, llevando a la recarga del listado completo | B61: =IF('ProductSprint Backlog'!$L140>B$2,'ProductSprint Backlog'!$M140,0) -> 1 | C61: =IF('ProductSprint Backlog'!$L140>C$2,'ProductSprint Backlog'!$M140,0) -> 1 | D61: =IF('ProductSprint Backlog'!$L140>D$2,'ProductSprint Backlog'!$M140,0) -> 1 | E61: =IF('ProductSprint Backlog'!$L140>E$2,'ProductSprint Backlog'!$M140,0) -> 1 | F61: =IF('ProductSprint Backlog'!$L140>F$2,'ProductSprint Backlog'!$M140,0) -> 1 | G61: =IF('ProductSprint Backlog'!$L140>G$2,'ProductSprint Backlog'!$M140,0) -> 1 | H61: =IF('ProductSprint Backlog'!$L140>H$2,'ProductSprint Backlog'!$M140,0) -> 1 | I61: =IF('ProductSprint Backlog'!$L140>I$2,'ProductSprint Backlog'!$M140,0) -> 1 | ... S61: =IF('ProductSprint Backlog'!$L140>S$2,'ProductSprint Backlog'!$M140,0) -> 0
... A87: Habilitar la Opcion de descarga del documento PDF tras su generación, permitiendo al usuario guardarlo en cualquier lugar de su dispositivo. | B87: =IF('ProductSprint Backlog'!$L166>B$2,'ProductSprint Backlog'!$M166,0) -> 1 | C87: =IF('ProductSprint Backlog'!$L166>C$2,'ProductSprint Backlog'!$M166,0) -> 1 | D87: =IF('ProductSprint Backlog'!$L166>D$2,'ProductSprint Backlog'!$M166,0) -> 1 | E87: =IF('ProductSprint Backlog'!$L166>E$2,'ProductSprint Backlog'!$M166,0) -> 1 | F87: =IF('ProductSprint Backlog'!$L166>F$2,'ProductSprint Backlog'!$M166,0) -> 1 | G87: =IF('ProductSprint Backlog'!$L166>G$2,'ProductSprint Backlog'!$M166,0) -> 1 | H87: =IF('ProductSprint Backlog'!$L166>H$2,'ProductSprint Backlog'!$M166,0) -> 1 | I87: =IF('ProductSprint Backlog'!$L166>I$2,'ProductSprint Backlog'!$M166,0) -> 1 | ... S87: =IF('ProductSprint Backlog'!$L166>S$2,'ProductSprint Backlog'!$M166,0) -> 0

Sheet BurnUp-BurnDown INC 1
A1: Periodo de Sprint | D1: 45806 | E1: 45819 | F1: =E1-D1 -> 13
B4: 45806 | C4: 45807 | D4: 45808 | E4: 45809 | F4: 45810 | G4: 45811 | H4: 45812 | I4: 45813 | J4: 45814 | K4: 45815 | L4: 45816 | M4: 45817 | N4: 45818 | O4: 45819
B5: DÍa 1 | C5: DÍa 2 | D5: DÍa 3 | E5: DÍa 4 | F5: DÍa 5 | G5: DÍa 6 | H5: DÍa 7 | I5: DÍa 8 | J5: DÍa 9 | K5: DÍa 10 | L5: DÍa 11 | M5: DÍa 12 | N5: DÍa 13 | O5: DÍa 14
A6: Esfuerzo Real Acumulado (HH) | B6: 0 | C6: =SUM('Auxiliar EsfuerzoDia'!B3:B84) -> 1.75 | D6: =SUM('Auxiliar EsfuerzoDia'!C3:C84)+C6 -> 4.5 | E6: =SUM('Auxiliar EsfuerzoDia'!D3:D84)+D6 -> 10.166667 | F6: =SUM('Auxiliar EsfuerzoDia'!E3:E84)+E6 -> 19.333333 | G6: =SUM('Auxiliar EsfuerzoDia'!F3:F84)+F6 -> 34 | H6: =SUM('Auxiliar EsfuerzoDia'!G3:G84)+G6 -> 50.666667 | I6: =SUM('Auxiliar EsfuerzoDia'!H3:H84)+H6 -> 63.416667 | J6: =SUM('Auxiliar EsfuerzoDia'!I3:I84)+I6 -> 72.833333 | K6: =SUM('Auxiliar EsfuerzoDia'!J3:J84)+J6 -> 88.583333 | ... O6: =SUM('Auxiliar EsfuerzoDia'!N3:N84)+N6 -> 126.5
A7: Esfuerzo Estimado Acumulado (HH) | B7: 0 | C7: =SUM('Auxiliar Esfuerzo Estimado'!B3:B84) -> 3.5 | D7: =SUM('Auxiliar Esfuerzo Estimado'!C3:C84)+C7 -> 8 | E7: =SUM('Auxiliar Esfuerzo Estimado'!D3:D84)+D7 -> 16.35 | F7: =SUM('Auxiliar Esfuerzo Estimado'!E3:E84)+E7 -> 24.7 | G7: =SUM('Auxiliar Esfuerzo Estimado'!F3:F84)+F7 -> 47.05 | H7: =SUM('Auxiliar Esfuerzo Estimado'!G3:G84)+G7 -> 65.066667 | I7: =SUM('Auxiliar Esfuerzo Estimado'!H3:H84)+H7 -> 82.833333 | J7: =SUM('Auxiliar Esfuerzo Estimado'!I3:I84)+I7 -> 99.9 | K7: =SUM('Auxiliar Esfuerzo Estimado'!J3:J84)+J7 -> 112.3 | ... O7: =SUM('Auxiliar Esfuerzo Estimado'!N3:N84)+N7 -> 143
B13: 45806 | C13: 45807 | D13: 45808 | E13: 45809 | F13: 45810 | G13: 45811 | H13: 45812 | I13: 45813 | J13: 45814 | K13: 45815 | L13: 45816 | M13: 45817 | N13: 45818 | O13: 45819
B14: DÍa 1 | C14: DÍa 2 | D14: DÍa 3 | E14: DÍa 4 | F14: DÍa 5 | G14: DÍa 6 | H14: DÍa 7 | I14: DÍa 8 | J14: DÍa 9 | K14: DÍa 10 | L14: DÍa 11 | M14: DÍa 12 | N14: DÍa 13 | O14: DÍa 14
A15: Esfuerzo Real Restante (HH) | B15: =126.5-B6 -> 126.5 | C15: =B15-SUM('Auxiliar EsfuerzoDia'!B3:B84) -> 124.75 | D15: =C15-SUM('Auxiliar EsfuerzoDia'!C3:C84) -> 122 | E15: =D15-SUM('Auxiliar EsfuerzoDia'!D3:D84) -> 116.33333 | F15: =E15-SUM('Auxiliar EsfuerzoDia'!E3:E84) -> 107.16667 | G15: =F15-SUM('Auxiliar EsfuerzoDia'!F3:F84) -> 92.5 | H15: =G15-SUM('Auxiliar EsfuerzoDia'!G3:G84) -> 75.833333 | I15: =H15-SUM('Auxiliar EsfuerzoDia'!H3:H84) -> 63.083333 | J15: =I15-SUM('Auxiliar EsfuerzoDia'!I3:I84) -> 53.666667 | ... O15: =N15-SUM('Auxiliar EsfuerzoDia'!N3:N84) -> -1.4210855e-14
A16: Esfuerzo Estimado Restante (HH) | B16: =143-B7 -> 143 | C16: =B16-SUM('Auxiliar Esfuerzo Estimado'!B3:B84) -> 139.5 | D16: =C16-SUM('Auxiliar Esfuerzo Estimado'!C3:C84) -> 135 | E16: =D16-SUM('Auxiliar Esfuerzo Estimado'!D3:D84) -> 126.65 | F16: =E16-SUM('Auxiliar Esfuerzo Estimado'!E3:E84) -> 118.3 | G16: =F16-SUM('Auxiliar Esfuerzo Estimado'!F3:F84) -> 95.95 | H16: =G16-SUM('Auxiliar Esfuerzo Estimado'!G3:G84) -> 77.933333 | I16: =H16-SUM('Auxiliar Esfuerzo Estimado'!H3:H84) -> 60.166667 | J16: =I16-SUM('Auxiliar Esfuerzo Estimado'!I3:I84) -> 43.1 | ... O16: =N16-SUM('Auxiliar Esfuerzo Estimado'!N3:N84) -> 2.4868996e-14

Sheet Tabla de Esfuerzo
B2: 45806 | C2: 45807 | D2: 45808 | E2: 45809 | F2: 45810 | G2: 45811 | H2: 45812 | I2: 45813 | J2: 45814 | K2: 45815 | L2: 45816 | M2: 45817 | N2: 45818 | O2: 45819
A3: Tareas Pendientes | B3: =COUNTIFS('ProductSprint Backlog'!$D$3:$D$84,"<>",'ProductSprint Backlog'!$L$3:$L$84,">"&DATEVALUE(B2)) -> 0 | C3: =COUNTIFS('ProductSprint Backlog'!$D$3:$D$84,"<>",'ProductSprint Backlog'!$L$3:$L$84,">"&DATEVALUE(C2)) -> 0 | D3: =COUNTIFS('ProductSprint Backlog'!$D$3:$D$84,"<>",'ProductSprint Backlog'!$L$3:$L$84,">"&DATEVALUE(D2)) -> 0 | E3: =COUNTIFS('ProductSprint Backlog'!$D$3:$D$84,"<>",'ProductSprint Backlog'!$L$3:$L$84,">"&DATEVALUE(E2)) -> 0 | F3: =COUNTIFS('ProductSprint Backlog'!$D$3:$D$84,"<>",'ProductSprint Backlog'!$L$3:$L$84,">"&DATEVALUE(F2)) -> 0 | G3: =COUNTIFS('ProductSprint Backlog'!$D$3:$D$84,"<>",'ProductSprint Backlog'!$L$3:$L$84,">"&DATEVALUE(G2)) -> 0 | H3: =COUNTIFS('ProductSprint Backlog'!$D$3:$D$84,"<>",'ProductSprint Backlog'!$L$3:$L$84,">"&DATEVALUE(H2)) -> 0 | I3: =COUNTIFS('ProductSprint Backlog'!$D$3:$D$84,"<>",'ProductSprint Backlog'!$L$3:$L$84,">"&DATEVALUE(I2)) -> 0 | ... O3: =COUNTIFS('ProductSprint Backlog'!$D$3:$D$84,"<>",'ProductSprint Backlog'!$L$3:$L$84,">"&DATEVALUE(O2)) -> 0
A4: Horas Pendientes | B4: =SUMIF('ProductSprint Backlog'!$J$3:$J$84,">"&DATEVALUE(B2),'ProductSprint Backlog'!$F$3:$F$84) -> 0 | C4: =SUMIF('ProductSprint Backlog'!$J$3:$J$84,">"&DATEVALUE(C2),'ProductSprint Backlog'!$F$3:$F$84) -> 0 | D4: =SUMIF('ProductSprint Backlog'!$J$3:$J$84,">"&DATEVALUE(D2),'ProductSprint Backlog'!$F$3:$F$84) -> 0 | E4: =SUMIF('ProductSprint Backlog'!$J$3:$J$84,">"&DATEVALUE(E2),'ProductSprint Backlog'!$F$3:$F$84) -> 0 | F4: =SUMIF('ProductSprint Backlog'!$J$3:$J$84,">"&DATEVALUE(F2),'ProductSprint Backlog'!$F$3:$F$84) -> 0 | G4: =SUMIF('ProductSprint Backlog'!$J$3:$J$84,">"&DATEVALUE(G2),'ProductSprint Backlog'!$F$3:$F$84) -> 0 | H4: =SUMIF('ProductSprint Backlog'!$J$3:$J$84,">"&DATEVALUE(H2),'ProductSprint Backlog'!$F$3:$F$84) -> 0 | I4: =SUMIF('ProductSprint Backlog'!$J$3:$J$84,">"&DATEVALUE(I2),'ProductSprint Backlog'!$F$3:$F$84) -> 0 | ... O4: =SUMIF('ProductSprint Backlog'!$J$3:$J$84,">"&DATEVALUE(O2),'ProductSprint Backlog'!$F$3:$F$84) -> 0
A7: Tarea | B7: Esfuerzo
A8: Diseñar y desarrollar el formulario de login. | B8: =IF('ProductSprint Backlog'!$L3>B$2,'ProductSprint Backlog'!$M3,0) -> 4.5 | C8: =IF('ProductSprint Backlog'!$L3>C$2,'ProductSprint Backlog'!$M3,0) -> 4.5 | D8: =IF('ProductSprint Backlog'!$L3>D$2,'ProductSprint Backlog'!$M3,0) -> 4.5 | E8: =IF('ProductSprint Backlog'!$L3>E$2,'ProductSprint Backlog'!$M3,0) -> 4.5 | F8: =IF('ProductSprint Backlog'!$L3>F$2,'ProductSprint Backlog'!$M3,0) -> 4.5 | G8: =IF('ProductSprint Backlog'!$L3>G$2,'ProductSprint Backlog'!$M3,0) -> 4.5 | H8: =IF('ProductSprint Backlog'!$L3>H$2,'ProductSprint Backlog'!$M3,0) -> 0 | I8: =IF('ProductSprint Backlog'!$L3>I$2,'ProductSprint Backlog'!$M3,0) -> 0 | ... O8: =IF('ProductSprint Backlog'!$L3>O$2,'ProductSprint Backlog'!$M3,0) -> 0
A9: Implementar validación de formato y de credenciales contra base de datos. | B9: =IF('ProductSprint Backlog'!$L4>B$2,'ProductSprint Backlog'!$M4,0) -> 2 | C9: =IF('ProductSprint Backlog'!$L4>C$2,'ProductSprint Backlog'!$M4,0) -> 2 | D9: =IF('ProductSprint Backlog'!$L4>D$2,'ProductSprint Backlog'!$M4,0) -> 2 | E9: =IF('ProductSprint Backlog'!$L4>E$2,'ProductSprint Backlog'!$M4,0) -> 2 | F9: =IF('ProductSprint Backlog'!$L4>F$2,'ProductSprint Backlog'!$M4,0) -> 2 | G9: =IF('ProductSprint Backlog'!$L4>G$2,'ProductSprint Backlog'!$M4,0) -> 2 | H9: =IF('ProductSprint Backlog'!$L4>H$2,'ProductSprint Backlog'!$M4,0) -> 2 | I9: =IF('ProductSprint Backlog'!$L4>I$2,'ProductSprint Backlog'!$M4,0) -> 0 | ... O9: =IF('ProductSprint Backlog'!$L4>O$2,'ProductSprint Backlog'!$M4,0) -> 0
A10: Redireccionar a vista según rol del usuario. | B10: =IF('ProductSprint Backlog'!$L5>B$2,'ProductSprint Backlog'!$M5,0) -> 1.5 | C10: =IF('ProductSprint Backlog'!$L5>C$2,'ProductSprint Backlog'!$M5,0) -> 1.5 | D10: =IF('ProductSprint Backlog'!$L5>D$2,'ProductSprint Backlog'!$M5,0) -> 1.5 | E10: =IF('ProductSprint Backlog'!$L5>E$2,'ProductSprint Backlog'!$M5,0) -> 1.5 | F10: =IF('ProductSprint Backlog'!$L5>F$2,'ProductSprint Backlog'!$M5,0) -> 1.5 | G10: =IF('ProductSprint Backlog'!$L5>G$2,'ProductSprint Backlog'!$M5,0) -> 1.5 | H10: =IF('ProductSprint Backlog'!$L5>H$2,'ProductSprint Backlog'!$M5,0) -> 0 | I10: =IF('ProductSprint Backlog'!$L5>I$2,'ProductSprint Backlog'!$M5,0) -> 0 | ... O10: =IF('ProductSprint Backlog'!$L5>O$2,'ProductSprint Backlog'!$M5,0) -> 0
A11: Registrar evento de inicio de sesión en logs. | B11: =IF('ProductSprint Backlog'!$L6>B$2,'ProductSprint Backlog'!$M6,0) -> 2 | C11: =IF('ProductSprint Backlog'!$L6>C$2,'ProductSprint Backlog'!$M6,0) -> 2 | D11: =IF('ProductSprint Backlog'!$L6>D$2,'ProductSprint Backlog'!$M6,0) -> 2 | E11: =IF('ProductSprint Backlog'!$L6>E$2,'ProductSprint Backlog'!$M6,0) -> 2 | F11: =IF('ProductSprint Backlog'!$L6>F$2,'ProductSprint Backlog'!$M6,0) -> 2 | G11: =IF('ProductSprint Backlog'!$L6>G$2,'ProductSprint Backlog'!$M6,0) -> 2 | H11: =IF('ProductSprint Backlog'!$L6>H$2,'ProductSprint Backlog'!$M6,0) -> 2 | I11: =IF('ProductSprint Backlog'!$L6>I$2,'ProductSprint Backlog'!$M6,0) -> 2 | ... O11: =IF('ProductSprint Backlog'!$L6>O$2,'ProductSprint Backlog'!$M6,0) -> 0
A13: Diseñar botón y flujo de “¿Olvidó su contraseña?”. | B13: =IF('ProductSprint Backlog'!$L8>B$2,'ProductSprint Backlog'!$M8,0) -> 1.5 | C13: =IF('ProductSprint Backlog'!$L8>C$2,'ProductSprint Backlog'!$M8,0) -> 1.5 | D13: =IF('ProductSprint Backlog'!$L8>D$2,'ProductSprint Backlog'!$M8,0) -> 1.5 | E13: =IF('ProductSprint Backlog'!$L8>E$2,'ProductSprint Backlog'!$M8,0) -> 1.5 | F13: =IF('ProductSprint Backlog'!$L8>F$2,'ProductSprint Backlog'!$M8,0) -> 1.5 | G13: =IF('ProductSprint Backlog'!$L8>G$2,'ProductSprint Backlog'!$M8,0) -> 1.5 | H13: =IF('ProductSprint Backlog'!$L8>H$2,'ProductSprint Backlog'!$M8,0) -> 0 | I13: =IF('ProductSprint Backlog'!$L8>I$2,'ProductSprint Backlog'!$M8,0) -> 0 | ... O13: =IF('ProductSprint Backlog'!$L8>O$2,'ProductSprint Backlog'!$M8,0) -> 0
A14: Implementar validación de existencia del correo electrónico. | B14: =IF('ProductSprint Backlog'!$L9>B$2,'ProductSprint Backlog'!$M9,0) -> 1 | C14: =IF('ProductSprint Backlog'!$L9>C$2,'ProductSprint Backlog'!$M9,0) -> 1 | D14: =IF('ProductSprint Backlog'!$L9>D$2,'ProductSprint Backlog'!$M9,0) -> 1 | E14: =IF('ProductSprint Backlog'!$L9>E$2,'ProductSprint Backlog'!$M9,0) -> 1 | F14: =IF('ProductSprint Backlog'!$L9>F$2,'ProductSprint Backlog'!$M9,0) -> 1 | G14: =IF('ProductSprint Backlog'!$L9>G$2,'ProductSprint Backlog'!$M9,0) -> 1 | H14: =IF('ProductSprint Backlog'!$L9>H$2,'ProductSprint Backlog'!$M9,0) -> 1 | I14: =IF('ProductSprint Backlog'!$L9>I$2,'ProductSprint Backlog'!$M9,0) -> 0 | ... O14: =IF('ProductSprint Backlog'!$L9>O$2,'ProductSprint Backlog'!$M9,0) -> 0
A15: Generar contraseña temporal de recuperación. | B15: =IF('ProductSprint Backlog'!$L10>B$2,'ProductSprint Backlog'!$M10,0) -> 3 | C15: =IF('ProductSprint Backlog'!$L10>C$2,'ProductSprint Backlog'!$M10,0) -> 3 | D15: =IF('ProductSprint Backlog'!$L10>D$2,'ProductSprint Backlog'!$M10,0) -> 3 | E15: =IF('ProductSprint Backlog'!$L10>E$2,'ProductSprint Backlog'!$M10,0) -> 3 | F15: =IF('ProductSprint Backlog'!$L10>F$2,'ProductSprint Backlog'!$M10,0) -> 3 | G15: =IF('ProductSprint Backlog'!$L10>G$2,'ProductSprint Backlog'!$M10,0) -> 3 | H15: =IF('ProductSprint Backlog'!$L10>H$2,'ProductSprint Backlog'!$M10,0) -> 3 | I15: =IF('ProductSprint Backlog'!$L10>I$2,'ProductSprint Backlog'!$M10,0) -> 0 | ... O15: =IF('ProductSprint Backlog'!$L10>O$2,'ProductSprint Backlog'!$M10,0) -> 0
A16: Enviar correo con la contraseña temporal. | B16: =IF('ProductSprint Backlog'!$L11>B$2,'ProductSprint Backlog'!$M11,0) -> 3 | C16: =IF('ProductSprint Backlog'!$L11>C$2,'ProductSprint Backlog'!$M11,0) -> 3 | D16: =IF('ProductSprint Backlog'!$L11>D$2,'ProductSprint Backlog'!$M11,0) -> 3 | E16: =IF('ProductSprint Backlog'!$L11>E$2,'ProductSprint Backlog'!$M11,0) -> 3 | F16: =IF('ProductSprint Backlog'!$L11>F$2,'ProductSprint Backlog'!$M11,0) -> 3 | G16: =IF('ProductSprint Backlog'!$L11>G$2,'ProductSprint Backlog'!$M11,0) -> 3 | H16: =IF('ProductSprint Backlog'!$L11>H$2,'ProductSprint Backlog'!$M11,0) -> 3 | I16: =IF('ProductSprint Backlog'!$L11>I$2,'ProductSprint Backlog'!$M11,0) -> 3 | ... O16: =IF('ProductSprint Backlog'!$L11>O$2,'ProductSprint Backlog'!$M11,0) -> 0
A17: Validar contraseña y permitir ingreso con nueva contraseña. | B17: =IF('ProductSprint Backlog'!$L12>B$2,'ProductSprint Backlog'!$M12,0) -> 2 | C17: =IF('ProductSprint Backlog'!$L12>C$2,'ProductSprint Backlog'!$M12,0) -> 2 | D17: =IF('ProductSprint Backlog'!$L12>D$2,'ProductSprint Backlog'!$M12,0) -> 2 | E17: =IF('ProductSprint Backlog'!$L12>E$2,'ProductSprint Backlog'!$M12,0) -> 2 | F17: =IF('ProductSprint Backlog'!$L12>F$2,'ProductSprint Backlog'!$M12,0) -> 2 | G17: =IF('ProductSprint Backlog'!$L12>G$2,'ProductSprint Backlog'!$M12,0) -> 2 | H17: =IF('ProductSprint Backlog'!$L12>H$2,'ProductSprint Backlog'!$M12,0) -> 2 | I17: =IF('ProductSprint Backlog'!$L12>I$2,'ProductSprint Backlog'!$M12,0) -> 2 | ... O17: =IF('ProductSprint Backlog'!$L12>O$2,'ProductSprint Backlog'!$M12,0) -> 0
A19: Registrar hora de inicio de sesión. | B19: =IF('ProductSprint Backlog'!$L14>B$2,'ProductSprint Backlog'!$M14,0) -> 1 | C19: =IF('ProductSprint Backlog'!$L14>C$2,'ProductSprint Backlog'!$M14,0) -> 1 | D19: =IF('ProductSprint Backlog'!$L14>D$2,'ProductSprint Backlog'!$M14,0) -> 1 | E19: =IF('ProductSprint Backlog'!$L14>E$2,'ProductSprint Backlog'!$M14,0) -> 1 | F19: =IF('ProductSprint Backlog'!$L14>F$2,'ProductSprint Backlog'!$M14,0) -> 1 | G19: =IF('ProductSprint Backlog'!$L14>G$2,'ProductSprint Backlog'!$M14,0) -> 1 | H19: =IF('ProductSprint Backlog'!$L14>H$2,'ProductSprint Backlog'!$M14,0) -> 1 | I19: =IF('ProductSprint Backlog'!$L14>I$2,'ProductSprint Backlog'!$M14,0) -> 1 | ... O19: =IF('ProductSprint Backlog'!$L14>O$2,'ProductSprint Backlog'!$M14,0) -> 0
A20: Implementar monitoreo de duración de sesión. | B20: =IF('ProductSprint Backlog'!$L15>B$2,'ProductSprint Backlog'!$M15,0) -> 4.5 | C20: =IF('ProductSprint Backlog'!$L15>C$2,'ProductSprint Backlog'!$M15,0) -> 4.5 | D20: =IF('ProductSprint Backlog'!$L15>D$2,'ProductSprint Backlog'!$M15,0) -> 4.5 | E20: =IF('ProductSprint Backlog'!$L15>E$2,'ProductSprint Backlog'!$M15,0) -> 4.5 | F20: =IF('ProductSprint Backlog'!$L15>F$2,'ProductSprint Backlog'!$M15,0) -> 4.5 | G20: =IF('ProductSprint Backlog'!$L15>G$2,'ProductSprint Backlog'!$M15,0) -> 4.5 | H20: =IF('ProductSprint Backlog'!$L15>H$2,'ProductSprint Backlog'!$M15,0) -> 4.5 | I20: =IF('ProductSprint Backlog'!$L15>I$2,'ProductSprint Backlog'!$M15,0) -> 4.5 | ... O20: =IF('ProductSprint Backlog'!$L15>O$2,'ProductSprint Backlog'!$M15,0) -> 0
A21: Forzar cierre de sesión a las 16 horas. | B21: =IF('ProductSprint Backlog'!$L16>B$2,'ProductSprint Backlog'!$M16,0) -> 2 | C21: =IF('ProductSprint Backlog'!$L16>C$2,'ProductSprint Backlog'!$M16,0) -> 2 | D21: =IF('ProductSprint Backlog'!$L16>D$2,'ProductSprint Backlog'!$M16,0) -> 2 | E21: =IF('ProductSprint Backlog'!$L16>E$2,'ProductSprint Backlog'!$M16,0) -> 2 | F21: =IF('ProductSprint Backlog'!$L16>F$2,'ProductSprint Backlog'!$M16,0) -> 2 | G21: =IF('ProductSprint Backlog'!$L16>G$2,'ProductSprint Backlog'!$M16,0) -> 2 | H21: =IF('ProductSprint Backlog'!$L16>H$2,'ProductSprint Backlog'!$M16,0) -> 2 | I21: =IF('ProductSprint Backlog'!$L16>I$2,'ProductSprint Backlog'!$M16,0) -> 2 | ... O21: =IF('ProductSprint Backlog'!$L16>O$2,'ProductSprint Backlog'!$M16,0) -> 0
